Workbook

Sheet RESUMEN
A1: IGF DIARIO SEMANAL · SAN LUIS
A2: SEMANA 41 · 04/10/2026–10/10/2026
A4: Concepto | B4: Semana | C4: Dom 04/10
A5: Venta en Kilos | B5: — | C5: —
A6: Precio de Venta al Público | B6: — | C6: —
A7: Ingreso Generado | B7: — | C7: —
A9: Costo del Gas LP | B9: — | C9: —
A10: Flete Terrestre | B10: — | C10: —
A11: Margen Bruto | B11: — | C11: —
A13: Gasto Corporativo | B13: — | C13: —
A14: Inversiones | B14: — | C14: —
A15: Impuestos Federales | B15: — | C15: —
A16: Margen Neto | B16: — | C16: —
A18: Presupuesto Nómina/Gastos | B18: — | C18: —
... A28: RESULTADO ($/kg) | B28: — | C28: —
A29: RESULTADO (Importe) | B29: 1 | C29: 1

Sheet DatosPlanta
C1: VENTA | D1: CASA | H1: COMISIONISTA | M1: PRECIO | P1: PEMEX TUXPAN | T1: TOMZA TUXPAN | W1: TOMZA TEPEJI | Z1: FLETE (TARIFA) | AD1: HG | AF1: DESCUENTOS
A2: Semana | B2: Fecha | C2: Venta Total (kg) | D2: Portátil (kg) | E2: Autotanque (kg) | F2: Carburación (kg) | G2: Total CASA (kg) | H2: Portátil (kg) | I2: Autotanque (kg) | J2: Carburación (kg) | K2: Total COMISIONISTA (kg) | M2: PRECIO ($/kg) | N2: Subsidio ($) | P2: COMPRA KG | Q2: COSTO KG | R2: CIRCULAR | T2: COMPRA KG | U2: COSTO KG | W2: COMPRA KG | X2: COSTO KG | Z2: PEMEX TUXPAN | AA2: TOMZA TUXPAN | AB2: TOMZA TEPEJI | AD2: HG Kilos | AF2: Descuento CASA ($) | AG2: Descuento COMISIONISTA ($)
A3: 40 | B3: 46296 | M3: =PRECIO!B2 -> 10.5 | Z3: 1.23
A4: 40 | B4: 46297 | M4: =PRECIO!B3 -> 10.5 | Z4: 1.23
A5: 40 | B5: 46298 | M5: =PRECIO!B4 -> 10.5 | Z5: 1.23
A6: 41 | B6: 46299 | M6: =PRECIO!B5 -> 10.5 | P6: 100 | Q6: 12 | Z6: 1.23 | AD6: -10 | AF6: -15.5 | AG6: 0
A7: 41 | B7: 46300 | M7: =PRECIO!B6 -> 10.5 | Z7: 1.23
A8: 41 | B8: 46301 | M8: =PRECIO!B7 -> 10.5 | Z8: 1.23
A9: 41 | B9: 46302 | M9: =PRECIO!B8 -> 10.5 | Z9: 1.23
A10: 41 | B10: 46303 | M10: =PRECIO!B9 -> 10.5 | Z10: 1.23
A11: 41 | B11: 46304 | M11: =PRECIO!B10 -> 10.5 | Z11: 1.23
A12: 41 | B12: 46305 | M12: =PRECIO!B11 -> 10.5 | Z12: 1.23
A13: 42 | B13: 46306 | M13: =PRECIO!B12 -> 10.5 | P13: 10 | Q13: 12 | Z13: 1.23 | AD13: -10
A14: 42 | B14: 46307 | M14: =PRECIO!B13 -> 10.5 | P14: 10 | Q14: 12 | Z14: 1.23 | AD14: -10
A15: 42 | B15: 46308 | M15: =PRECIO!B14 -> 10.5 | P15: 10 | Q15: 12 | Z15: 1.23 | AD15: -10
A16: 42 | B16: 46309 | M16: =PRECIO!B15 -> 10.5 | P16: 10 | Q16: 12 | Z16: 1.23 | AD16: -10
A17: 42 | B17: 46310 | M17: =PRECIO!B16 -> 10.5 | P17: 10 | Q17: 12 | Z17: 1.23 | AD17: -10
A18: 42 | B18: 46311 | M18: =PRECIO!B17 -> 10.5 | P18: 10 | Q18: 12 | Z18: 1.23 | AD18: -10
A19: 42 | B19: 46312 | M19: =PRECIO!B18 -> 10.5 | P19: 10 | Q19: 12 | Z19: 1.23 | AD19: -10
A20: 43 | B20: 46313 | M20: =PRECIO!B19 -> 10.5 | P20: 10 | Q20: 12 | Z20: 1.23 | AD20: -10
A21: 43 | B21: 46314 | M21: =PRECIO!B20 -> 10.5 | P21: 10 | Q21: 12 | Z21: 1.23 | AD21: -10
A22: 43 | B22: 46315 | M22: =PRECIO!B21 -> 10.5 | P22: 10 | Q22: 12 | Z22: 1.23 | AD22: -10
A23: 43 | B23: 46316 | M23: =PRECIO!B22 -> 10.5 | P23: 10 | Q23: 12 | Z23: 1.23 | AD23: -10
A24: 43 | B24: 46317 | M24: =PRECIO!B23 -> 10.5 | P24: 10 | Q24: 12 | Z24: 1.23 | AD24: -10
... A33: 44 | B33: 46326 | M33: =PRECIO!B32 -> 10.5 | P33: 10 | Q33: 12 | Z33: 1.23 | AD33: -10

Sheet IGF Diario San Luis
A1: IGF DIARIO | O1: 2026
A2: PLANTA SAN LUIS | O2: OCTUBRE
A4: FECHA | B4: VENTA E INGRESO | F4: COSTO DEL GAS (COSTO Y FLETE) | J4: GASTOS CORPORATIVOS | O4: MARGEN NETO | Q4: GASTOS OPERATIVOS | W4: SOBRANTE OPERACIÓN | Y4: HG | AB4: SOBRANTE OPERACIÓN | AD4: C&D | AF4: RESULTADO | AI4: COMENTARIO DEL DIA | AJ4: VENTAS | AK4: DESCUENTOS
B5: VENTA KG | C5: PRECIO | D5: INGRESO | F5: COSTO KG | G5: FLETE KG | H5: MARGEN BRUTO | J5: Gasto Corporativo | K5: Inversiones | L5: Impuestos Federales | M5: IMPORTE | O5: MARGEN NETO | Q5: Presupuesto Nómina/Gastos | R5: Presupuesto IMSS/SUA | S5: Extraordinarios | T5: Provisiones de la Planta | U5: IMPORTE | W5: SOBRANTE OPERACIÓN | Y5: IMPORTE HG | Z5: IMPORTE HG POR KG | AB5: SOBRANTE OPERACIÓN | AD5: C&D | AF5: RESULTADO POR KG | AG5: RESULTADO | AI5: COMENTARIO DEL DIA | AJ5: VENTAS | AK5: DESCUENTOS
A6: 46296 | B6: =IF(OR(ISNUMBER('Provincia Venta Diaria'!J2),ISNUMBER('Provincia Venta Diaria'!K2)),(IF(ISNUMBER('Provincia Venta Diaria'!J2),'Provincia Venta Diaria'!J2,0)+IF(ISNUMBER('Provincia Venta Diaria'!K2),'Provincia Venta Diaria'!K2,0))*1000,"") | C6: =IF(AND(ISNUMBER(PRECIO!B2),ISNUMBER(PRECIO!B2)),PRECIO!B2,"") | D6: =IF(AND(ISNUMBER(C6),ISNUMBER(B6)),C6*B6,"") | H6: =IF(AND(ISNUMBER(C6),ISNUMBER(F6),ISNUMBER(G6)),C6-F6-G6,"") | M6: =IF(AND(ISNUMBER($M$3),ISNUMBER(B6),B6<>0),($M$3/27)/B6,"") | O6: =IF(AND(ISNUMBER(H6),ISNUMBER(M6)),H6-M6,"") | U6: =IF(AND(ISNUMBER($U$3),ISNUMBER(B6),B6<>0),($U$3/27)/B6,"") | W6: =IF(AND(ISNUMBER(O6),ISNUMBER(U6)),O6-U6,"") | Z6: =IF(AND(ISNUMBER(Y6),ISNUMBER(B6),B6<>0),Y6/B6,"") | AB6: =IF(AND(ISNUMBER(W6),ISNUMBER(Z6)),W6-Z6,"") | AD6: =IF(AND(ISNUMBER('Provincia Comisiones'!B2),ISNUMBER('Provincia Comisiones'!B2)),'Provincia Comisiones'!B2,"") | AF6: =IF(AND(ISNUMBER(AB6),ISNUMBER(AD6)),AB6+AD6,"") | AG6: =IF(AND(ISNUMBER(AF6),ISNUMBER(B6)),AF6*B6,"")
A7: 46297 | B7: =IF(OR(ISNUMBER('Provincia Venta Diaria'!J3),ISNUMBER('Provincia Venta Diaria'!K3)),(IF(ISNUMBER('Provincia Venta Diaria'!J3),'Provincia Venta Diaria'!J3,0)+IF(ISNUMBER('Provincia Venta Diaria'!K3),'Provincia Venta Diaria'!K3,0))*1000,"") | C7: =IF(AND(ISNUMBER(PRECIO!B3),ISNUMBER(PRECIO!B3)),PRECIO!B3,"") | D7: =IF(AND(ISNUMBER(C7),ISNUMBER(B7)),C7*B7,"") | H7: =IF(AND(ISNUMBER(C7),ISNUMBER(F7),ISNUMBER(G7)),C7-F7-G7,"") | M7: =IF(AND(ISNUMBER($M$3),ISNUMBER(B7),B7<>0),($M$3/27)/B7,"") | O7: =IF(AND(ISNUMBER(H7),ISNUMBER(M7)),H7-M7,"") | U7: =IF(AND(ISNUMBER($U$3),ISNUMBER(B7),B7<>0),($U$3/27)/B7,"") | W7: =IF(AND(ISNUMBER(O7),ISNUMBER(U7)),O7-U7,"") | Z7: =IF(AND(ISNUMBER(Y7),ISNUMBER(B7),B7<>0),Y7/B7,"") | AB7: =IF(AND(ISNUMBER(W7),ISNUMBER(Z7)),W7-Z7,"") | AD7: =IF(AND(ISNUMBER('Provincia Comisiones'!B3),ISNUMBER('Provincia Comisiones'!B3)),'Provincia Comisiones'!B3,"") | AF7: =IF(AND(ISNUMBER(AB7),ISNUMBER(AD7)),AB7+AD7,"") | AG7: =IF(AND(ISNUMBER(AF7),ISNUMBER(B7)),AF7*B7,"")
A8: 46298 | B8: =IF(OR(ISNUMBER('Provincia Venta Diaria'!J4),ISNUMBER('Provincia Venta Diaria'!K4)),(IF(ISNUMBER('Provincia Venta Diaria'!J4),'Provincia Venta Diaria'!J4,0)+IF(ISNUMBER('Provincia Venta Diaria'!K4),'Provincia Venta Diaria'!K4,0))*1000,"") | C8: =IF(AND(ISNUMBER(PRECIO!B4),ISNUMBER(PRECIO!B4)),PRECIO!B4,"") | D8: =IF(AND(ISNUMBER(C8),ISNUMBER(B8)),C8*B8,"") | H8: =IF(AND(ISNUMBER(C8),ISNUMBER(F8),ISNUMBER(G8)),C8-F8-G8,"") | M8: =IF(AND(ISNUMBER($M$3),ISNUMBER(B8),B8<>0),($M$3/27)/B8,"") | O8: =IF(AND(ISNUMBER(H8),ISNUMBER(M8)),H8-M8,"") | U8: =IF(AND(ISNUMBER($U$3),ISNUMBER(B8),B8<>0),($U$3/27)/B8,"") | W8: =IF(AND(ISNUMBER(O8),ISNUMBER(U8)),O8-U8,"") | Z8: =IF(AND(ISNUMBER(Y8),ISNUMBER(B8),B8<>0),Y8/B8,"") | AB8: =IF(AND(ISNUMBER(W8),ISNUMBER(Z8)),W8-Z8,"") | AD8: =IF(AND(ISNUMBER('Provincia Comisiones'!B4),ISNUMBER('Provincia Comisiones'!B4)),'Provincia Comisiones'!B4,"") | AF8: =IF(AND(ISNUMBER(AB8),ISNUMBER(AD8)),AB8+AD8,"") | AG8: =IF(AND(ISNUMBER(AF8),ISNUMBER(B8)),AF8*B8,"")
A9: Semana 40 | B9: =IF(COUNT(B6:B8)=0,"",SUM(B6:B8)) | C9: =IF((IF(AND(ISNUMBER(C6),ISNUMBER(B6)),B6,0)+IF(AND(ISNUMBER(C7),ISNUMBER(B7)),B7,0)+IF(AND(ISNUMBER(C8),ISNUMBER(B8)),B8,0))=0,"",(IF(AND(ISNUMBER(C6),ISNUMBER(B6)),C6*B6,0)+IF(AND(ISNUMBER(C7),ISNUMBER(B7)),C7*B7,0)+IF(AND(ISNUMBER(C8),ISNUMBER(B8)),C8*B8,0))/(IF(AND(ISNUMBER(C6),ISNUMBER(B6)),B6,0)+IF(AND(ISNUMBER(C7),ISNUMBER(B7)),B7,0)+IF(AND(ISNUMBER(C8),ISNUMBER(B8)),B8,0))) | D9: =IF(COUNT(D6:D8)=0,"",SUM(D6:D8)) | F9: =IF((IF(AND(ISNUMBER(F6),ISNUMBER(B6)),B6,0)+IF(AND(ISNUMBER(F7),ISNUMBER(B7)),B7,0)+IF(AND(ISNUMBER(F8),ISNUMBER(B8)),B8,0))=0,"",(IF(AND(ISNUMBER(F6),ISNUMBER(B6)),F6*B6,0)+IF(AND(ISNUMBER(F7),ISNUMBER(B7)),F7*B7,0)+IF(AND(ISNUMBER(F8),ISNUMBER(B8)),F8*B8,0))/(IF(AND(ISNUMBER(F6),ISNUMBER(B6)),B6,0)+IF(AND(ISNUMBER(F7),ISNUMBER(B7)),B7,0)+IF(AND(ISNUMBER(F8),ISNUMBER(B8)),B8,0))) | G9: =IF((IF(AND(ISNUMBER(G6),ISNUMBER(B6)),B6,0)+IF(AND(ISNUMBER(G7),ISNUMBER(B7)),B7,0)+IF(AND(ISNUMBER(G8),ISNUMBER(B8)),B8,0))=0,"",(IF(AND(ISNUMBER(G6),ISNUMBER(B6)),G6*B6,0)+IF(AND(ISNUMBER(G7),ISNUMBER(B7)),G7*B7,0)+IF(AND(ISNUMBER(G8),ISNUMBER(B8)),G8*B8,0))/(IF(AND(ISNUMBER(G6),ISNUMBER(B6)),B6,0)+IF(AND(ISNUMBER(G7),ISNUMBER(B7)),B7,0)+IF(AND(ISNUMBER(G8),ISNUMBER(B8)),B8,0))) | H9: =IF((IF(AND(ISNUMBER(H6),ISNUMBER(B6)),B6,0)+IF(AND(ISNUMBER(H7),ISNUMBER(B7)),B7,0)+IF(AND(ISNUMBER(H8),ISNUMBER(B8)),B8,0))=0,"",(IF(AND(ISNUMBER(H6),ISNUMBER(B6)),H6*B6,0)+IF(AND(ISNUMBER(H7),ISNUMBER(B7)),H7*B7,0)+IF(AND(ISNUMBER(H8),ISNUMBER(B8)),H8*B8,0))/(IF(AND(ISNUMBER(H6),ISNUMBER(B6)),B6,0)+IF(AND(ISNUMBER(H7),ISNUMBER(B7)),B7,0)+IF(AND(ISNUMBER(H8),ISNUMBER(B8)),B8,0))) | M9: =IF((IF(AND(ISNUMBER(M6),ISNUMBER(B6)),B6,0)+IF(AND(ISNUMBER(M7),ISNUMBER(B7)),B7,0)+IF(AND(ISNUMBER(M8),ISNUMBER(B8)),B8,0))=0,"",(IF(AND(ISNUMBER(M6),ISNUMBER(B6)),M6*B6,0)+IF(AND(ISNUMBER(M7),ISNUMBER(B7)),M7*B7,0)+IF(AND(ISNUMBER(M8),ISNUMBER(B8)),M8*B8,0))/(IF(AND(ISNUMBER(M6),ISNUMBER(B6)),B6,0)+IF(AND(ISNUMBER(M7),ISNUMBER(B7)),B7,0)+IF(AND(ISNUMBER(M8),ISNUMBER(B8)),B8,0))) | O9: =IF((IF(AND(ISNUMBER(O6),ISNUMBER(B6)),B6,0)+IF(AND(ISNUMBER(O7),ISNUMBER(B7)),B7,0)+IF(AND(ISNUMBER(O8),ISNUMBER(B8)),B8,0))=0,"",(IF(AND(ISNUMBER(O6),ISNUMBER(B6)),O6*B6,0)+IF(AND(ISNUMBER(O7),ISNUMBER(B7)),O7*B7,0)+IF(AND(ISNUMBER(O8),ISNUMBER(B8)),O8*B8,0))/(IF(AND(ISNUMBER(O6),ISNUMBER(B6)),B6,0)+IF(AND(ISNUMBER(O7),ISNUMBER(B7)),B7,0)+IF(AND(ISNUMBER(O8),ISNUMBER(B8)),B8,0))) | U9: =IF((IF(AND(ISNUMBER(U6),ISNUMBER(B6)),B6,0)+IF(AND(ISNUMBER(U7),ISNUMBER(B7)),B7,0)+IF(AND(ISNUMBER(U8),ISNUMBER(B8)),B8,0))=0,"",(IF(AND(ISNUMBER(U6),ISNUMBER(B6)),U6*B6,0)+IF(AND(ISNUMBER(U7),ISNUMBER(B7)),U7*B7,0)+IF(AND(ISNUMBER(U8),ISNUMBER(B8)),U8*B8,0))/(IF(AND(ISNUMBER(U6),ISNUMBER(B6)),B6,0)+IF(AND(ISNUMBER(U7),ISNUMBER(B7)),B7,0)+IF(AND(ISNUMBER(U8),ISNUMBER(B8)),B8,0))) | W9: =IF((IF(AND(ISNUMBER(W6),ISNUMBER(B6)),B6,0)+IF(AND(ISNUMBER(W7),ISNUMBER(B7)),B7,0)+IF(AND(ISNUMBER(W8),ISNUMBER(B8)),B8,0))=0,"",(IF(AND(ISNUMBER(W6),ISNUMBER(B6)),W6*B6,0)+IF(AND(ISNUMBER(W7),ISNUMBER(B7)),W7*B7,0)+IF(AND(ISNUMBER(W8),ISNUMBER(B8)),W8*B8,0))/(IF(AND(ISNUMBER(W6),ISNUMBER(B6)),B6,0)+IF(AND(ISNUMBER(W7),ISNUMBER(B7)),B7,0)+IF(AND(ISNUMBER(W8),ISNUMBER(B8)),B8,0))) | Y9: =IF(COUNT(Y6:Y8)=0,"",SUM(Y6:Y8)) | Z9: =IF((IF(AND(ISNUMBER(Z6),ISNUMBER(B6)),B6,0)+IF(AND(ISNUMBER(Z7),ISNUMBER(B7)),B7,0)+IF(AND(ISNUMBER(Z8),ISNUMBER(B8)),B8,0))=0,"",(IF(AND(ISNUMBER(Z6),ISNUMBER(B6)),Z6*B6,0)+IF(AND(ISNUMBER(Z7),ISNUMBER(B7)),Z7*B7,0)+IF(AND(ISNUMBER(Z8),ISNUMBER(B8)),Z8*B8,0))/(IF(AND(ISNUMBER(Z6),ISNUMBER(B6)),B6,0)+IF(AND(ISNUMBER(Z7),ISNUMBER(B7)),B7,0)+IF(AND(ISNUMBER(Z8),ISNUMBER(B8)),B8,0))) | AB9: =IF((IF(AND(ISNUMBER(AB6),ISNUMBER(B6)),B6,0)+IF(AND(ISNUMBER(AB7),ISNUMBER(B7)),B7,0)+IF(AND(ISNUMBER(AB8),ISNUMBER(B8)),B8,0))=0,"",(IF(AND(ISNUMBER(AB6),ISNUMBER(B6)),AB6*B6,0)+IF(AND(ISNUMBER(AB7),ISNUMBER(B7)),AB7*B7,0)+IF(AND(ISNUMBER(AB8),ISNUMBER(B8)),AB8*B8,0))/(IF(AND(ISNUMBER(AB6),ISNUMBER(B6)),B6,0)+IF(AND(ISNUMBER(AB7),ISNUMBER(B7)),B7,0)+IF(AND(ISNUMBER(AB8),ISNUMBER(B8)),B8,0))) | AD9: =IF((IF(AND(ISNUMBER(AD6),ISNUMBER(B6)),B6,0)+IF(AND(ISNUMBER(AD7),ISNUMBER(B7)),B7,0)+IF(AND(ISNUMBER(AD8),ISNUMBER(B8)),B8,0))=0,"",(IF(AND(ISNUMBER(AD6),ISNUMBER(B6)),AD6*B6,0)+IF(AND(ISNUMBER(AD7),ISNUMBER(B7)),AD7*B7,0)+IF(AND(ISNUMBER(AD8),ISNUMBER(B8)),AD8*B8,0))/(IF(AND(ISNUMBER(AD6),ISNUMBER(B6)),B6,0)+IF(AND(ISNUMBER(AD7),ISNUMBER(B7)),B7,0)+IF(AND(ISNUMBER(AD8),ISNUMBER(B8)),B8,0))) | AF9: =IF(OR(NOT(ISNUMBER(B9)),B9=0),"",AG9/B9) | AG9: =IF(COUNT(AG6:AG8)=0,"",SUM(AG6:AG8))
A11: 46299 | B11: =IF(OR(ISNUMBER('Provincia Venta Diaria'!J5),ISNUMBER('Provincia Venta Diaria'!K5)),(IF(ISNUMBER('Provincia Venta Diaria'!J5),'Provincia Venta Diaria'!J5,0)+IF(ISNUMBER('Provincia Venta Diaria'!K5),'Provincia Venta Diaria'!K5,0))*1000,"") | C11: =IF(AND(ISNUMBER(PRECIO!B5),ISNUMBER(PRECIO!B5)),PRECIO!B5,"") | D11: =IF(AND(ISNUMBER(C11),ISNUMBER(B11)),C11*B11,"") | H11: =IF(AND(ISNUMBER(C11),ISNUMBER(F11),ISNUMBER(G11)),C11-F11-G11,"") | O11: =IF(ISNUMBER(H11),H11,"") | W11: =IF(ISNUMBER(O11),O11,"") | Z11: =IF(AND(ISNUMBER(Y11),ISNUMBER(B11),B11<>0),Y11/B11,"") | AB11: =IF(AND(ISNUMBER(W11),ISNUMBER(Z11)),W11-Z11,"") | AD11: =IF(AND(ISNUMBER('Provincia Comisiones'!B5),ISNUMBER('Provincia Comisiones'!B5)),'Provincia Comisiones'!B5,"") | AF11: =IF(AND(ISNUMBER(AB11),ISNUMBER(AD11)),AB11+AD11,"") | AG11: =IF(AND(ISNUMBER(AF11),ISNUMBER(B11)),AF11*B11,"")
A12: 46300 | B12: =IF(OR(ISNUMBER('Provincia Venta Diaria'!J6),ISNUMBER('Provincia Venta Diaria'!K6)),(IF(ISNUMBER('Provincia Venta Diaria'!J6),'Provincia Venta Diaria'!J6,0)+IF(ISNUMBER('Provincia Venta Diaria'!K6),'Provincia Venta Diaria'!K6,0))*1000,"") | C12: =IF(AND(ISNUMBER(PRECIO!B6),ISNUMBER(PRECIO!B6)),PRECIO!B6,"") | D12: =IF(AND(ISNUMBER(C12),ISNUMBER(B12)),C12*B12,"") | H12: =IF(AND(ISNUMBER(C12),ISNUMBER(F12),ISNUMBER(G12)),C12-F12-G12,"") | M12: =IF(AND(ISNUMBER($M$3),ISNUMBER(B12),B12<>0),($M$3/27)/B12,"") | O12: =IF(AND(ISNUMBER(H12),ISNUMBER(M12)),H12-M12,"") | U12: =IF(AND(ISNUMBER($U$3),ISNUMBER(B12),B12<>0),($U$3/27)/B12,"") | W12: =IF(AND(ISNUMBER(O12),ISNUMBER(U12)),O12-U12,"") | Z12: =IF(AND(ISNUMBER(Y12),ISNUMBER(B12),B12<>0),Y12/B12,"") | AB12: =IF(AND(ISNUMBER(W12),ISNUMBER(Z12)),W12-Z12,"") | AD12: =IF(AND(ISNUMBER('Provincia Comisiones'!B6),ISNUMBER('Provincia Comisiones'!B6)),'Provincia Comisiones'!B6,"") | AF12: =IF(AND(ISNUMBER(AB12),ISNUMBER(AD12)),AB12+AD12,"") | AG12: =IF(AND(ISNUMBER(AF12),ISNUMBER(B12)),AF12*B12,"")
A13: 46301 | B13: =IF(OR(ISNUMBER('Provincia Venta Diaria'!J7),ISNUMBER('Provincia Venta Diaria'!K7)),(IF(ISNUMBER('Provincia Venta Diaria'!J7),'Provincia Venta Diaria'!J7,0)+IF(ISNUMBER('Provincia Venta Diaria'!K7),'Provincia Venta Diaria'!K7,0))*1000,"") | C13: =IF(AND(ISNUMBER(PRECIO!B7),ISNUMBER(PRECIO!B7)),PRECIO!B7,"") | D13: =IF(AND(ISNUMBER(C13),ISNUMBER(B13)),C13*B13,"") | H13: =IF(AND(ISNUMBER(C13),ISNUMBER(F13),ISNUMBER(G13)),C13-F13-G13,"") | M13: =IF(AND(ISNUMBER($M$3),ISNUMBER(B13),B13<>0),($M$3/27)/B13,"") | O13: =IF(AND(ISNUMBER(H13),ISNUMBER(M13)),H13-M13,"") | U13: =IF(AND(ISNUMBER($U$3),ISNUMBER(B13),B13<>0),($U$3/27)/B13,"") | W13: =IF(AND(ISNUMBER(O13),ISNUMBER(U13)),O13-U13,"") | Z13: =IF(AND(ISNUMBER(Y13),ISNUMBER(B13),B13<>0),Y13/B13,"") | AB13: =IF(AND(ISNUMBER(W13),ISNUMBER(Z13)),W13-Z13,"") | AD13: =IF(AND(ISNUMBER('Provincia Comisiones'!B7),ISNUMBER('Provincia Comisiones'!B7)),'Provincia Comisiones'!B7,"") | AF13: =IF(AND(ISNUMBER(AB13),ISNUMBER(AD13)),AB13+AD13,"") | AG13: =IF(AND(ISNUMBER(AF13),ISNUMBER(B13)),AF13*B13,"")
A14: 46302 | B14: =IF(OR(ISNUMBER('Provincia Venta Diaria'!J8),ISNUMBER('Provincia Venta Diaria'!K8)),(IF(ISNUMBER('Provincia Venta Diaria'!J8),'Provincia Venta Diaria'!J8,0)+IF(ISNUMBER('Provincia Venta Diaria'!K8),'Provincia Venta Diaria'!K8,0))*1000,"") | C14: =IF(AND(ISNUMBER(PRECIO!B8),ISNUMBER(PRECIO!B8)),PRECIO!B8,"") | D14: =IF(AND(ISNUMBER(C14),ISNUMBER(B14)),C14*B14,"") | H14: =IF(AND(ISNUMBER(C14),ISNUMBER(F14),ISNUMBER(G14)),C14-F14-G14,"") | M14: =IF(AND(ISNUMBER($M$3),ISNUMBER(B14),B14<>0),($M$3/27)/B14,"") | O14: =IF(AND(ISNUMBER(H14),ISNUMBER(M14)),H14-M14,"") | U14: =IF(AND(ISNUMBER($U$3),ISNUMBER(B14),B14<>0),($U$3/27)/B14,"") | W14: =IF(AND(ISNUMBER(O14),ISNUMBER(U14)),O14-U14,"") | Z14: =IF(AND(ISNUMBER(Y14),ISNUMBER(B14),B14<>0),Y14/B14,"") | AB14: =IF(AND(ISNUMBER(W14),ISNUMBER(Z14)),W14-Z14,"") | AD14: =IF(AND(ISNUMBER('Provincia Comisiones'!B8),ISNUMBER('Provincia Comisiones'!B8)),'Provincia Comisiones'!B8,"") | AF14: =IF(AND(ISNUMBER(AB14),ISNUMBER(AD14)),AB14+AD14,"") | AG14: =IF(AND(ISNUMBER(AF14),ISNUMBER(B14)),AF14*B14,"")
A15: 46303 | B15: =IF(OR(ISNUMBER('Provincia Venta Diaria'!J9),ISNUMBER('Provincia Venta Diaria'!K9)),(IF(ISNUMBER('Provincia Venta Diaria'!J9),'Provincia Venta Diaria'!J9,0)+IF(ISNUMBER('Provincia Venta Diaria'!K9),'Provincia Venta Diaria'!K9,0))*1000,"") | C15: =IF(AND(ISNUMBER(PRECIO!B9),ISNUMBER(PRECIO!B9)),PRECIO!B9,"") | D15: =IF(AND(ISNUMBER(C15),ISNUMBER(B15)),C15*B15,"") | H15: =IF(AND(ISNUMBER(C15),ISNUMBER(F15),ISNUMBER(G15)),C15-F15-G15,"") | M15: =IF(AND(ISNUMBER($M$3),ISNUMBER(B15),B15<>0),($M$3/27)/B15,"") | O15: =IF(AND(ISNUMBER(H15),ISNUMBER(M15)),H15-M15,"") | U15: =IF(AND(ISNUMBER($U$3),ISNUMBER(B15),B15<>0),($U$3/27)/B15,"") | W15: =IF(AND(ISNUMBER(O15),ISNUMBER(U15)),O15-U15,"") | Z15: =IF(AND(ISNUMBER(Y15),ISNUMBER(B15),B15<>0),Y15/B15,"") | AB15: =IF(AND(ISNUMBER(W15),ISNUMBER(Z15)),W15-Z15,"") | AD15: =IF(AND(ISNUMBER('Provincia Comisiones'!B9),ISNUMBER('Provincia Comisiones'!B9)),'Provincia Comisiones'!B9,"") | AF15: =IF(AND(ISNUMBER(AB15),ISNUMBER(AD15)),AB15+AD15,"") | AG15: =IF(AND(ISNUMBER(AF15),ISNUMBER(B15)),AF15*B15,"")
A16: 46304 | B16: =IF(OR(ISNUMBER('Provincia Venta Diaria'!J10),ISNUMBER('Provincia Venta Diaria'!K10)),(IF(ISNUMBER('Provincia Venta Diaria'!J10),'Provincia Venta Diaria'!J10,0)+IF(ISNUMBER('Provincia Venta Diaria'!K10),'Provincia Venta Diaria'!K10,0))*1000,"") | C16: =IF(AND(ISNUMBER(PRECIO!B10),ISNUMBER(PRECIO!B10)),PRECIO!B10,"") | D16: =IF(AND(ISNUMBER(C16),ISNUMBER(B16)),C16*B16,"") | H16: =IF(AND(ISNUMBER(C16),ISNUMBER(F16),ISNUMBER(G16)),C16-F16-G16,"") | M16: =IF(AND(ISNUMBER($M$3),ISNUMBER(B16),B16<>0),($M$3/27)/B16,"") | O16: =IF(AND(ISNUMBER(H16),ISNUMBER(M16)),H16-M16,"") | U16: =IF(AND(ISNUMBER($U$3),ISNUMBER(B16),B16<>0),($U$3/27)/B16,"") | W16: =IF(AND(ISNUMBER(O16),ISNUMBER(U16)),O16-U16,"") | Z16: =IF(AND(ISNUMBER(Y16),ISNUMBER(B16),B16<>0),Y16/B16,"") | AB16: =IF(AND(ISNUMBER(W16),ISNUMBER(Z16)),W16-Z16,"") | AD16: =IF(AND(ISNUMBER('Provincia Comisiones'!B10),ISNUMBER('Provincia Comisiones'!B10)),'Provincia Comisiones'!B10,"") | AF16: =IF(AND(ISNUMBER(AB16),ISNUMBER(AD16)),AB16+AD16,"") | AG16: =IF(AND(ISNUMBER(AF16),ISNUMBER(B16)),AF16*B16,"")
A17: 46305 | B17: =IF(OR(ISNUMBER('Provincia Venta Diaria'!J11),ISNUMBER('Provincia Venta Diaria'!K11)),(IF(ISNUMBER('Provincia Venta Diaria'!J11),'Provincia Venta Diaria'!J11,0)+IF(ISNUMBER('Provincia Venta Diaria'!K11),'Provincia Venta Diaria'!K11,0))*1000,"") | C17: =IF(AND(ISNUMBER(PRECIO!B11),ISNUMBER(PRECIO!B11)),PRECIO!B11,"") | D17: =IF(AND(ISNUMBER(C17),ISNUMBER(B17)),C17*B17,"") | H17: =IF(AND(ISNUMBER(C17),ISNUMBER(F17),ISNUMBER(G17)),C17-F17-G17,"") | M17: =IF(AND(ISNUMBER($M$3),ISNUMBER(B17),B17<>0),($M$3/27)/B17,"") | O17: =IF(AND(ISNUMBER(H17),ISNUMBER(M17)),H17-M17,"") | U17: =IF(AND(ISNUMBER($U$3),ISNUMBER(B17),B17<>0),($U$3/27)/B17,"") | W17: =IF(AND(ISNUMBER(O17),ISNUMBER(U17)),O17-U17,"") | Z17: =IF(AND(ISNUMBER(Y17),ISNUMBER(B17),B17<>0),Y17/B17,"") | AB17: =IF(AND(ISNUMBER(W17),ISNUMBER(Z17)),W17-Z17,"") | AD17: =IF(AND(ISNUMBER('Provincia Comisiones'!B11),ISNUMBER('Provincia Comisiones'!B11)),'Provincia Comisiones'!B11,"") | AF17: =IF(AND(ISNUMBER(AB17),ISNUMBER(AD17)),AB17+AD17,"") | AG17: =IF(AND(ISNUMBER(AF17),ISNUMBER(B17)),AF17*B17,"")
A18: Semana 41 | B18: =IF(COUNT(B11:B17)=0,"",SUM(B11:B17)) | C18: =IF((IF(AND(ISNUMBER(C11),ISNUMBER(B11)),B11,0)+IF(AND(ISNUMBER(C12),ISNUMBER(B12)),B12,0)+IF(AND(ISNUMBER(C13),ISNUMBER(B13)),B13,0)+IF(AND(ISNUMBER(C14),ISNUMBER(B14)),B14,0)+IF(AND(ISNUMBER(C15),ISNUMBER(B15)),B15,0)+IF(AND(ISNUMBER(C16),ISNUMBER(B16)),B16,0)+IF(AND(ISNUMBER(C17),ISNUMBER(B17)),B17,0))=0,"",(IF(AND(ISNUMBER(C11),ISNUMBER(B11)),C11*B11,0)+IF(AND(ISNUMBER(C12),ISNUMBER(B12)),C12*B12,0)+IF(AND(ISNUMBER(C13),ISNUMBER(B13)),C13*B13,0)+IF(AND(ISNUMBER(C14),ISNUMBER(B14)),C14*B14,0)+IF(AND(ISNUMBER(C15),ISNUMBER(B15)),C15*B15,0)+IF(AND(ISNUMBER(C16),ISNUMBER(B16)),C16*B16,0)+IF(AND(ISNUMBER(C17),ISNUMBER(B17)),C17*B17,0))/(IF(AND(ISNUMBER(C11),ISNUMBER(B11)),B11,0)+IF(AND(ISNUMBER(C12),ISNUMBER(B12)),B12,0)+IF(AND(ISNUMBER(C13),ISNUMBER(B13)),B13,0)+IF(AND(ISNUMBER(C14),ISNUMBER(B14)),B14,0)+IF(AND(ISNUMBER(C15),ISNUMBER(B15)),B15,0)+IF(AND(ISNUMBER(C16),ISNUMBER(B16)),B16,0)+IF(AND(ISNUMBER(C17),ISNUMBER(B17)),B17,0))) | D18: =IF(COUNT(D11:D17)=0,"",SUM(D11:D17)) | F18: =IF((IF(AND(ISNUMBER(F11),ISNUMBER(B11)),B11,0)+IF(AND(ISNUMBER(F12),ISNUMBER(B12)),B12,0)+IF(AND(ISNUMBER(F13),ISNUMBER(B13)),B13,0)+IF(AND(ISNUMBER(F14),ISNUMBER(B14)),B14,0)+IF(AND(ISNUMBER(F15),ISNUMBER(B15)),B15,0)+IF(AND(ISNUMBER(F16),ISNUMBER(B16)),B16,0)+IF(AND(ISNUMBER(F17),ISNUMBER(B17)),B17,0))=0,"",(IF(AND(ISNUMBER(F11),ISNUMBER(B11)),F11*B11,0)+IF(AND(ISNUMBER(F12),ISNUMBER(B12)),F12*B12,0)+IF(AND(ISNUMBER(F13),ISNUMBER(B13)),F13*B13,0)+IF(AND(ISNUMBER(F14),ISNUMBER(B14)),F14*B14,0)+IF(AND(ISNUMBER(F15),ISNUMBER(B15)),F15*B15,0)+IF(AND(ISNUMBER(F16),ISNUMBER(B16)),F16*B16,0)+IF(AND(ISNUMBER(F17),ISNUMBER(B17)),F17*B17,0))/(IF(AND(ISNUMBER(F11),ISNUMBER(B11)),B11,0)+IF(AND(ISNUMBER(F12),ISNUMBER(B12)),B12,0)+IF(AND(ISNUMBER(F13),ISNUMBER(B13)),B13,0)+IF(AND(ISNUMBER(F14),ISNUMBER(B14)),B14,0)+IF(AND(ISNUMBER(F15),ISNUMBER(B15)),B15,0)+IF(AND(ISNUMBER(F16),ISNUMBER(B16)),B16,0)+IF(AND(ISNUMBER(F17),ISNUMBER(B17)),B17,0))) | G18: =IF((IF(AND(ISNUMBER(G11),ISNUMBER(B11)),B11,0)+IF(AND(ISNUMBER(G12),ISNUMBER(B12)),B12,0)+IF(AND(ISNUMBER(G13),ISNUMBER(B13)),B13,0)+IF(AND(ISNUMBER(G14),ISNUMBER(B14)),B14,0)+IF(AND(ISNUMBER(G15),ISNUMBER(B15)),B15,0)+IF(AND(ISNUMBER(G16),ISNUMBER(B16)),B16,0)+IF(AND(ISNUMBER(G17),ISNUMBER(B17)),B17,0))=0,"",(IF(AND(ISNUMBER(G11),ISNUMBER(B11)),G11*B11,0)+IF(AND(ISNUMBER(G12),ISNUMBER(B12)),G12*B12,0)+IF(AND(ISNUMBER(G13),ISNUMBER(B13)),G13*B13,0)+IF(AND(ISNUMBER(G14),ISNUMBER(B14)),G14*B14,0)+IF(AND(ISNUMBER(G15),ISNUMBER(B15)),G15*B15,0)+IF(AND(ISNUMBER(G16),ISNUMBER(B16)),G16*B16,0)+IF(AND(ISNUMBER(G17),ISNUMBER(B17)),G17*B17,0))/(IF(AND(ISNUMBER(G11),ISNUMBER(B11)),B11,0)+IF(AND(ISNUMBER(G12),ISNUMBER(B12)),B12,0)+IF(AND(ISNUMBER(G13),ISNUMBER(B13)),B13,0)+IF(AND(ISNUMBER(G14),ISNUMBER(B14)),B14,0)+IF(AND(ISNUMBER(G15),ISNUMBER(B15)),B15,0)+IF(AND(ISNUMBER(G16),ISNUMBER(B16)),B16,0)+IF(AND(ISNUMBER(G17),ISNUMBER(B17)),B17,0))) | H18: =IF((IF(AND(ISNUMBER(H11),ISNUMBER(B11)),B11,0)+IF(AND(ISNUMBER(H12),ISNUMBER(B12)),B12,0)+IF(AND(ISNUMBER(H13),ISNUMBER(B13)),B13,0)+IF(AND(ISNUMBER(H14),ISNUMBER(B14)),B14,0)+IF(AND(ISNUMBER(H15),ISNUMBER(B15)),B15,0)+IF(AND(ISNUMBER(H16),ISNUMBER(B16)),B16,0)+IF(AND(ISNUMBER(H17),ISNUMBER(B17)),B17,0))=0,"",(IF(AND(ISNUMBER(H11),ISNUMBER(B11)),H11*B11,0)+IF(AND(ISNUMBER(H12),ISNUMBER(B12)),H12*B12,0)+IF(AND(ISNUMBER(H13),ISNUMBER(B13)),H13*B13,0)+IF(AND(ISNUMBER(H14),ISNUMBER(B14)),H14*B14,0)+IF(AND(ISNUMBER(H15),ISNUMBER(B15)),H15*B15,0)+IF(AND(ISNUMBER(H16),ISNUMBER(B16)),H16*B16,0)+IF(AND(ISNUMBER(H17),ISNUMBER(B17)),H17*B17,0))/(IF(AND(ISNUMBER(H11),ISNUMBER(B11)),B11,0)+IF(AND(ISNUMBER(H12),ISNUMBER(B12)),B12,0)+IF(AND(ISNUMBER(H13),ISNUMBER(B13)),B13,0)+IF(AND(ISNUMBER(H14),ISNUMBER(B14)),B14,0)+IF(AND(ISNUMBER(H15),ISNUMBER(B15)),B15,0)+IF(AND(ISNUMBER(H16),ISNUMBER(B16)),B16,0)+IF(AND(ISNUMBER(H17),ISNUMBER(B17)),B17,0))) | M18: =IF((IF(AND(ISNUMBER(M11),ISNUMBER(B11)),B11,0)+IF(AND(ISNUMBER(M12),ISNUMBER(B12)),B12,0)+IF(AND(ISNUMBER(M13),ISNUMBER(B13)),B13,0)+IF(AND(ISNUMBER(M14),ISNUMBER(B14)),B14,0)+IF(AND(ISNUMBER(M15),ISNUMBER(B15)),B15,0)+IF(AND(ISNUMBER(M16),ISNUMBER(B16)),B16,0)+IF(AND(ISNUMBER(M17),ISNUMBER(B17)),B17,0))=0,"",(IF(AND(ISNUMBER(M11),ISNUMBER(B11)),M11*B11,0)+IF(AND(ISNUMBER(M12),ISNUMBER(B12)),M12*B12,0)+IF(AND(ISNUMBER(M13),ISNUMBER(B13)),M13*B13,0)+IF(AND(ISNUMBER(M14),ISNUMBER(B14)),M14*B14,0)+IF(AND(ISNUMBER(M15),ISNUMBER(B15)),M15*B15,0)+IF(AND(ISNUMBER(M16),ISNUMBER(B16)),M16*B16,0)+IF(AND(ISNUMBER(M17),ISNUMBER(B17)),M17*B17,0))/(IF(AND(ISNUMBER(M11),ISNUMBER(B11)),B11,0)+IF(AND(ISNUMBER(M12),ISNUMBER(B12)),B12,0)+IF(AND(ISNUMBER(M13),ISNUMBER(B13)),B13,0)+IF(AND(ISNUMBER(M14),ISNUMBER(B14)),B14,0)+IF(AND(ISNUMBER(M15),ISNUMBER(B15)),B15,0)+IF(AND(ISNUMBER(M16),ISNUMBER(B16)),B16,0)+IF(AND(ISNUMBER(M17),ISNUMBER(B17)),B17,0))) | O18: =IF((IF(AND(ISNUMBER(O11),ISNUMBER(B11)),B11,0)+IF(AND(ISNUMBER(O12),ISNUMBER(B12)),B12,0)+IF(AND(ISNUMBER(O13),ISNUMBER(B13)),B13,0)+IF(AND(ISNUMBER(O14),ISNUMBER(B14)),B14,0)+IF(AND(ISNUMBER(O15),ISNUMBER(B15)),B15,0)+IF(AND(ISNUMBER(O16),ISNUMBER(B16)),B16,0)+IF(AND(ISNUMBER(O17),ISNUMBER(B17)),B17,0))=0,"",(IF(AND(ISNUMBER(O11),ISNUMBER(B11)),O11*B11,0)+IF(AND(ISNUMBER(O12),ISNUMBER(B12)),O12*B12,0)+IF(AND(ISNUMBER(O13),ISNUMBER(B13)),O13*B13,0)+IF(AND(ISNUMBER(O14),ISNUMBER(B14)),O14*B14,0)+IF(AND(ISNUMBER(O15),ISNUMBER(B15)),O15*B15,0)+IF(AND(ISNUMBER(O16),ISNUMBER(B16)),O16*B16,0)+IF(AND(ISNUMBER(O17),ISNUMBER(B17)),O17*B17,0))/(IF(AND(ISNUMBER(O11),ISNUMBER(B11)),B11,0)+IF(AND(ISNUMBER(O12),ISNUMBER(B12)),B12,0)+IF(AND(ISNUMBER(O13),ISNUMBER(B13)),B13,0)+IF(AND(ISNUMBER(O14),ISNUMBER(B14)),B14,0)+IF(AND(ISNUMBER(O15),ISNUMBER(B15)),B15,0)+IF(AND(ISNUMBER(O16),ISNUMBER(B16)),B16,0)+IF(AND(ISNUMBER(O17),ISNUMBER(B17)),B17,0))) | U18: =IF((IF(AND(ISNUMBER(U11),ISNUMBER(B11)),B11,0)+IF(AND(ISNUMBER(U12),ISNUMBER(B12)),B12,0)+IF(AND(ISNUMBER(U13),ISNUMBER(B13)),B13,0)+IF(AND(ISNUMBER(U14),ISNUMBER(B14)),B14,0)+IF(AND(ISNUMBER(U15),ISNUMBER(B15)),B15,0)+IF(AND(ISNUMBER(U16),ISNUMBER(B16)),B16,0)+IF(AND(ISNUMBER(U17),ISNUMBER(B17)),B17,0))=0,"",(IF(AND(ISNUMBER(U11),ISNUMBER(B11)),U11*B11,0)+IF(AND(ISNUMBER(U12),ISNUMBER(B12)),U12*B12,0)+IF(AND(ISNUMBER(U13),ISNUMBER(B13)),U13*B13,0)+IF(AND(ISNUMBER(U14),ISNUMBER(B14)),U14*B14,0)+IF(AND(ISNUMBER(U15),ISNUMBER(B15)),U15*B15,0)+IF(AND(ISNUMBER(U16),ISNUMBER(B16)),U16*B16,0)+IF(AND(ISNUMBER(U17),ISNUMBER(B17)),U17*B17,0))/(IF(AND(ISNUMBER(U11),ISNUMBER(B11)),B11,0)+IF(AND(ISNUMBER(U12),ISNUMBER(B12)),B12,0)+IF(AND(ISNUMBER(U13),ISNUMBER(B13)),B13,0)+IF(AND(ISNUMBER(U14),ISNUMBER(B14)),B14,0)+IF(AND(ISNUMBER(U15),ISNUMBER(B15)),B15,0)+IF(AND(ISNUMBER(U16),ISNUMBER(B16)),B16,0)+IF(AND(ISNUMBER(U17),ISNUMBER(B17)),B17,0))) | W18: =IF((IF(AND(ISNUMBER(W11),ISNUMBER(B11)),B11,0)+IF(AND(ISNUMBER(W12),ISNUMBER(B12)),B12,0)+IF(AND(ISNUMBER(W13),ISNUMBER(B13)),B13,0)+IF(AND(ISNUMBER(W14),ISNUMBER(B14)),B14,0)+IF(AND(ISNUMBER(W15),ISNUMBER(B15)),B15,0)+IF(AND(ISNUMBER(W16),ISNUMBER(B16)),B16,0)+IF(AND(ISNUMBER(W17),ISNUMBER(B17)),B17,0))=0,"",(IF(AND(ISNUMBER(W11),ISNUMBER(B11)),W11*B11,0)+IF(AND(ISNUMBER(W12),ISNUMBER(B12)),W12*B12,0)+IF(AND(ISNUMBER(W13),ISNUMBER(B13)),W13*B13,0)+IF(AND(ISNUMBER(W14),ISNUMBER(B14)),W14*B14,0)+IF(AND(ISNUMBER(W15),ISNUMBER(B15)),W15*B15,0)+IF(AND(ISNUMBER(W16),ISNUMBER(B16)),W16*B16,0)+IF(AND(ISNUMBER(W17),ISNUMBER(B17)),W17*B17,0))/(IF(AND(ISNUMBER(W11),ISNUMBER(B11)),B11,0)+IF(AND(ISNUMBER(W12),ISNUMBER(B12)),B12,0)+IF(AND(ISNUMBER(W13),ISNUMBER(B13)),B13,0)+IF(AND(ISNUMBER(W14),ISNUMBER(B14)),B14,0)+IF(AND(ISNUMBER(W15),ISNUMBER(B15)),B15,0)+IF(AND(ISNUMBER(W16),ISNUMBER(B16)),B16,0)+IF(AND(ISNUMBER(W17),ISNUMBER(B17)),B17,0))) | Y18: =IF(COUNT(Y11:Y17)=0,"",SUM(Y11:Y17)) | Z18: =IF((IF(AND(ISNUMBER(Z11),ISNUMBER(B11)),B11,0)+IF(AND(ISNUMBER(Z12),ISNUMBER(B12)),B12,0)+IF(AND(ISNUMBER(Z13),ISNUMBER(B13)),B13,0)+IF(AND(ISNUMBER(Z14),ISNUMBER(B14)),B14,0)+IF(AND(ISNUMBER(Z15),ISNUMBER(B15)),B15,0)+IF(AND(ISNUMBER(Z16),ISNUMBER(B16)),B16,0)+IF(AND(ISNUMBER(Z17),ISNUMBER(B17)),B17,0))=0,"",(IF(AND(ISNUMBER(Z11),ISNUMBER(B11)),Z11*B11,0)+IF(AND(ISNUMBER(Z12),ISNUMBER(B12)),Z12*B12,0)+IF(AND(ISNUMBER(Z13),ISNUMBER(B13)),Z13*B13,0)+IF(AND(ISNUMBER(Z14),ISNUMBER(B14)),Z14*B14,0)+IF(AND(ISNUMBER(Z15),ISNUMBER(B15)),Z15*B15,0)+IF(AND(ISNUMBER(Z16),ISNUMBER(B16)),Z16*B16,0)+IF(AND(ISNUMBER(Z17),ISNUMBER(B17)),Z17*B17,0))/(IF(AND(ISNUMBER(Z11),ISNUMBER(B11)),B11,0)+IF(AND(ISNUMBER(Z12),ISNUMBER(B12)),B12,0)+IF(AND(ISNUMBER(Z13),ISNUMBER(B13)),B13,0)+IF(AND(ISNUMBER(Z14),ISNUMBER(B14)),B14,0)+IF(AND(ISNUMBER(Z15),ISNUMBER(B15)),B15,0)+IF(AND(ISNUMBER(Z16),ISNUMBER(B16)),B16,0)+IF(AND(ISNUMBER(Z17),ISNUMBER(B17)),B17,0))) | AB18: =IF((IF(AND(ISNUMBER(AB11),ISNUMBER(B11)),B11,0)+IF(AND(ISNUMBER(AB12),ISNUMBER(B12)),B12,0)+IF(AND(ISNUMBER(AB13),ISNUMBER(B13)),B13,0)+IF(AND(ISNUMBER(AB14),ISNUMBER(B14)),B14,0)+IF(AND(ISNUMBER(AB15),ISNUMBER(B15)),B15,0)+IF(AND(ISNUMBER(AB16),ISNUMBER(B16)),B16,0)+IF(AND(ISNUMBER(AB17),ISNUMBER(B17)),B17,0))=0,"",(IF(AND(ISNUMBER(AB11),ISNUMBER(B11)),AB11*B11,0)+IF(AND(ISNUMBER(AB12),ISNUMBER(B12)),AB12*B12,0)+IF(AND(ISNUMBER(AB13),ISNUMBER(B13)),AB13*B13,0)+IF(AND(ISNUMBER(AB14),ISNUMBER(B14)),AB14*B14,0)+IF(AND(ISNUMBER(AB15),ISNUMBER(B15)),AB15*B15,0)+IF(AND(ISNUMBER(AB16),ISNUMBER(B16)),AB16*B16,0)+IF(AND(ISNUMBER(AB17),ISNUMBER(B17)),AB17*B17,0))/(IF(AND(ISNUMBER(AB11),ISNUMBER(B11)),B11,0)+IF(AND(ISNUMBER(AB12),ISNUMBER(B12)),B12,0)+IF(AND(ISNUMBER(AB13),ISNUMBER(B13)),B13,0)+IF(AND(ISNUMBER(AB14),ISNUMBER(B14)),B14,0)+IF(AND(ISNUMBER(AB15),ISNUMBER(B15)),B15,0)+IF(AND(ISNUMBER(AB16),ISNUMBER(B16)),B16,0)+IF(AND(ISNUMBER(AB17),ISNUMBER(B17)),B17,0))) | AD18: =IF((IF(AND(ISNUMBER(AD11),ISNUMBER(B11)),B11,0)+IF(AND(ISNUMBER(AD12),ISNUMBER(B12)),B12,0)+IF(AND(ISNUMBER(AD13),ISNUMBER(B13)),B13,0)+IF(AND(ISNUMBER(AD14),ISNUMBER(B14)),B14,0)+IF(AND(ISNUMBER(AD15),ISNUMBER(B15)),B15,0)+IF(AND(ISNUMBER(AD16),ISNUMBER(B16)),B16,0)+IF(AND(ISNUMBER(AD17),ISNUMBER(B17)),B17,0))=0,"",(IF(AND(ISNUMBER(AD11),ISNUMBER(B11)),AD11*B11,0)+IF(AND(ISNUMBER(AD12),ISNUMBER(B12)),AD12*B12,0)+IF(AND(ISNUMBER(AD13),ISNUMBER(B13)),AD13*B13,0)+IF(AND(ISNUMBER(AD14),ISNUMBER(B14)),AD14*B14,0)+IF(AND(ISNUMBER(AD15),ISNUMBER(B15)),AD15*B15,0)+IF(AND(ISNUMBER(AD16),ISNUMBER(B16)),AD16*B16,0)+IF(AND(ISNUMBER(AD17),ISNUMBER(B17)),AD17*B17,0))/(IF(AND(ISNUMBER(AD11),ISNUMBER(B11)),B11,0)+IF(AND(ISNUMBER(AD12),ISNUMBER(B12)),B12,0)+IF(AND(ISNUMBER(AD13),ISNUMBER(B13)),B13,0)+IF(AND(ISNUMBER(AD14),ISNUMBER(B14)),B14,0)+IF(AND(ISNUMBER(AD15),ISNUMBER(B15)),B15,0)+IF(AND(ISNUMBER(AD16),ISNUMBER(B16)),B16,0)+IF(AND(ISNUMBER(AD17),ISNUMBER(B17)),B17,0))) | AF18: =IF(OR(NOT(ISNUMBER(B18)),B18=0),"",AG18/B18) | AG18: =IF(COUNT(AG11:AG17)=0,"",SUM(AG11:AG17))
A20: 46306 | B20: =IF(OR(ISNUMBER('Provincia Venta Diaria'!J12),ISNUMBER('Provincia Venta Diaria'!K12)),(IF(ISNUMBER('Provincia Venta Diaria'!J12),'Provincia Venta Diaria'!J12,0)+IF(ISNUMBER('Provincia Venta Diaria'!K12),'Provincia Venta Diaria'!K12,0))*1000,"") | C20: =IF(AND(ISNUMBER(PRECIO!B12),ISNUMBER(PRECIO!B12)),PRECIO!B12,"") | D20: =IF(AND(ISNUMBER(C20),ISNUMBER(B20)),C20*B20,"") | H20: =IF(AND(ISNUMBER(C20),ISNUMBER(F20),ISNUMBER(G20)),C20-F20-G20,"") | O20: =IF(ISNUMBER(H20),H20,"") | W20: =IF(ISNUMBER(O20),O20,"") | Z20: =IF(AND(ISNUMBER(Y20),ISNUMBER(B20),B20<>0),Y20/B20,"") | AB20: =IF(AND(ISNUMBER(W20),ISNUMBER(Z20)),W20-Z20,"") | AD20: =IF(AND(ISNUMBER('Provincia Comisiones'!B12),ISNUMBER('Provincia Comisiones'!B12)),'Provincia Comisiones'!B12,"") | AF20: =IF(AND(ISNUMBER(AB20),ISNUMBER(AD20)),AB20+AD20,"") | AG20: =IF(AND(ISNUMBER(AF20),ISNUMBER(B20)),AF20*B20,"")
A21: 46307 | B21: =IF(OR(ISNUMBER('Provincia Venta Diaria'!J13),ISNUMBER('Provincia Venta Diaria'!K13)),(IF(ISNUMBER('Provincia Venta Diaria'!J13),'Provincia Venta Diaria'!J13,0)+IF(ISNUMBER('Provincia Venta Diaria'!K13),'Provincia Venta Diaria'!K13,0))*1000,"") | C21: =IF(AND(ISNUMBER(PRECIO!B13),ISNUMBER(PRECIO!B13)),PRECIO!B13,"") | D21: =IF(AND(ISNUMBER(C21),ISNUMBER(B21)),C21*B21,"") | H21: =IF(AND(ISNUMBER(C21),ISNUMBER(F21),ISNUMBER(G21)),C21-F21-G21,"") | M21: =IF(AND(ISNUMBER($M$3),ISNUMBER(B21),B21<>0),($M$3/27)/B21,"") | O21: =IF(AND(ISNUMBER(H21),ISNUMBER(M21)),H21-M21,"") | U21: =IF(AND(ISNUMBER($U$3),ISNUMBER(B21),B21<>0),($U$3/27)/B21,"") | W21: =IF(AND(ISNUMBER(O21),ISNUMBER(U21)),O21-U21,"") | Z21: =IF(AND(ISNUMBER(Y21),ISNUMBER(B21),B21<>0),Y21/B21,"") | AB21: =IF(AND(ISNUMBER(W21),ISNUMBER(Z21)),W21-Z21,"") | AD21: =IF(AND(ISNUMBER('Provincia Comisiones'!B13),ISNUMBER('Provincia Comisiones'!B13)),'Provincia Comisiones'!B13,"") | AF21: =IF(AND(ISNUMBER(AB21),ISNUMBER(AD21)),AB21+AD21,"") | AG21: =IF(AND(ISNUMBER(AF21),ISNUMBER(B21)),AF21*B21,"")
A22: 46308 | B22: =IF(OR(ISNUMBER('Provincia Venta Diaria'!J14),ISNUMBER('Provincia Venta Diaria'!K14)),(IF(ISNUMBER('Provincia Venta Diaria'!J14),'Provincia Venta Diaria'!J14,0)+IF(ISNUMBER('Provincia Venta Diaria'!K14),'Provincia Venta Diaria'!K14,0))*1000,"") | C22: =IF(AND(ISNUMBER(PRECIO!B14),ISNUMBER(PRECIO!B14)),PRECIO!B14,"") | D22: =IF(AND(ISNUMBER(C22),ISNUMBER(B22)),C22*B22,"") | H22: =IF(AND(ISNUMBER(C22),ISNUMBER(F22),ISNUMBER(G22)),C22-F22-G22,"") | M22: =IF(AND(ISNUMBER($M$3),ISNUMBER(B22),B22<>0),($M$3/27)/B22,"") | O22: =IF(AND(ISNUMBER(H22),ISNUMBER(M22)),H22-M22,"") | U22: =IF(AND(ISNUMBER($U$3),ISNUMBER(B22),B22<>0),($U$3/27)/B22,"") | W22: =IF(AND(ISNUMBER(O22),ISNUMBER(U22)),O22-U22,"") | Z22: =IF(AND(ISNUMBER(Y22),ISNUMBER(B22),B22<>0),Y22/B22,"") | AB22: =IF(AND(ISNUMBER(W22),ISNUMBER(Z22)),W22-Z22,"") | AD22: =IF(AND(ISNUMBER('Provincia Comisiones'!B14),ISNUMBER('Provincia Comisiones'!B14)),'Provincia Comisiones'!B14,"") | AF22: =IF(AND(ISNUMBER(AB22),ISNUMBER(AD22)),AB22+AD22,"") | AG22: =IF(AND(ISNUMBER(AF22),ISNUMBER(B22)),AF22*B22,"")
A23: 46309 | B23: =IF(OR(ISNUMBER('Provincia Venta Diaria'!J15),ISNUMBER('Provincia Venta Diaria'!K15)),(IF(ISNUMBER('Provincia Venta Diaria'!J15),'Provincia Venta Diaria'!J15,0)+IF(ISNUMBER('Provincia Venta Diaria'!K15),'Provincia Venta Diaria'!K15,0))*1000,"") | C23: =IF(AND(ISNUMBER(PRECIO!B15),ISNUMBER(PRECIO!B15)),PRECIO!B15,"") | D23: =IF(AND(ISNUMBER(C23),ISNUMBER(B23)),C23*B23,"") | H23: =IF(AND(ISNUMBER(C23),ISNUMBER(F23),ISNUMBER(G23)),C23-F23-G23,"") | M23: =IF(AND(ISNUMBER($M$3),ISNUMBER(B23),B23<>0),($M$3/27)/B23,"") | O23: =IF(AND(ISNUMBER(H23),ISNUMBER(M23)),H23-M23,"") | U23: =IF(AND(ISNUMBER($U$3),ISNUMBER(B23),B23<>0),($U$3/27)/B23,"") | W23: =IF(AND(ISNUMBER(O23),ISNUMBER(U23)),O23-U23,"") | Z23: =IF(AND(ISNUMBER(Y23),ISNUMBER(B23),B23<>0),Y23/B23,"") | AB23: =IF(AND(ISNUMBER(W23),ISNUMBER(Z23)),W23-Z23,"") | AD23: =IF(AND(ISNUMBER('Provincia Comisiones'!B15),ISNUMBER('Provincia Comisiones'!B15)),'Provincia Comisiones'!B15,"") | AF23: =IF(AND(ISNUMBER(AB23),ISNUMBER(AD23)),AB23+AD23,"") | AG23: =IF(AND(ISNUMBER(AF23),ISNUMBER(B23)),AF23*B23,"")
A24: 46310 | B24: =IF(OR(ISNUMBER('Provincia Venta Diaria'!J16),ISNUMBER('Provincia Venta Diaria'!K16)),(IF(ISNUMBER('Provincia Venta Diaria'!J16),'Provincia Venta Diaria'!J16,0)+IF(ISNUMBER('Provincia Venta Diaria'!K16),'Provincia Venta Diaria'!K16,0))*1000,"") | C24: =IF(AND(ISNUMBER(PRECIO!B16),ISNUMBER(PRECIO!B16)),PRECIO!B16,"") | D24: =IF(AND(ISNUMBER(C24),ISNUMBER(B24)),C24*B24,"") | H24: =IF(AND(ISNUMBER(C24),ISNUMBER(F24),ISNUMBER(G24)),C24-F24-G24,"") | M24: =IF(AND(ISNUMBER($M$3),ISNUMBER(B24),B24<>0),($M$3/27)/B24,"") | O24: =IF(AND(ISNUMBER(H24),ISNUMBER(M24)),H24-M24,"") | U24: =IF(AND(ISNUMBER($U$3),ISNUMBER(B24),B24<>0),($U$3/27)/B24,"") | W24: =IF(AND(ISNUMBER(O24),ISNUMBER(U24)),O24-U24,"") | Z24: =IF(AND(ISNUMBER(Y24),ISNUMBER(B24),B24<>0),Y24/B24,"") | AB24: =IF(AND(ISNUMBER(W24),ISNUMBER(Z24)),W24-Z24,"") | AD24: =IF(AND(ISNUMBER('Provincia Comisiones'!B16),ISNUMBER('Provincia Comisiones'!B16)),'Provincia Comisiones'!B16,"") | AF24: =IF(AND(ISNUMBER(AB24),ISNUMBER(AD24)),AB24+AD24,"") | AG24: =IF(AND(ISNUMBER(AF24),ISNUMBER(B24)),AF24*B24,"")
A25: 46311 | B25: =IF(OR(ISNUMBER('Provincia Venta Diaria'!J17),ISNUMBER('Provincia Venta Diaria'!K17)),(IF(ISNUMBER('Provincia Venta Diaria'!J17),'Provincia Venta Diaria'!J17,0)+IF(ISNUMBER('Provincia Venta Diaria'!K17),'Provincia Venta Diaria'!K17,0))*1000,"") | C25: =IF(AND(ISNUMBER(PRECIO!B17),ISNUMBER(PRECIO!B17)),PRECIO!B17,"") | D25: =IF(AND(ISNUMBER(C25),ISNUMBER(B25)),C25*B25,"") | H25: =IF(AND(ISNUMBER(C25),ISNUMBER(F25),ISNUMBER(G25)),C25-F25-G25,"") | M25: =IF(AND(ISNUMBER($M$3),ISNUMBER(B25),B25<>0),($M$3/27)/B25,"") | O25: =IF(AND(ISNUMBER(H25),ISNUMBER(M25)),H25-M25,"") | U25: =IF(AND(ISNUMBER($U$3),ISNUMBER(B25),B25<>0),($U$3/27)/B25,"") | W25: =IF(AND(ISNUMBER(O25),ISNUMBER(U25)),O25-U25,"") | Z25: =IF(AND(ISNUMBER(Y25),ISNUMBER(B25),B25<>0),Y25/B25,"") | AB25: =IF(AND(ISNUMBER(W25),ISNUMBER(Z25)),W25-Z25,"") | AD25: =IF(AND(ISNUMBER('Provincia Comisiones'!B17),ISNUMBER('Provincia Comisiones'!B17)),'Provincia Comisiones'!B17,"") | AF25: =IF(AND(ISNUMBER(AB25),ISNUMBER(AD25)),AB25+AD25,"") | AG25: =IF(AND(ISNUMBER(AF25),ISNUMBER(B25)),AF25*B25,"")
A26: 46312 | B26: =IF(OR(ISNUMBER('Provincia Venta Diaria'!J18),ISNUMBER('Provincia Venta Diaria'!K18)),(IF(ISNUMBER('Provincia Venta Diaria'!J18),'Provincia Venta Diaria'!J18,0)+IF(ISNUMBER('Provincia Venta Diaria'!K18),'Provincia Venta Diaria'!K18,0))*1000,"") | C26: =IF(AND(ISNUMBER(PRECIO!B18),ISNUMBER(PRECIO!B18)),PRECIO!B18,"") | D26: =IF(AND(ISNUMBER(C26),ISNUMBER(B26)),C26*B26,"") | H26: =IF(AND(ISNUMBER(C26),ISNUMBER(F26),ISNUMBER(G26)),C26-F26-G26,"") | M26: =IF(AND(ISNUMBER($M$3),ISNUMBER(B26),B26<>0),($M$3/27)/B26,"") | O26: =IF(AND(ISNUMBER(H26),ISNUMBER(M26)),H26-M26,"") | U26: =IF(AND(ISNUMBER($U$3),ISNUMBER(B26),B26<>0),($U$3/27)/B26,"") | W26: =IF(AND(ISNUMBER(O26),ISNUMBER(U26)),O26-U26,"") | Z26: =IF(AND(ISNUMBER(Y26),ISNUMBER(B26),B26<>0),Y26/B26,"") | AB26: =IF(AND(ISNUMBER(W26),ISNUMBER(Z26)),W26-Z26,"") | AD26: =IF(AND(ISNUMBER('Provincia Comisiones'!B18),ISNUMBER('Provincia Comisiones'!B18)),'Provincia Comisiones'!B18,"") | AF26: =IF(AND(ISNUMBER(AB26),ISNUMBER(AD26)),AB26+AD26,"") | AG26: =IF(AND(ISNUMBER(AF26),ISNUMBER(B26)),AF26*B26,"")
A27: Semana 42 | B27: =IF(COUNT(B20:B26)=0,"",SUM(B20:B26)) | C27: =IF((IF(AND(ISNUMBER(C20),ISNUMBER(B20)),B20,0)+IF(AND(ISNUMBER(C21),ISNUMBER(B21)),B21,0)+IF(AND(ISNUMBER(C22),ISNUMBER(B22)),B22,0)+IF(AND(ISNUMBER(C23),ISNUMBER(B23)),B23,0)+IF(AND(ISNUMBER(C24),ISNUMBER(B24)),B24,0)+IF(AND(ISNUMBER(C25),ISNUMBER(B25)),B25,0)+IF(AND(ISNUMBER(C26),ISNUMBER(B26)),B26,0))=0,"",(IF(AND(ISNUMBER(C20),ISNUMBER(B20)),C20*B20,0)+IF(AND(ISNUMBER(C21),ISNUMBER(B21)),C21*B21,0)+IF(AND(ISNUMBER(C22),ISNUMBER(B22)),C22*B22,0)+IF(AND(ISNUMBER(C23),ISNUMBER(B23)),C23*B23,0)+IF(AND(ISNUMBER(C24),ISNUMBER(B24)),C24*B24,0)+IF(AND(ISNUMBER(C25),ISNUMBER(B25)),C25*B25,0)+IF(AND(ISNUMBER(C26),ISNUMBER(B26)),C26*B26,0))/(IF(AND(ISNUMBER(C20),ISNUMBER(B20)),B20,0)+IF(AND(ISNUMBER(C21),ISNUMBER(B21)),B21,0)+IF(AND(ISNUMBER(C22),ISNUMBER(B22)),B22,0)+IF(AND(ISNUMBER(C23),ISNUMBER(B23)),B23,0)+IF(AND(ISNUMBER(C24),ISNUMBER(B24)),B24,0)+IF(AND(ISNUMBER(C25),ISNUMBER(B25)),B25,0)+IF(AND(ISNUMBER(C26),ISNUMBER(B26)),B26,0))) | D27: =IF(COUNT(D20:D26)=0,"",SUM(D20:D26)) | F27: =IF((IF(AND(ISNUMBER(F20),ISNUMBER(B20)),B20,0)+IF(AND(ISNUMBER(F21),ISNUMBER(B21)),B21,0)+IF(AND(ISNUMBER(F22),ISNUMBER(B22)),B22,0)+IF(AND(ISNUMBER(F23),ISNUMBER(B23)),B23,0)+IF(AND(ISNUMBER(F24),ISNUMBER(B24)),B24,0)+IF(AND(ISNUMBER(F25),ISNUMBER(B25)),B25,0)+IF(AND(ISNUMBER(F26),ISNUMBER(B26)),B26,0))=0,"",(IF(AND(ISNUMBER(F20),ISNUMBER(B20)),F20*B20,0)+IF(AND(ISNUMBER(F21),ISNUMBER(B21)),F21*B21,0)+IF(AND(ISNUMBER(F22),ISNUMBER(B22)),F22*B22,0)+IF(AND(ISNUMBER(F23),ISNUMBER(B23)),F23*B23,0)+IF(AND(ISNUMBER(F24),ISNUMBER(B24)),F24*B24,0)+IF(AND(ISNUMBER(F25),ISNUMBER(B25)),F25*B25,0)+IF(AND(ISNUMBER(F26),ISNUMBER(B26)),F26*B26,0))/(IF(AND(ISNUMBER(F20),ISNUMBER(B20)),B20,0)+IF(AND(ISNUMBER(F21),ISNUMBER(B21)),B21,0)+IF(AND(ISNUMBER(F22),ISNUMBER(B22)),B22,0)+IF(AND(ISNUMBER(F23),ISNUMBER(B23)),B23,0)+IF(AND(ISNUMBER(F24),ISNUMBER(B24)),B24,0)+IF(AND(ISNUMBER(F25),ISNUMBER(B25)),B25,0)+IF(AND(ISNUMBER(F26),ISNUMBER(B26)),B26,0))) | G27: =IF((IF(AND(ISNUMBER(G20),ISNUMBER(B20)),B20,0)+IF(AND(ISNUMBER(G21),ISNUMBER(B21)),B21,0)+IF(AND(ISNUMBER(G22),ISNUMBER(B22)),B22,0)+IF(AND(ISNUMBER(G23),ISNUMBER(B23)),B23,0)+IF(AND(ISNUMBER(G24),ISNUMBER(B24)),B24,0)+IF(AND(ISNUMBER(G25),ISNUMBER(B25)),B25,0)+IF(AND(ISNUMBER(G26),ISNUMBER(B26)),B26,0))=0,"",(IF(AND(ISNUMBER(G20),ISNUMBER(B20)),G20*B20,0)+IF(AND(ISNUMBER(G21),ISNUMBER(B21)),G21*B21,0)+IF(AND(ISNUMBER(G22),ISNUMBER(B22)),G22*B22,0)+IF(AND(ISNUMBER(G23),ISNUMBER(B23)),G23*B23,0)+IF(AND(ISNUMBER(G24),ISNUMBER(B24)),G24*B24,0)+IF(AND(ISNUMBER(G25),ISNUMBER(B25)),G25*B25,0)+IF(AND(ISNUMBER(G26),ISNUMBER(B26)),G26*B26,0))/(IF(AND(ISNUMBER(G20),ISNUMBER(B20)),B20,0)+IF(AND(ISNUMBER(G21),ISNUMBER(B21)),B21,0)+IF(AND(ISNUMBER(G22),ISNUMBER(B22)),B22,0)+IF(AND(ISNUMBER(G23),ISNUMBER(B23)),B23,0)+IF(AND(ISNUMBER(G24),ISNUMBER(B24)),B24,0)+IF(AND(ISNUMBER(G25),ISNUMBER(B25)),B25,0)+IF(AND(ISNUMBER(G26),ISNUMBER(B26)),B26,0))) | H27: =IF((IF(AND(ISNUMBER(H20),ISNUMBER(B20)),B20,0)+IF(AND(ISNUMBER(H21),ISNUMBER(B21)),B21,0)+IF(AND(ISNUMBER(H22),ISNUMBER(B22)),B22,0)+IF(AND(ISNUMBER(H23),ISNUMBER(B23)),B23,0)+IF(AND(ISNUMBER(H24),ISNUMBER(B24)),B24,0)+IF(AND(ISNUMBER(H25),ISNUMBER(B25)),B25,0)+IF(AND(ISNUMBER(H26),ISNUMBER(B26)),B26,0))=0,"",(IF(AND(ISNUMBER(H20),ISNUMBER(B20)),H20*B20,0)+IF(AND(ISNUMBER(H21),ISNUMBER(B21)),H21*B21,0)+IF(AND(ISNUMBER(H22),ISNUMBER(B22)),H22*B22,0)+IF(AND(ISNUMBER(H23),ISNUMBER(B23)),H23*B23,0)+IF(AND(ISNUMBER(H24),ISNUMBER(B24)),H24*B24,0)+IF(AND(ISNUMBER(H25),ISNUMBER(B25)),H25*B25,0)+IF(AND(ISNUMBER(H26),ISNUMBER(B26)),H26*B26,0))/(IF(AND(ISNUMBER(H20),ISNUMBER(B20)),B20,0)+IF(AND(ISNUMBER(H21),ISNUMBER(B21)),B21,0)+IF(AND(ISNUMBER(H22),ISNUMBER(B22)),B22,0)+IF(AND(ISNUMBER(H23),ISNUMBER(B23)),B23,0)+IF(AND(ISNUMBER(H24),ISNUMBER(B24)),B24,0)+IF(AND(ISNUMBER(H25),ISNUMBER(B25)),B25,0)+IF(AND(ISNUMBER(H26),ISNUMBER(B26)),B26,0))) | M27: =IF((IF(AND(ISNUMBER(M20),ISNUMBER(B20)),B20,0)+IF(AND(ISNUMBER(M21),ISNUMBER(B21)),B21,0)+IF(AND(ISNUMBER(M22),ISNUMBER(B22)),B22,0)+IF(AND(ISNUMBER(M23),ISNUMBER(B23)),B23,0)+IF(AND(ISNUMBER(M24),ISNUMBER(B24)),B24,0)+IF(AND(ISNUMBER(M25),ISNUMBER(B25)),B25,0)+IF(AND(ISNUMBER(M26),ISNUMBER(B26)),B26,0))=0,"",(IF(AND(ISNUMBER(M20),ISNUMBER(B20)),M20*B20,0)+IF(AND(ISNUMBER(M21),ISNUMBER(B21)),M21*B21,0)+IF(AND(ISNUMBER(M22),ISNUMBER(B22)),M22*B22,0)+IF(AND(ISNUMBER(M23),ISNUMBER(B23)),M23*B23,0)+IF(AND(ISNUMBER(M24),ISNUMBER(B24)),M24*B24,0)+IF(AND(ISNUMBER(M25),ISNUMBER(B25)),M25*B25,0)+IF(AND(ISNUMBER(M26),ISNUMBER(B26)),M26*B26,0))/(IF(AND(ISNUMBER(M20),ISNUMBER(B20)),B20,0)+IF(AND(ISNUMBER(M21),ISNUMBER(B21)),B21,0)+IF(AND(ISNUMBER(M22),ISNUMBER(B22)),B22,0)+IF(AND(ISNUMBER(M23),ISNUMBER(B23)),B23,0)+IF(AND(ISNUMBER(M24),ISNUMBER(B24)),B24,0)+IF(AND(ISNUMBER(M25),ISNUMBER(B25)),B25,0)+IF(AND(ISNUMBER(M26),ISNUMBER(B26)),B26,0))) | O27: =IF((IF(AND(ISNUMBER(O20),ISNUMBER(B20)),B20,0)+IF(AND(ISNUMBER(O21),ISNUMBER(B21)),B21,0)+IF(AND(ISNUMBER(O22),ISNUMBER(B22)),B22,0)+IF(AND(ISNUMBER(O23),ISNUMBER(B23)),B23,0)+IF(AND(ISNUMBER(O24),ISNUMBER(B24)),B24,0)+IF(AND(ISNUMBER(O25),ISNUMBER(B25)),B25,0)+IF(AND(ISNUMBER(O26),ISNUMBER(B26)),B26,0))=0,"",(IF(AND(ISNUMBER(O20),ISNUMBER(B20)),O20*B20,0)+IF(AND(ISNUMBER(O21),ISNUMBER(B21)),O21*B21,0)+IF(AND(ISNUMBER(O22),ISNUMBER(B22)),O22*B22,0)+IF(AND(ISNUMBER(O23),ISNUMBER(B23)),O23*B23,0)+IF(AND(ISNUMBER(O24),ISNUMBER(B24)),O24*B24,0)+IF(AND(ISNUMBER(O25),ISNUMBER(B25)),O25*B25,0)+IF(AND(ISNUMBER(O26),ISNUMBER(B26)),O26*B26,0))/(IF(AND(ISNUMBER(O20),ISNUMBER(B20)),B20,0)+IF(AND(ISNUMBER(O21),ISNUMBER(B21)),B21,0)+IF(AND(ISNUMBER(O22),ISNUMBER(B22)),B22,0)+IF(AND(ISNUMBER(O23),ISNUMBER(B23)),B23,0)+IF(AND(ISNUMBER(O24),ISNUMBER(B24)),B24,0)+IF(AND(ISNUMBER(O25),ISNUMBER(B25)),B25,0)+IF(AND(ISNUMBER(O26),ISNUMBER(B26)),B26,0))) | U27: =IF((IF(AND(ISNUMBER(U20),ISNUMBER(B20)),B20,0)+IF(AND(ISNUMBER(U21),ISNUMBER(B21)),B21,0)+IF(AND(ISNUMBER(U22),ISNUMBER(B22)),B22,0)+IF(AND(ISNUMBER(U23),ISNUMBER(B23)),B23,0)+IF(AND(ISNUMBER(U24),ISNUMBER(B24)),B24,0)+IF(AND(ISNUMBER(U25),ISNUMBER(B25)),B25,0)+IF(AND(ISNUMBER(U26),ISNUMBER(B26)),B26,0))=0,"",(IF(AND(ISNUMBER(U20),ISNUMBER(B20)),U20*B20,0)+IF(AND(ISNUMBER(U21),ISNUMBER(B21)),U21*B21,0)+IF(AND(ISNUMBER(U22),ISNUMBER(B22)),U22*B22,0)+IF(AND(ISNUMBER(U23),ISNUMBER(B23)),U23*B23,0)+IF(AND(ISNUMBER(U24),ISNUMBER(B24)),U24*B24,0)+IF(AND(ISNUMBER(U25),ISNUMBER(B25)),U25*B25,0)+IF(AND(ISNUMBER(U26),ISNUMBER(B26)),U26*B26,0))/(IF(AND(ISNUMBER(U20),ISNUMBER(B20)),B20,0)+IF(AND(ISNUMBER(U21),ISNUMBER(B21)),B21,0)+IF(AND(ISNUMBER(U22),ISNUMBER(B22)),B22,0)+IF(AND(ISNUMBER(U23),ISNUMBER(B23)),B23,0)+IF(AND(ISNUMBER(U24),ISNUMBER(B24)),B24,0)+IF(AND(ISNUMBER(U25),ISNUMBER(B25)),B25,0)+IF(AND(ISNUMBER(U26),ISNUMBER(B26)),B26,0))) | W27: =IF((IF(AND(ISNUMBER(W20),ISNUMBER(B20)),B20,0)+IF(AND(ISNUMBER(W21),ISNUMBER(B21)),B21,0)+IF(AND(ISNUMBER(W22),ISNUMBER(B22)),B22,0)+IF(AND(ISNUMBER(W23),ISNUMBER(B23)),B23,0)+IF(AND(ISNUMBER(W24),ISNUMBER(B24)),B24,0)+IF(AND(ISNUMBER(W25),ISNUMBER(B25)),B25,0)+IF(AND(ISNUMBER(W26),ISNUMBER(B26)),B26,0))=0,"",(IF(AND(ISNUMBER(W20),ISNUMBER(B20)),W20*B20,0)+IF(AND(ISNUMBER(W21),ISNUMBER(B21)),W21*B21,0)+IF(AND(ISNUMBER(W22),ISNUMBER(B22)),W22*B22,0)+IF(AND(ISNUMBER(W23),ISNUMBER(B23)),W23*B23,0)+IF(AND(ISNUMBER(W24),ISNUMBER(B24)),W24*B24,0)+IF(AND(ISNUMBER(W25),ISNUMBER(B25)),W25*B25,0)+IF(AND(ISNUMBER(W26),ISNUMBER(B26)),W26*B26,0))/(IF(AND(ISNUMBER(W20),ISNUMBER(B20)),B20,0)+IF(AND(ISNUMBER(W21),ISNUMBER(B21)),B21,0)+IF(AND(ISNUMBER(W22),ISNUMBER(B22)),B22,0)+IF(AND(ISNUMBER(W23),ISNUMBER(B23)),B23,0)+IF(AND(ISNUMBER(W24),ISNUMBER(B24)),B24,0)+IF(AND(ISNUMBER(W25),ISNUMBER(B25)),B25,0)+IF(AND(ISNUMBER(W26),ISNUMBER(B26)),B26,0))) | Y27: =IF(COUNT(Y20:Y26)=0,"",SUM(Y20:Y26)) | Z27: =IF((IF(AND(ISNUMBER(Z20),ISNUMBER(B20)),B20,0)+IF(AND(ISNUMBER(Z21),ISNUMBER(B21)),B21,0)+IF(AND(ISNUMBER(Z22),ISNUMBER(B22)),B22,0)+IF(AND(ISNUMBER(Z23),ISNUMBER(B23)),B23,0)+IF(AND(ISNUMBER(Z24),ISNUMBER(B24)),B24,0)+IF(AND(ISNUMBER(Z25),ISNUMBER(B25)),B25,0)+IF(AND(ISNUMBER(Z26),ISNUMBER(B26)),B26,0))=0,"",(IF(AND(ISNUMBER(Z20),ISNUMBER(B20)),Z20*B20,0)+IF(AND(ISNUMBER(Z21),ISNUMBER(B21)),Z21*B21,0)+IF(AND(ISNUMBER(Z22),ISNUMBER(B22)),Z22*B22,0)+IF(AND(ISNUMBER(Z23),ISNUMBER(B23)),Z23*B23,0)+IF(AND(ISNUMBER(Z24),ISNUMBER(B24)),Z24*B24,0)+IF(AND(ISNUMBER(Z25),ISNUMBER(B25)),Z25*B25,0)+IF(AND(ISNUMBER(Z26),ISNUMBER(B26)),Z26*B26,0))/(IF(AND(ISNUMBER(Z20),ISNUMBER(B20)),B20,0)+IF(AND(ISNUMBER(Z21),ISNUMBER(B21)),B21,0)+IF(AND(ISNUMBER(Z22),ISNUMBER(B22)),B22,0)+IF(AND(ISNUMBER(Z23),ISNUMBER(B23)),B23,0)+IF(AND(ISNUMBER(Z24),ISNUMBER(B24)),B24,0)+IF(AND(ISNUMBER(Z25),ISNUMBER(B25)),B25,0)+IF(AND(ISNUMBER(Z26),ISNUMBER(B26)),B26,0))) | AB27: =IF((IF(AND(ISNUMBER(AB20),ISNUMBER(B20)),B20,0)+IF(AND(ISNUMBER(AB21),ISNUMBER(B21)),B21,0)+IF(AND(ISNUMBER(AB22),ISNUMBER(B22)),B22,0)+IF(AND(ISNUMBER(AB23),ISNUMBER(B23)),B23,0)+IF(AND(ISNUMBER(AB24),ISNUMBER(B24)),B24,0)+IF(AND(ISNUMBER(AB25),ISNUMBER(B25)),B25,0)+IF(AND(ISNUMBER(AB26),ISNUMBER(B26)),B26,0))=0,"",(IF(AND(ISNUMBER(AB20),ISNUMBER(B20)),AB20*B20,0)+IF(AND(ISNUMBER(AB21),ISNUMBER(B21)),AB21*B21,0)+IF(AND(ISNUMBER(AB22),ISNUMBER(B22)),AB22*B22,0)+IF(AND(ISNUMBER(AB23),ISNUMBER(B23)),AB23*B23,0)+IF(AND(ISNUMBER(AB24),ISNUMBER(B24)),AB24*B24,0)+IF(AND(ISNUMBER(AB25),ISNUMBER(B25)),AB25*B25,0)+IF(AND(ISNUMBER(AB26),ISNUMBER(B26)),AB26*B26,0))/(IF(AND(ISNUMBER(AB20),ISNUMBER(B20)),B20,0)+IF(AND(ISNUMBER(AB21),ISNUMBER(B21)),B21,0)+IF(AND(ISNUMBER(AB22),ISNUMBER(B22)),B22,0)+IF(AND(ISNUMBER(AB23),ISNUMBER(B23)),B23,0)+IF(AND(ISNUMBER(AB24),ISNUMBER(B24)),B24,0)+IF(AND(ISNUMBER(AB25),ISNUMBER(B25)),B25,0)+IF(AND(ISNUMBER(AB26),ISNUMBER(B26)),B26,0))) | AD27: =IF((IF(AND(ISNUMBER(AD20),ISNUMBER(B20)),B20,0)+IF(AND(ISNUMBER(AD21),ISNUMBER(B21)),B21,0)+IF(AND(ISNUMBER(AD22),ISNUMBER(B22)),B22,0)+IF(AND(ISNUMBER(AD23),ISNUMBER(B23)),B23,0)+IF(AND(ISNUMBER(AD24),ISNUMBER(B24)),B24,0)+IF(AND(ISNUMBER(AD25),ISNUMBER(B25)),B25,0)+IF(AND(ISNUMBER(AD26),ISNUMBER(B26)),B26,0))=0,"",(IF(AND(ISNUMBER(AD20),ISNUMBER(B20)),AD20*B20,0)+IF(AND(ISNUMBER(AD21),ISNUMBER(B21)),AD21*B21,0)+IF(AND(ISNUMBER(AD22),ISNUMBER(B22)),AD22*B22,0)+IF(AND(ISNUMBER(AD23),ISNUMBER(B23)),AD23*B23,0)+IF(AND(ISNUMBER(AD24),ISNUMBER(B24)),AD24*B24,0)+IF(AND(ISNUMBER(AD25),ISNUMBER(B25)),AD25*B25,0)+IF(AND(ISNUMBER(AD26),ISNUMBER(B26)),AD26*B26,0))/(IF(AND(ISNUMBER(AD20),ISNUMBER(B20)),B20,0)+IF(AND(ISNUMBER(AD21),ISNUMBER(B21)),B21,0)+IF(AND(ISNUMBER(AD22),ISNUMBER(B22)),B22,0)+IF(AND(ISNUMBER(AD23),ISNUMBER(B23)),B23,0)+IF(AND(ISNUMBER(AD24),ISNUMBER(B24)),B24,0)+IF(AND(ISNUMBER(AD25),ISNUMBER(B25)),B25,0)+IF(AND(ISNUMBER(AD26),ISNUMBER(B26)),B26,0))) | AF27: =IF(OR(NOT(ISNUMBER(B27)),B27=0),"",AG27/B27) | AG27: =IF(COUNT(AG20:AG26)=0,"",SUM(AG20:AG26))
A29: 46313 | B29: =IF(OR(ISNUMBER('Provincia Venta Diaria'!J19),ISNUMBER('Provincia Venta Diaria'!K19)),(IF(ISNUMBER('Provincia Venta Diaria'!J19),'Provincia Venta Diaria'!J19,0)+IF(ISNUMBER('Provincia Venta Diaria'!K19),'Provincia Venta Diaria'!K19,0))*1000,"") | C29: =IF(AND(ISNUMBER(PRECIO!B19),ISNUMBER(PRECIO!B19)),PRECIO!B19,"") | D29: =IF(AND(ISNUMBER(C29),ISNUMBER(B29)),C29*B29,"") | H29: =IF(AND(ISNUMBER(C29),ISNUMBER(F29),ISNUMBER(G29)),C29-F29-G29,"") | O29: =IF(ISNUMBER(H29),H29,"") | W29: =IF(ISNUMBER(O29),O29,"") | Z29: =IF(AND(ISNUMBER(Y29),ISNUMBER(B29),B29<>0),Y29/B29,"") | AB29: =IF(AND(ISNUMBER(W29),ISNUMBER(Z29)),W29-Z29,"") | AD29: =IF(AND(ISNUMBER('Provincia Comisiones'!B19),ISNUMBER('Provincia Comisiones'!B19)),'Provincia Comisiones'!B19,"") | AF29: =IF(AND(ISNUMBER(AB29),ISNUMBER(AD29)),AB29+AD29,"") | AG29: =IF(AND(ISNUMBER(AF29),ISNUMBER(B29)),AF29*B29,"")
A30: 46314 | B30: =IF(OR(ISNUMBER('Provincia Venta Diaria'!J20),ISNUMBER('Provincia Venta Diaria'!K20)),(IF(ISNUMBER('Provincia Venta Diaria'!J20),'Provincia Venta Diaria'!J20,0)+IF(ISNUMBER('Provincia Venta Diaria'!K20),'Provincia Venta Diaria'!K20,0))*1000,"") | C30: =IF(AND(ISNUMBER(PRECIO!B20),ISNUMBER(PRECIO!B20)),PRECIO!B20,"") | D30: =IF(AND(ISNUMBER(C30),ISNUMBER(B30)),C30*B30,"") | H30: =IF(AND(ISNUMBER(C30),ISNUMBER(F30),ISNUMBER(G30)),C30-F30-G30,"") | M30: =IF(AND(ISNUMBER($M$3),ISNUMBER(B30),B30<>0),($M$3/27)/B30,"") | O30: =IF(AND(ISNUMBER(H30),ISNUMBER(M30)),H30-M30,"") | U30: =IF(AND(ISNUMBER($U$3),ISNUMBER(B30),B30<>0),($U$3/27)/B30,"") | W30: =IF(AND(ISNUMBER(O30),ISNUMBER(U30)),O30-U30,"") | Z30: =IF(AND(ISNUMBER(Y30),ISNUMBER(B30),B30<>0),Y30/B30,"") | AB30: =IF(AND(ISNUMBER(W30),ISNUMBER(Z30)),W30-Z30,"") | AD30: =IF(AND(ISNUMBER('Provincia Comisiones'!B20),ISNUMBER('Provincia Comisiones'!B20)),'Provincia Comisiones'!B20,"") | AF30: =IF(AND(ISNUMBER(AB30),ISNUMBER(AD30)),AB30+AD30,"") | AG30: =IF(AND(ISNUMBER(AF30),ISNUMBER(B30)),AF30*B30,"")
A31: 46315 | B31: =IF(OR(ISNUMBER('Provincia Venta Diaria'!J21),ISNUMBER('Provincia Venta Diaria'!K21)),(IF(ISNUMBER('Provincia Venta Diaria'!J21),'Provincia Venta Diaria'!J21,0)+IF(ISNUMBER('Provincia Venta Diaria'!K21),'Provincia Venta Diaria'!K21,0))*1000,"") | C31: =IF(AND(ISNUMBER(PRECIO!B21),ISNUMBER(PRECIO!B21)),PRECIO!B21,"") | D31: =IF(AND(ISNUMBER(C31),ISNUMBER(B31)),C31*B31,"") | H31: =IF(AND(ISNUMBER(C31),ISNUMBER(F31),ISNUMBER(G31)),C31-F31-G31,"") | M31: =IF(AND(ISNUMBER($M$3),ISNUMBER(B31),B31<>0),($M$3/27)/B31,"") | O31: =IF(AND(ISNUMBER(H31),ISNUMBER(M31)),H31-M31,"") | U31: =IF(AND(ISNUMBER($U$3),ISNUMBER(B31),B31<>0),($U$3/27)/B31,"") | W31: =IF(AND(ISNUMBER(O31),ISNUMBER(U31)),O31-U31,"") | Z31: =IF(AND(ISNUMBER(Y31),ISNUMBER(B31),B31<>0),Y31/B31,"") | AB31: =IF(AND(ISNUMBER(W31),ISNUMBER(Z31)),W31-Z31,"") | AD31: =IF(AND(ISNUMBER('Provincia Comisiones'!B21),ISNUMBER('Provincia Comisiones'!B21)),'Provincia Comisiones'!B21,"") | AF31: =IF(AND(ISNUMBER(AB31),ISNUMBER(AD31)),AB31+AD31,"") | AG31: =IF(AND(ISNUMBER(AF31),ISNUMBER(B31)),AF31*B31,"")
A32: 46316 | B32: =IF(OR(ISNUMBER('Provincia Venta Diaria'!J22),ISNUMBER('Provincia Venta Diaria'!K22)),(IF(ISNUMBER('Provincia Venta Diaria'!J22),'Provincia Venta Diaria'!J22,0)+IF(ISNUMBER('Provincia Venta Diaria'!K22),'Provincia Venta Diaria'!K22,0))*1000,"") | C32: =IF(AND(ISNUMBER(PRECIO!B22),ISNUMBER(PRECIO!B22)),PRECIO!B22,"") | D32: =IF(AND(ISNUMBER(C32),ISNUMBER(B32)),C32*B32,"") | H32: =IF(AND(ISNUMBER(C32),ISNUMBER(F32),ISNUMBER(G32)),C32-F32-G32,"") | M32: =IF(AND(ISNUMBER($M$3),ISNUMBER(B32),B32<>0),($M$3/27)/B32,"") | O32: =IF(AND(ISNUMBER(H32),ISNUMBER(M32)),H32-M32,"") | U32: =IF(AND(ISNUMBER($U$3),ISNUMBER(B32),B32<>0),($U$3/27)/B32,"") | W32: =IF(AND(ISNUMBER(O32),ISNUMBER(U32)),O32-U32,"") | Z32: =IF(AND(ISNUMBER(Y32),ISNUMBER(B32),B32<>0),Y32/B32,"") | AB32: =IF(AND(ISNUMBER(W32),ISNUMBER(Z32)),W32-Z32,"") | AD32: =IF(AND(ISNUMBER('Provincia Comisiones'!B22),ISNUMBER('Provincia Comisiones'!B22)),'Provincia Comisiones'!B22,"") | AF32: =IF(AND(ISNUMBER(AB32),ISNUMBER(AD32)),AB32+AD32,"") | AG32: =IF(AND(ISNUMBER(AF32),ISNUMBER(B32)),AF32*B32,"")
A33: 46317 | B33: =IF(OR(ISNUMBER('Provincia Venta Diaria'!J23),ISNUMBER('Provincia Venta Diaria'!K23)),(IF(ISNUMBER('Provincia Venta Diaria'!J23),'Provincia Venta Diaria'!J23,0)+IF(ISNUMBER('Provincia Venta Diaria'!K23),'Provincia Venta Diaria'!K23,0))*1000,"") | C33: =IF(AND(ISNUMBER(PRECIO!B23),ISNUMBER(PRECIO!B23)),PRECIO!B23,"") | D33: =IF(AND(ISNUMBER(C33),ISNUMBER(B33)),C33*B33,"") | H33: =IF(AND(ISNUMBER(C33),ISNUMBER(F33),ISNUMBER(G33)),C33-F33-G33,"") | M33: =IF(AND(ISNUMBER($M$3),ISNUMBER(B33),B33<>0),($M$3/27)/B33,"") | O33: =IF(AND(ISNUMBER(H33),ISNUMBER(M33)),H33-M33,"") | U33: =IF(AND(ISNUMBER($U$3),ISNUMBER(B33),B33<>0),($U$3/27)/B33,"") | W33: =IF(AND(ISNUMBER(O33),ISNUMBER(U33)),O33-U33,"") | Z33: =IF(AND(ISNUMBER(Y33),ISNUMBER(B33),B33<>0),Y33/B33,"") | AB33: =IF(AND(ISNUMBER(W33),ISNUMBER(Z33)),W33-Z33,"") | AD33: =IF(AND(ISNUMBER('Provincia Comisiones'!B23),ISNUMBER('Provincia Comisiones'!B23)),'Provincia Comisiones'!B23,"") | AF33: =IF(AND(ISNUMBER(AB33),ISNUMBER(AD33)),AB33+AD33,"") | AG33: =IF(AND(ISNUMBER(AF33),ISNUMBER(B33)),AF33*B33,"")
A34: 46318 | B34: =IF(OR(ISNUMBER('Provincia Venta Diaria'!J24),ISNUMBER('Provincia Venta Diaria'!K24)),(IF(ISNUMBER('Provincia Venta Diaria'!J24),'Provincia Venta Diaria'!J24,0)+IF(ISNUMBER('Provincia Venta Diaria'!K24),'Provincia Venta Diaria'!K24,0))*1000,"") | C34: =IF(AND(ISNUMBER(PRECIO!B24),ISNUMBER(PRECIO!B24)),PRECIO!B24,"") | D34: =IF(AND(ISNUMBER(C34),ISNUMBER(B34)),C34*B34,"") | H34: =IF(AND(ISNUMBER(C34),ISNUMBER(F34),ISNUMBER(G34)),C34-F34-G34,"") | M34: =IF(AND(ISNUMBER($M$3),ISNUMBER(B34),B34<>0),($M$3/27)/B34,"") | O34: =IF(AND(ISNUMBER(H34),ISNUMBER(M34)),H34-M34,"") | U34: =IF(AND(ISNUMBER($U$3),ISNUMBER(B34),B34<>0),($U$3/27)/B34,"") | W34: =IF(AND(ISNUMBER(O34),ISNUMBER(U34)),O34-U34,"") | Z34: =IF(AND(ISNUMBER(Y34),ISNUMBER(B34),B34<>0),Y34/B34,"") | AB34: =IF(AND(ISNUMBER(W34),ISNUMBER(Z34)),W34-Z34,"") | AD34: =IF(AND(ISNUMBER('Provincia Comisiones'!B24),ISNUMBER('Provincia Comisiones'!B24)),'Provincia Comisiones'!B24,"") | AF34: =IF(AND(ISNUMBER(AB34),ISNUMBER(AD34)),AB34+AD34,"") | AG34: =IF(AND(ISNUMBER(AF34),ISNUMBER(B34)),AF34*B34,"")
A35: 46319 | B35: =IF(OR(ISNUMBER('Provincia Venta Diaria'!J25),ISNUMBER('Provincia Venta Diaria'!K25)),(IF(ISNUMBER('Provincia Venta Diaria'!J25),'Provincia Venta Diaria'!J25,0)+IF(ISNUMBER('Provincia Venta Diaria'!K25),'Provincia Venta Diaria'!K25,0))*1000,"") | C35: =IF(AND(ISNUMBER(PRECIO!B25),ISNUMBER(PRECIO!B25)),PRECIO!B25,"") | D35: =IF(AND(ISNUMBER(C35),ISNUMBER(B35)),C35*B35,"") | H35: =IF(AND(ISNUMBER(C35),ISNUMBER(F35),ISNUMBER(G35)),C35-F35-G35,"") | M35: =IF(AND(ISNUMBER($M$3),ISNUMBER(B35),B35<>0),($M$3/27)/B35,"") | O35: =IF(AND(ISNUMBER(H35),ISNUMBER(M35)),H35-M35,"") | U35: =IF(AND(ISNUMBER($U$3),ISNUMBER(B35),B35<>0),($U$3/27)/B35,"") | W35: =IF(AND(ISNUMBER(O35),ISNUMBER(U35)),O35-U35,"") | Z35: =IF(AND(ISNUMBER(Y35),ISNUMBER(B35),B35<>0),Y35/B35,"") | AB35: =IF(AND(ISNUMBER(W35),ISNUMBER(Z35)),W35-Z35,"") | AD35: =IF(AND(ISNUMBER('Provincia Comisiones'!B25),ISNUMBER('Provincia Comisiones'!B25)),'Provincia Comisiones'!B25,"") | AF35: =IF(AND(ISNUMBER(AB35),ISNUMBER(AD35)),AB35+AD35,"") | AG35: =IF(AND(ISNUMBER(AF35),ISNUMBER(B35)),AF35*B35,"")
A36: Semana 43 | B36: =IF(COUNT(B29:B35)=0,"",SUM(B29:B35)) | C36: =IF((IF(AND(ISNUMBER(C29),ISNUMBER(B29)),B29,0)+IF(AND(ISNUMBER(C30),ISNUMBER(B30)),B30,0)+IF(AND(ISNUMBER(C31),ISNUMBER(B31)),B31,0)+IF(AND(ISNUMBER(C32),ISNUMBER(B32)),B32,0)+IF(AND(ISNUMBER(C33),ISNUMBER(B33)),B33,0)+IF(AND(ISNUMBER(C34),ISNUMBER(B34)),B34,0)+IF(AND(ISNUMBER(C35),ISNUMBER(B35)),B35,0))=0,"",(IF(AND(ISNUMBER(C29),ISNUMBER(B29)),C29*B29,0)+IF(AND(ISNUMBER(C30),ISNUMBER(B30)),C30*B30,0)+IF(AND(ISNUMBER(C31),ISNUMBER(B31)),C31*B31,0)+IF(AND(ISNUMBER(C32),ISNUMBER(B32)),C32*B32,0)+IF(AND(ISNUMBER(C33),ISNUMBER(B33)),C33*B33,0)+IF(AND(ISNUMBER(C34),ISNUMBER(B34)),C34*B34,0)+IF(AND(ISNUMBER(C35),ISNUMBER(B35)),C35*B35,0))/(IF(AND(ISNUMBER(C29),ISNUMBER(B29)),B29,0)+IF(AND(ISNUMBER(C30),ISNUMBER(B30)),B30,0)+IF(AND(ISNUMBER(C31),ISNUMBER(B31)),B31,0)+IF(AND(ISNUMBER(C32),ISNUMBER(B32)),B32,0)+IF(AND(ISNUMBER(C33),ISNUMBER(B33)),B33,0)+IF(AND(ISNUMBER(C34),ISNUMBER(B34)),B34,0)+IF(AND(ISNUMBER(C35),ISNUMBER(B35)),B35,0))) | D36: =IF(COUNT(D29:D35)=0,"",SUM(D29:D35)) | F36: =IF((IF(AND(ISNUMBER(F29),ISNUMBER(B29)),B29,0)+IF(AND(ISNUMBER(F30),ISNUMBER(B30)),B30,0)+IF(AND(ISNUMBER(F31),ISNUMBER(B31)),B31,0)+IF(AND(ISNUMBER(F32),ISNUMBER(B32)),B32,0)+IF(AND(ISNUMBER(F33),ISNUMBER(B33)),B33,0)+IF(AND(ISNUMBER(F34),ISNUMBER(B34)),B34,0)+IF(AND(ISNUMBER(F35),ISNUMBER(B35)),B35,0))=0,"",(IF(AND(ISNUMBER(F29),ISNUMBER(B29)),F29*B29,0)+IF(AND(ISNUMBER(F30),ISNUMBER(B30)),F30*B30,0)+IF(AND(ISNUMBER(F31),ISNUMBER(B31)),F31*B31,0)+IF(AND(ISNUMBER(F32),ISNUMBER(B32)),F32*B32,0)+IF(AND(ISNUMBER(F33),ISNUMBER(B33)),F33*B33,0)+IF(AND(ISNUMBER(F34),ISNUMBER(B34)),F34*B34,0)+IF(AND(ISNUMBER(F35),ISNUMBER(B35)),F35*B35,0))/(IF(AND(ISNUMBER(F29),ISNUMBER(B29)),B29,0)+IF(AND(ISNUMBER(F30),ISNUMBER(B30)),B30,0)+IF(AND(ISNUMBER(F31),ISNUMBER(B31)),B31,0)+IF(AND(ISNUMBER(F32),ISNUMBER(B32)),B32,0)+IF(AND(ISNUMBER(F33),ISNUMBER(B33)),B33,0)+IF(AND(ISNUMBER(F34),ISNUMBER(B34)),B34,0)+IF(AND(ISNUMBER(F35),ISNUMBER(B35)),B35,0))) | G36: =IF((IF(AND(ISNUMBER(G29),ISNUMBER(B29)),B29,0)+IF(AND(ISNUMBER(G30),ISNUMBER(B30)),B30,0)+IF(AND(ISNUMBER(G31),ISNUMBER(B31)),B31,0)+IF(AND(ISNUMBER(G32),ISNUMBER(B32)),B32,0)+IF(AND(ISNUMBER(G33),ISNUMBER(B33)),B33,0)+IF(AND(ISNUMBER(G34),ISNUMBER(B34)),B34,0)+IF(AND(ISNUMBER(G35),ISNUMBER(B35)),B35,0))=0,"",(IF(AND(ISNUMBER(G29),ISNUMBER(B29)),G29*B29,0)+IF(AND(ISNUMBER(G30),ISNUMBER(B30)),G30*B30,0)+IF(AND(ISNUMBER(G31),ISNUMBER(B31)),G31*B31,0)+IF(AND(ISNUMBER(G32),ISNUMBER(B32)),G32*B32,0)+IF(AND(ISNUMBER(G33),ISNUMBER(B33)),G33*B33,0)+IF(AND(ISNUMBER(G34),ISNUMBER(B34)),G34*B34,0)+IF(AND(ISNUMBER(G35),ISNUMBER(B35)),G35*B35,0))/(IF(AND(ISNUMBER(G29),ISNUMBER(B29)),B29,0)+IF(AND(ISNUMBER(G30),ISNUMBER(B30)),B30,0)+IF(AND(ISNUMBER(G31),ISNUMBER(B31)),B31,0)+IF(AND(ISNUMBER(G32),ISNUMBER(B32)),B32,0)+IF(AND(ISNUMBER(G33),ISNUMBER(B33)),B33,0)+IF(AND(ISNUMBER(G34),ISNUMBER(B34)),B34,0)+IF(AND(ISNUMBER(G35),ISNUMBER(B35)),B35,0))) | H36: =IF((IF(AND(ISNUMBER(H29),ISNUMBER(B29)),B29,0)+IF(AND(ISNUMBER(H30),ISNUMBER(B30)),B30,0)+IF(AND(ISNUMBER(H31),ISNUMBER(B31)),B31,0)+IF(AND(ISNUMBER(H32),ISNUMBER(B32)),B32,0)+IF(AND(ISNUMBER(H33),ISNUMBER(B33)),B33,0)+IF(AND(ISNUMBER(H34),ISNUMBER(B34)),B34,0)+IF(AND(ISNUMBER(H35),ISNUMBER(B35)),B35,0))=0,"",(IF(AND(ISNUMBER(H29),ISNUMBER(B29)),H29*B29,0)+IF(AND(ISNUMBER(H30),ISNUMBER(B30)),H30*B30,0)+IF(AND(ISNUMBER(H31),ISNUMBER(B31)),H31*B31,0)+IF(AND(ISNUMBER(H32),ISNUMBER(B32)),H32*B32,0)+IF(AND(ISNUMBER(H33),ISNUMBER(B33)),H33*B33,0)+IF(AND(ISNUMBER(H34),ISNUMBER(B34)),H34*B34,0)+IF(AND(ISNUMBER(H35),ISNUMBER(B35)),H35*B35,0))/(IF(AND(ISNUMBER(H29),ISNUMBER(B29)),B29,0)+IF(AND(ISNUMBER(H30),ISNUMBER(B30)),B30,0)+IF(AND(ISNUMBER(H31),ISNUMBER(B31)),B31,0)+IF(AND(ISNUMBER(H32),ISNUMBER(B32)),B32,0)+IF(AND(ISNUMBER(H33),ISNUMBER(B33)),B33,0)+IF(AND(ISNUMBER(H34),ISNUMBER(B34)),B34,0)+IF(AND(ISNUMBER(H35),ISNUMBER(B35)),B35,0))) | M36: =IF((IF(AND(ISNUMBER(M29),ISNUMBER(B29)),B29,0)+IF(AND(ISNUMBER(M30),ISNUMBER(B30)),B30,0)+IF(AND(ISNUMBER(M31),ISNUMBER(B31)),B31,0)+IF(AND(ISNUMBER(M32),ISNUMBER(B32)),B32,0)+IF(AND(ISNUMBER(M33),ISNUMBER(B33)),B33,0)+IF(AND(ISNUMBER(M34),ISNUMBER(B34)),B34,0)+IF(AND(ISNUMBER(M35),ISNUMBER(B35)),B35,0))=0,"",(IF(AND(ISNUMBER(M29),ISNUMBER(B29)),M29*B29,0)+IF(AND(ISNUMBER(M30),ISNUMBER(B30)),M30*B30,0)+IF(AND(ISNUMBER(M31),ISNUMBER(B31)),M31*B31,0)+IF(AND(ISNUMBER(M32),ISNUMBER(B32)),M32*B32,0)+IF(AND(ISNUMBER(M33),ISNUMBER(B33)),M33*B33,0)+IF(AND(ISNUMBER(M34),ISNUMBER(B34)),M34*B34,0)+IF(AND(ISNUMBER(M35),ISNUMBER(B35)),M35*B35,0))/(IF(AND(ISNUMBER(M29),ISNUMBER(B29)),B29,0)+IF(AND(ISNUMBER(M30),ISNUMBER(B30)),B30,0)+IF(AND(ISNUMBER(M31),ISNUMBER(B31)),B31,0)+IF(AND(ISNUMBER(M32),ISNUMBER(B32)),B32,0)+IF(AND(ISNUMBER(M33),ISNUMBER(B33)),B33,0)+IF(AND(ISNUMBER(M34),ISNUMBER(B34)),B34,0)+IF(AND(ISNUMBER(M35),ISNUMBER(B35)),B35,0))) | O36: =IF((IF(AND(ISNUMBER(O29),ISNUMBER(B29)),B29,0)+IF(AND(ISNUMBER(O30),ISNUMBER(B30)),B30,0)+IF(AND(ISNUMBER(O31),ISNUMBER(B31)),B31,0)+IF(AND(ISNUMBER(O32),ISNUMBER(B32)),B32,0)+IF(AND(ISNUMBER(O33),ISNUMBER(B33)),B33,0)+IF(AND(ISNUMBER(O34),ISNUMBER(B34)),B34,0)+IF(AND(ISNUMBER(O35),ISNUMBER(B35)),B35,0))=0,"",(IF(AND(ISNUMBER(O29),ISNUMBER(B29)),O29*B29,0)+IF(AND(ISNUMBER(O30),ISNUMBER(B30)),O30*B30,0)+IF(AND(ISNUMBER(O31),ISNUMBER(B31)),O31*B31,0)+IF(AND(ISNUMBER(O32),ISNUMBER(B32)),O32*B32,0)+IF(AND(ISNUMBER(O33),ISNUMBER(B33)),O33*B33,0)+IF(AND(ISNUMBER(O34),ISNUMBER(B34)),O34*B34,0)+IF(AND(ISNUMBER(O35),ISNUMBER(B35)),O35*B35,0))/(IF(AND(ISNUMBER(O29),ISNUMBER(B29)),B29,0)+IF(AND(ISNUMBER(O30),ISNUMBER(B30)),B30,0)+IF(AND(ISNUMBER(O31),ISNUMBER(B31)),B31,0)+IF(AND(ISNUMBER(O32),ISNUMBER(B32)),B32,0)+IF(AND(ISNUMBER(O33),ISNUMBER(B33)),B33,0)+IF(AND(ISNUMBER(O34),ISNUMBER(B34)),B34,0)+IF(AND(ISNUMBER(O35),ISNUMBER(B35)),B35,0))) | U36: =IF((IF(AND(ISNUMBER(U29),ISNUMBER(B29)),B29,0)+IF(AND(ISNUMBER(U30),ISNUMBER(B30)),B30,0)+IF(AND(ISNUMBER(U31),ISNUMBER(B31)),B31,0)+IF(AND(ISNUMBER(U32),ISNUMBER(B32)),B32,0)+IF(AND(ISNUMBER(U33),ISNUMBER(B33)),B33,0)+IF(AND(ISNUMBER(U34),ISNUMBER(B34)),B34,0)+IF(AND(ISNUMBER(U35),ISNUMBER(B35)),B35,0))=0,"",(IF(AND(ISNUMBER(U29),ISNUMBER(B29)),U29*B29,0)+IF(AND(ISNUMBER(U30),ISNUMBER(B30)),U30*B30,0)+IF(AND(ISNUMBER(U31),ISNUMBER(B31)),U31*B31,0)+IF(AND(ISNUMBER(U32),ISNUMBER(B32)),U32*B32,0)+IF(AND(ISNUMBER(U33),ISNUMBER(B33)),U33*B33,0)+IF(AND(ISNUMBER(U34),ISNUMBER(B34)),U34*B34,0)+IF(AND(ISNUMBER(U35),ISNUMBER(B35)),U35*B35,0))/(IF(AND(ISNUMBER(U29),ISNUMBER(B29)),B29,0)+IF(AND(ISNUMBER(U30),ISNUMBER(B30)),B30,0)+IF(AND(ISNUMBER(U31),ISNUMBER(B31)),B31,0)+IF(AND(ISNUMBER(U32),ISNUMBER(B32)),B32,0)+IF(AND(ISNUMBER(U33),ISNUMBER(B33)),B33,0)+IF(AND(ISNUMBER(U34),ISNUMBER(B34)),B34,0)+IF(AND(ISNUMBER(U35),ISNUMBER(B35)),B35,0))) | W36: =IF((IF(AND(ISNUMBER(W29),ISNUMBER(B29)),B29,0)+IF(AND(ISNUMBER(W30),ISNUMBER(B30)),B30,0)+IF(AND(ISNUMBER(W31),ISNUMBER(B31)),B31,0)+IF(AND(ISNUMBER(W32),ISNUMBER(B32)),B32,0)+IF(AND(ISNUMBER(W33),ISNUMBER(B33)),B33,0)+IF(AND(ISNUMBER(W34),ISNUMBER(B34)),B34,0)+IF(AND(ISNUMBER(W35),ISNUMBER(B35)),B35,0))=0,"",(IF(AND(ISNUMBER(W29),ISNUMBER(B29)),W29*B29,0)+IF(AND(ISNUMBER(W30),ISNUMBER(B30)),W30*B30,0)+IF(AND(ISNUMBER(W31),ISNUMBER(B31)),W31*B31,0)+IF(AND(ISNUMBER(W32),ISNUMBER(B32)),W32*B32,0)+IF(AND(ISNUMBER(W33),ISNUMBER(B33)),W33*B33,0)+IF(AND(ISNUMBER(W34),ISNUMBER(B34)),W34*B34,0)+IF(AND(ISNUMBER(W35),ISNUMBER(B35)),W35*B35,0))/(IF(AND(ISNUMBER(W29),ISNUMBER(B29)),B29,0)+IF(AND(ISNUMBER(W30),ISNUMBER(B30)),B30,0)+IF(AND(ISNUMBER(W31),ISNUMBER(B31)),B31,0)+IF(AND(ISNUMBER(W32),ISNUMBER(B32)),B32,0)+IF(AND(ISNUMBER(W33),ISNUMBER(B33)),B33,0)+IF(AND(ISNUMBER(W34),ISNUMBER(B34)),B34,0)+IF(AND(ISNUMBER(W35),ISNUMBER(B35)),B35,0))) | Y36: =IF(COUNT(Y29:Y35)=0,"",SUM(Y29:Y35)) | Z36: =IF((IF(AND(ISNUMBER(Z29),ISNUMBER(B29)),B29,0)+IF(AND(ISNUMBER(Z30),ISNUMBER(B30)),B30,0)+IF(AND(ISNUMBER(Z31),ISNUMBER(B31)),B31,0)+IF(AND(ISNUMBER(Z32),ISNUMBER(B32)),B32,0)+IF(AND(ISNUMBER(Z33),ISNUMBER(B33)),B33,0)+IF(AND(ISNUMBER(Z34),ISNUMBER(B34)),B34,0)+IF(AND(ISNUMBER(Z35),ISNUMBER(B35)),B35,0))=0,"",(IF(AND(ISNUMBER(Z29),ISNUMBER(B29)),Z29*B29,0)+IF(AND(ISNUMBER(Z30),ISNUMBER(B30)),Z30*B30,0)+IF(AND(ISNUMBER(Z31),ISNUMBER(B31)),Z31*B31,0)+IF(AND(ISNUMBER(Z32),ISNUMBER(B32)),Z32*B32,0)+IF(AND(ISNUMBER(Z33),ISNUMBER(B33)),Z33*B33,0)+IF(AND(ISNUMBER(Z34),ISNUMBER(B34)),Z34*B34,0)+IF(AND(ISNUMBER(Z35),ISNUMBER(B35)),Z35*B35,0))/(IF(AND(ISNUMBER(Z29),ISNUMBER(B29)),B29,0)+IF(AND(ISNUMBER(Z30),ISNUMBER(B30)),B30,0)+IF(AND(ISNUMBER(Z31),ISNUMBER(B31)),B31,0)+IF(AND(ISNUMBER(Z32),ISNUMBER(B32)),B32,0)+IF(AND(ISNUMBER(Z33),ISNUMBER(B33)),B33,0)+IF(AND(ISNUMBER(Z34),ISNUMBER(B34)),B34,0)+IF(AND(ISNUMBER(Z35),ISNUMBER(B35)),B35,0))) | AB36: =IF((IF(AND(ISNUMBER(AB29),ISNUMBER(B29)),B29,0)+IF(AND(ISNUMBER(AB30),ISNUMBER(B30)),B30,0)+IF(AND(ISNUMBER(AB31),ISNUMBER(B31)),B31,0)+IF(AND(ISNUMBER(AB32),ISNUMBER(B32)),B32,0)+IF(AND(ISNUMBER(AB33),ISNUMBER(B33)),B33,0)+IF(AND(ISNUMBER(AB34),ISNUMBER(B34)),B34,0)+IF(AND(ISNUMBER(AB35),ISNUMBER(B35)),B35,0))=0,"",(IF(AND(ISNUMBER(AB29),ISNUMBER(B29)),AB29*B29,0)+IF(AND(ISNUMBER(AB30),ISNUMBER(B30)),AB30*B30,0)+IF(AND(ISNUMBER(AB31),ISNUMBER(B31)),AB31*B31,0)+IF(AND(ISNUMBER(AB32),ISNUMBER(B32)),AB32*B32,0)+IF(AND(ISNUMBER(AB33),ISNUMBER(B33)),AB33*B33,0)+IF(AND(ISNUMBER(AB34),ISNUMBER(B34)),AB34*B34,0)+IF(AND(ISNUMBER(AB35),ISNUMBER(B35)),AB35*B35,0))/(IF(AND(ISNUMBER(AB29),ISNUMBER(B29)),B29,0)+IF(AND(ISNUMBER(AB30),ISNUMBER(B30)),B30,0)+IF(AND(ISNUMBER(AB31),ISNUMBER(B31)),B31,0)+IF(AND(ISNUMBER(AB32),ISNUMBER(B32)),B32,0)+IF(AND(ISNUMBER(AB33),ISNUMBER(B33)),B33,0)+IF(AND(ISNUMBER(AB34),ISNUMBER(B34)),B34,0)+IF(AND(ISNUMBER(AB35),ISNUMBER(B35)),B35,0))) | AD36: =IF((IF(AND(ISNUMBER(AD29),ISNUMBER(B29)),B29,0)+IF(AND(ISNUMBER(AD30),ISNUMBER(B30)),B30,0)+IF(AND(ISNUMBER(AD31),ISNUMBER(B31)),B31,0)+IF(AND(ISNUMBER(AD32),ISNUMBER(B32)),B32,0)+IF(AND(ISNUMBER(AD33),ISNUMBER(B33)),B33,0)+IF(AND(ISNUMBER(AD34),ISNUMBER(B34)),B34,0)+IF(AND(ISNUMBER(AD35),ISNUMBER(B35)),B35,0))=0,"",(IF(AND(ISNUMBER(AD29),ISNUMBER(B29)),AD29*B29,0)+IF(AND(ISNUMBER(AD30),ISNUMBER(B30)),AD30*B30,0)+IF(AND(ISNUMBER(AD31),ISNUMBER(B31)),AD31*B31,0)+IF(AND(ISNUMBER(AD32),ISNUMBER(B32)),AD32*B32,0)+IF(AND(ISNUMBER(AD33),ISNUMBER(B33)),AD33*B33,0)+IF(AND(ISNUMBER(AD34),ISNUMBER(B34)),AD34*B34,0)+IF(AND(ISNUMBER(AD35),ISNUMBER(B35)),AD35*B35,0))/(IF(AND(ISNUMBER(AD29),ISNUMBER(B29)),B29,0)+IF(AND(ISNUMBER(AD30),ISNUMBER(B30)),B30,0)+IF(AND(ISNUMBER(AD31),ISNUMBER(B31)),B31,0)+IF(AND(ISNUMBER(AD32),ISNUMBER(B32)),B32,0)+IF(AND(ISNUMBER(AD33),ISNUMBER(B33)),B33,0)+IF(AND(ISNUMBER(AD34),ISNUMBER(B34)),B34,0)+IF(AND(ISNUMBER(AD35),ISNUMBER(B35)),B35,0))) | AF36: =IF(OR(NOT(ISNUMBER(B36)),B36=0),"",AG36/B36) | AG36: =IF(COUNT(AG29:AG35)=0,"",SUM(AG29:AG35))
A38: 46320 | B38: =IF(OR(ISNUMBER('Provincia Venta Diaria'!J26),ISNUMBER('Provincia Venta Diaria'!K26)),(IF(ISNUMBER('Provincia Venta Diaria'!J26),'Provincia Venta Diaria'!J26,0)+IF(ISNUMBER('Provincia Venta Diaria'!K26),'Provincia Venta Diaria'!K26,0))*1000,"") | C38: =IF(AND(ISNUMBER(PRECIO!B26),ISNUMBER(PRECIO!B26)),PRECIO!B26,"") | D38: =IF(AND(ISNUMBER(C38),ISNUMBER(B38)),C38*B38,"") | H38: =IF(AND(ISNUMBER(C38),ISNUMBER(F38),ISNUMBER(G38)),C38-F38-G38,"") | O38: =IF(ISNUMBER(H38),H38,"") | W38: =IF(ISNUMBER(O38),O38,"") | Z38: =IF(AND(ISNUMBER(Y38),ISNUMBER(B38),B38<>0),Y38/B38,"") | AB38: =IF(AND(ISNUMBER(W38),ISNUMBER(Z38)),W38-Z38,"") | AD38: =IF(AND(ISNUMBER('Provincia Comisiones'!B26),ISNUMBER('Provincia Comisiones'!B26)),'Provincia Comisiones'!B26,"") | AF38: =IF(AND(ISNUMBER(AB38),ISNUMBER(AD38)),AB38+AD38,"") | AG38: =IF(AND(ISNUMBER(AF38),ISNUMBER(B38)),AF38*B38,"")
A39: 46321 | B39: =IF(OR(ISNUMBER('Provincia Venta Diaria'!J27),ISNUMBER('Provincia Venta Diaria'!K27)),(IF(ISNUMBER('Provincia Venta Diaria'!J27),'Provincia Venta Diaria'!J27,0)+IF(ISNUMBER('Provincia Venta Diaria'!K27),'Provincia Venta Diaria'!K27,0))*1000,"") | C39: =IF(AND(ISNUMBER(PRECIO!B27),ISNUMBER(PRECIO!B27)),PRECIO!B27,"") | D39: =IF(AND(ISNUMBER(C39),ISNUMBER(B39)),C39*B39,"") | H39: =IF(AND(ISNUMBER(C39),ISNUMBER(F39),ISNUMBER(G39)),C39-F39-G39,"") | M39: =IF(AND(ISNUMBER($M$3),ISNUMBER(B39),B39<>0),($M$3/27)/B39,"") | O39: =IF(AND(ISNUMBER(H39),ISNUMBER(M39)),H39-M39,"") | U39: =IF(AND(ISNUMBER($U$3),ISNUMBER(B39),B39<>0),($U$3/27)/B39,"") | W39: =IF(AND(ISNUMBER(O39),ISNUMBER(U39)),O39-U39,"") | Z39: =IF(AND(ISNUMBER(Y39),ISNUMBER(B39),B39<>0),Y39/B39,"") | AB39: =IF(AND(ISNUMBER(W39),ISNUMBER(Z39)),W39-Z39,"") | AD39: =IF(AND(ISNUMBER('Provincia Comisiones'!B27),ISNUMBER('Provincia Comisiones'!B27)),'Provincia Comisiones'!B27,"") | AF39: =IF(AND(ISNUMBER(AB39),ISNUMBER(AD39)),AB39+AD39,"") | AG39: =IF(AND(ISNUMBER(AF39),ISNUMBER(B39)),AF39*B39,"")
A40: 46322 | B40: =IF(OR(ISNUMBER('Provincia Venta Diaria'!J28),ISNUMBER('Provincia Venta Diaria'!K28)),(IF(ISNUMBER('Provincia Venta Diaria'!J28),'Provincia Venta Diaria'!J28,0)+IF(ISNUMBER('Provincia Venta Diaria'!K28),'Provincia Venta Diaria'!K28,0))*1000,"") | C40: =IF(AND(ISNUMBER(PRECIO!B28),ISNUMBER(PRECIO!B28)),PRECIO!B28,"") | D40: =IF(AND(ISNUMBER(C40),ISNUMBER(B40)),C40*B40,"") | H40: =IF(AND(ISNUMBER(C40),ISNUMBER(F40),ISNUMBER(G40)),C40-F40-G40,"") | M40: =IF(AND(ISNUMBER($M$3),ISNUMBER(B40),B40<>0),($M$3/27)/B40,"") | O40: =IF(AND(ISNUMBER(H40),ISNUMBER(M40)),H40-M40,"") | U40: =IF(AND(ISNUMBER($U$3),ISNUMBER(B40),B40<>0),($U$3/27)/B40,"") | W40: =IF(AND(ISNUMBER(O40),ISNUMBER(U40)),O40-U40,"") | Z40: =IF(AND(ISNUMBER(Y40),ISNUMBER(B40),B40<>0),Y40/B40,"") | AB40: =IF(AND(ISNUMBER(W40),ISNUMBER(Z40)),W40-Z40,"") | AD40: =IF(AND(ISNUMBER('Provincia Comisiones'!B28),ISNUMBER('Provincia Comisiones'!B28)),'Provincia Comisiones'!B28,"") | AF40: =IF(AND(ISNUMBER(AB40),ISNUMBER(AD40)),AB40+AD40,"") | AG40: =IF(AND(ISNUMBER(AF40),ISNUMBER(B40)),AF40*B40,"")
A41: 46323 | B41: =IF(OR(ISNUMBER('Provincia Venta Diaria'!J29),ISNUMBER('Provincia Venta Diaria'!K29)),(IF(ISNUMBER('Provincia Venta Diaria'!J29),'Provincia Venta Diaria'!J29,0)+IF(ISNUMBER('Provincia Venta Diaria'!K29),'Provincia Venta Diaria'!K29,0))*1000,"") | C41: =IF(AND(ISNUMBER(PRECIO!B29),ISNUMBER(PRECIO!B29)),PRECIO!B29,"") | D41: =IF(AND(ISNUMBER(C41),ISNUMBER(B41)),C41*B41,"") | H41: =IF(AND(ISNUMBER(C41),ISNUMBER(F41),ISNUMBER(G41)),C41-F41-G41,"") | M41: =IF(AND(ISNUMBER($M$3),ISNUMBER(B41),B41<>0),($M$3/27)/B41,"") | O41: =IF(AND(ISNUMBER(H41),ISNUMBER(M41)),H41-M41,"") | U41: =IF(AND(ISNUMBER($U$3),ISNUMBER(B41),B41<>0),($U$3/27)/B41,"") | W41: =IF(AND(ISNUMBER(O41),ISNUMBER(U41)),O41-U41,"") | Z41: =IF(AND(ISNUMBER(Y41),ISNUMBER(B41),B41<>0),Y41/B41,"") | AB41: =IF(AND(ISNUMBER(W41),ISNUMBER(Z41)),W41-Z41,"") | AD41: =IF(AND(ISNUMBER('Provincia Comisiones'!B29),ISNUMBER('Provincia Comisiones'!B29)),'Provincia Comisiones'!B29,"") | AF41: =IF(AND(ISNUMBER(AB41),ISNUMBER(AD41)),AB41+AD41,"") | AG41: =IF(AND(ISNUMBER(AF41),ISNUMBER(B41)),AF41*B41,"")
A42: 46324 | B42: =IF(OR(ISNUMBER('Provincia Venta Diaria'!J30),ISNUMBER('Provincia Venta Diaria'!K30)),(IF(ISNUMBER('Provincia Venta Diaria'!J30),'Provincia Venta Diaria'!J30,0)+IF(ISNUMBER('Provincia Venta Diaria'!K30),'Provincia Venta Diaria'!K30,0))*1000,"") | C42: =IF(AND(ISNUMBER(PRECIO!B30),ISNUMBER(PRECIO!B30)),PRECIO!B30,"") | D42: =IF(AND(ISNUMBER(C42),ISNUMBER(B42)),C42*B42,"") | H42: =IF(AND(ISNUMBER(C42),ISNUMBER(F42),ISNUMBER(G42)),C42-F42-G42,"") | M42: =IF(AND(ISNUMBER($M$3),ISNUMBER(B42),B42<>0),($M$3/27)/B42,"") | O42: =IF(AND(ISNUMBER(H42),ISNUMBER(M42)),H42-M42,"") | U42: =IF(AND(ISNUMBER($U$3),ISNUMBER(B42),B42<>0),($U$3/27)/B42,"") | W42: =IF(AND(ISNUMBER(O42),ISNUMBER(U42)),O42-U42,"") | Z42: =IF(AND(ISNUMBER(Y42),ISNUMBER(B42),B42<>0),Y42/B42,"") | AB42: =IF(AND(ISNUMBER(W42),ISNUMBER(Z42)),W42-Z42,"") | AD42: =IF(AND(ISNUMBER('Provincia Comisiones'!B30),ISNUMBER('Provincia Comisiones'!B30)),'Provincia Comisiones'!B30,"") | AF42: =IF(AND(ISNUMBER(AB42),ISNUMBER(AD42)),AB42+AD42,"") | AG42: =IF(AND(ISNUMBER(AF42),ISNUMBER(B42)),AF42*B42,"")
A43: 46325 | B43: =IF(OR(ISNUMBER('Provincia Venta Diaria'!J31),ISNUMBER('Provincia Venta Diaria'!K31)),(IF(ISNUMBER('Provincia Venta Diaria'!J31),'Provincia Venta Diaria'!J31,0)+IF(ISNUMBER('Provincia Venta Diaria'!K31),'Provincia Venta Diaria'!K31,0))*1000,"") | C43: =IF(AND(ISNUMBER(PRECIO!B31),ISNUMBER(PRECIO!B31)),PRECIO!B31,"") | D43: =IF(AND(ISNUMBER(C43),ISNUMBER(B43)),C43*B43,"") | H43: =IF(AND(ISNUMBER(C43),ISNUMBER(F43),ISNUMBER(G43)),C43-F43-G43,"") | M43: =IF(AND(ISNUMBER($M$3),ISNUMBER(B43),B43<>0),($M$3/27)/B43,"") | O43: =IF(AND(ISNUMBER(H43),ISNUMBER(M43)),H43-M43,"") | U43: =IF(AND(ISNUMBER($U$3),ISNUMBER(B43),B43<>0),($U$3/27)/B43,"") | W43: =IF(AND(ISNUMBER(O43),ISNUMBER(U43)),O43-U43,"") | Z43: =IF(AND(ISNUMBER(Y43),ISNUMBER(B43),B43<>0),Y43/B43,"") | AB43: =IF(AND(ISNUMBER(W43),ISNUMBER(Z43)),W43-Z43,"") | AD43: =IF(AND(ISNUMBER('Provincia Comisiones'!B31),ISNUMBER('Provincia Comisiones'!B31)),'Provincia Comisiones'!B31,"") | AF43: =IF(AND(ISNUMBER(AB43),ISNUMBER(AD43)),AB43+AD43,"") | AG43: =IF(AND(ISNUMBER(AF43),ISNUMBER(B43)),AF43*B43,"")
A44: 46326 | B44: =IF(OR(ISNUMBER('Provincia Venta Diaria'!J32),ISNUMBER('Provincia Venta Diaria'!K32)),(IF(ISNUMBER('Provincia Venta Diaria'!J32),'Provincia Venta Diaria'!J32,0)+IF(ISNUMBER('Provincia Venta Diaria'!K32),'Provincia Venta Diaria'!K32,0))*1000,"") | C44: =IF(AND(ISNUMBER(PRECIO!B32),ISNUMBER(PRECIO!B32)),PRECIO!B32,"") | D44: =IF(AND(ISNUMBER(C44),ISNUMBER(B44)),C44*B44,"") | H44: =IF(AND(ISNUMBER(C44),ISNUMBER(F44),ISNUMBER(G44)),C44-F44-G44,"") | M44: =IF(AND(ISNUMBER($M$3),ISNUMBER(B44),B44<>0),($M$3/27)/B44,"") | O44: =IF(AND(ISNUMBER(H44),ISNUMBER(M44)),H44-M44,"") | U44: =IF(AND(ISNUMBER($U$3),ISNUMBER(B44),B44<>0),($U$3/27)/B44,"") | W44: =IF(AND(ISNUMBER(O44),ISNUMBER(U44)),O44-U44,"") | Z44: =IF(AND(ISNUMBER(Y44),ISNUMBER(B44),B44<>0),Y44/B44,"") | AB44: =IF(AND(ISNUMBER(W44),ISNUMBER(Z44)),W44-Z44,"") | AD44: =IF(AND(ISNUMBER('Provincia Comisiones'!B32),ISNUMBER('Provincia Comisiones'!B32)),'Provincia Comisiones'!B32,"") | AF44: =IF(AND(ISNUMBER(AB44),ISNUMBER(AD44)),AB44+AD44,"") | AG44: =IF(AND(ISNUMBER(AF44),ISNUMBER(B44)),AF44*B44,"")
A46: Semana 44 | B46: =IF(COUNT(B38:B44)=0,"",SUM(B38:B44)) | C46: =IF((IF(AND(ISNUMBER(C38),ISNUMBER(B38)),B38,0)+IF(AND(ISNUMBER(C39),ISNUMBER(B39)),B39,0)+IF(AND(ISNUMBER(C40),ISNUMBER(B40)),B40,0)+IF(AND(ISNUMBER(C41),ISNUMBER(B41)),B41,0)+IF(AND(ISNUMBER(C42),ISNUMBER(B42)),B42,0)+IF(AND(ISNUMBER(C43),ISNUMBER(B43)),B43,0)+IF(AND(ISNUMBER(C44),ISNUMBER(B44)),B44,0))=0,"",(IF(AND(ISNUMBER(C38),ISNUMBER(B38)),C38*B38,0)+IF(AND(ISNUMBER(C39),ISNUMBER(B39)),C39*B39,0)+IF(AND(ISNUMBER(C40),ISNUMBER(B40)),C40*B40,0)+IF(AND(ISNUMBER(C41),ISNUMBER(B41)),C41*B41,0)+IF(AND(ISNUMBER(C42),ISNUMBER(B42)),C42*B42,0)+IF(AND(ISNUMBER(C43),ISNUMBER(B43)),C43*B43,0)+IF(AND(ISNUMBER(C44),ISNUMBER(B44)),C44*B44,0))/(IF(AND(ISNUMBER(C38),ISNUMBER(B38)),B38,0)+IF(AND(ISNUMBER(C39),ISNUMBER(B39)),B39,0)+IF(AND(ISNUMBER(C40),ISNUMBER(B40)),B40,0)+IF(AND(ISNUMBER(C41),ISNUMBER(B41)),B41,0)+IF(AND(ISNUMBER(C42),ISNUMBER(B42)),B42,0)+IF(AND(ISNUMBER(C43),ISNUMBER(B43)),B43,0)+IF(AND(ISNUMBER(C44),ISNUMBER(B44)),B44,0))) | D46: =IF(COUNT(D38:D44)=0,"",SUM(D38:D44)) | F46: =IF((IF(AND(ISNUMBER(F38),ISNUMBER(B38)),B38,0)+IF(AND(ISNUMBER(F39),ISNUMBER(B39)),B39,0)+IF(AND(ISNUMBER(F40),ISNUMBER(B40)),B40,0)+IF(AND(ISNUMBER(F41),ISNUMBER(B41)),B41,0)+IF(AND(ISNUMBER(F42),ISNUMBER(B42)),B42,0)+IF(AND(ISNUMBER(F43),ISNUMBER(B43)),B43,0)+IF(AND(ISNUMBER(F44),ISNUMBER(B44)),B44,0))=0,"",(IF(AND(ISNUMBER(F38),ISNUMBER(B38)),F38*B38,0)+IF(AND(ISNUMBER(F39),ISNUMBER(B39)),F39*B39,0)+IF(AND(ISNUMBER(F40),ISNUMBER(B40)),F40*B40,0)+IF(AND(ISNUMBER(F41),ISNUMBER(B41)),F41*B41,0)+IF(AND(ISNUMBER(F42),ISNUMBER(B42)),F42*B42,0)+IF(AND(ISNUMBER(F43),ISNUMBER(B43)),F43*B43,0)+IF(AND(ISNUMBER(F44),ISNUMBER(B44)),F44*B44,0))/(IF(AND(ISNUMBER(F38),ISNUMBER(B38)),B38,0)+IF(AND(ISNUMBER(F39),ISNUMBER(B39)),B39,0)+IF(AND(ISNUMBER(F40),ISNUMBER(B40)),B40,0)+IF(AND(ISNUMBER(F41),ISNUMBER(B41)),B41,0)+IF(AND(ISNUMBER(F42),ISNUMBER(B42)),B42,0)+IF(AND(ISNUMBER(F43),ISNUMBER(B43)),B43,0)+IF(AND(ISNUMBER(F44),ISNUMBER(B44)),B44,0))) | G46: =IF((IF(AND(ISNUMBER(G38),ISNUMBER(B38)),B38,0)+IF(AND(ISNUMBER(G39),ISNUMBER(B39)),B39,0)+IF(AND(ISNUMBER(G40),ISNUMBER(B40)),B40,0)+IF(AND(ISNUMBER(G41),ISNUMBER(B41)),B41,0)+IF(AND(ISNUMBER(G42),ISNUMBER(B42)),B42,0)+IF(AND(ISNUMBER(G43),ISNUMBER(B43)),B43,0)+IF(AND(ISNUMBER(G44),ISNUMBER(B44)),B44,0))=0,"",(IF(AND(ISNUMBER(G38),ISNUMBER(B38)),G38*B38,0)+IF(AND(ISNUMBER(G39),ISNUMBER(B39)),G39*B39,0)+IF(AND(ISNUMBER(G40),ISNUMBER(B40)),G40*B40,0)+IF(AND(ISNUMBER(G41),ISNUMBER(B41)),G41*B41,0)+IF(AND(ISNUMBER(G42),ISNUMBER(B42)),G42*B42,0)+IF(AND(ISNUMBER(G43),ISNUMBER(B43)),G43*B43,0)+IF(AND(ISNUMBER(G44),ISNUMBER(B44)),G44*B44,0))/(IF(AND(ISNUMBER(G38),ISNUMBER(B38)),B38,0)+IF(AND(ISNUMBER(G39),ISNUMBER(B39)),B39,0)+IF(AND(ISNUMBER(G40),ISNUMBER(B40)),B40,0)+IF(AND(ISNUMBER(G41),ISNUMBER(B41)),B41,0)+IF(AND(ISNUMBER(G42),ISNUMBER(B42)),B42,0)+IF(AND(ISNUMBER(G43),ISNUMBER(B43)),B43,0)+IF(AND(ISNUMBER(G44),ISNUMBER(B44)),B44,0))) | H46: =IF((IF(AND(ISNUMBER(H38),ISNUMBER(B38)),B38,0)+IF(AND(ISNUMBER(H39),ISNUMBER(B39)),B39,0)+IF(AND(ISNUMBER(H40),ISNUMBER(B40)),B40,0)+IF(AND(ISNUMBER(H41),ISNUMBER(B41)),B41,0)+IF(AND(ISNUMBER(H42),ISNUMBER(B42)),B42,0)+IF(AND(ISNUMBER(H43),ISNUMBER(B43)),B43,0)+IF(AND(ISNUMBER(H44),ISNUMBER(B44)),B44,0))=0,"",(IF(AND(ISNUMBER(H38),ISNUMBER(B38)),H38*B38,0)+IF(AND(ISNUMBER(H39),ISNUMBER(B39)),H39*B39,0)+IF(AND(ISNUMBER(H40),ISNUMBER(B40)),H40*B40,0)+IF(AND(ISNUMBER(H41),ISNUMBER(B41)),H41*B41,0)+IF(AND(ISNUMBER(H42),ISNUMBER(B42)),H42*B42,0)+IF(AND(ISNUMBER(H43),ISNUMBER(B43)),H43*B43,0)+IF(AND(ISNUMBER(H44),ISNUMBER(B44)),H44*B44,0))/(IF(AND(ISNUMBER(H38),ISNUMBER(B38)),B38,0)+IF(AND(ISNUMBER(H39),ISNUMBER(B39)),B39,0)+IF(AND(ISNUMBER(H40),ISNUMBER(B40)),B40,0)+IF(AND(ISNUMBER(H41),ISNUMBER(B41)),B41,0)+IF(AND(ISNUMBER(H42),ISNUMBER(B42)),B42,0)+IF(AND(ISNUMBER(H43),ISNUMBER(B43)),B43,0)+IF(AND(ISNUMBER(H44),ISNUMBER(B44)),B44,0))) | M46: =IF((IF(AND(ISNUMBER(M38),ISNUMBER(B38)),B38,0)+IF(AND(ISNUMBER(M39),ISNUMBER(B39)),B39,0)+IF(AND(ISNUMBER(M40),ISNUMBER(B40)),B40,0)+IF(AND(ISNUMBER(M41),ISNUMBER(B41)),B41,0)+IF(AND(ISNUMBER(M42),ISNUMBER(B42)),B42,0)+IF(AND(ISNUMBER(M43),ISNUMBER(B43)),B43,0)+IF(AND(ISNUMBER(M44),ISNUMBER(B44)),B44,0))=0,"",(IF(AND(ISNUMBER(M38),ISNUMBER(B38)),M38*B38,0)+IF(AND(ISNUMBER(M39),ISNUMBER(B39)),M39*B39,0)+IF(AND(ISNUMBER(M40),ISNUMBER(B40)),M40*B40,0)+IF(AND(ISNUMBER(M41),ISNUMBER(B41)),M41*B41,0)+IF(AND(ISNUMBER(M42),ISNUMBER(B42)),M42*B42,0)+IF(AND(ISNUMBER(M43),ISNUMBER(B43)),M43*B43,0)+IF(AND(ISNUMBER(M44),ISNUMBER(B44)),M44*B44,0))/(IF(AND(ISNUMBER(M38),ISNUMBER(B38)),B38,0)+IF(AND(ISNUMBER(M39),ISNUMBER(B39)),B39,0)+IF(AND(ISNUMBER(M40),ISNUMBER(B40)),B40,0)+IF(AND(ISNUMBER(M41),ISNUMBER(B41)),B41,0)+IF(AND(ISNUMBER(M42),ISNUMBER(B42)),B42,0)+IF(AND(ISNUMBER(M43),ISNUMBER(B43)),B43,0)+IF(AND(ISNUMBER(M44),ISNUMBER(B44)),B44,0))) | O46: =IF((IF(AND(ISNUMBER(O38),ISNUMBER(B38)),B38,0)+IF(AND(ISNUMBER(O39),ISNUMBER(B39)),B39,0)+IF(AND(ISNUMBER(O40),ISNUMBER(B40)),B40,0)+IF(AND(ISNUMBER(O41),ISNUMBER(B41)),B41,0)+IF(AND(ISNUMBER(O42),ISNUMBER(B42)),B42,0)+IF(AND(ISNUMBER(O43),ISNUMBER(B43)),B43,0)+IF(AND(ISNUMBER(O44),ISNUMBER(B44)),B44,0))=0,"",(IF(AND(ISNUMBER(O38),ISNUMBER(B38)),O38*B38,0)+IF(AND(ISNUMBER(O39),ISNUMBER(B39)),O39*B39,0)+IF(AND(ISNUMBER(O40),ISNUMBER(B40)),O40*B40,0)+IF(AND(ISNUMBER(O41),ISNUMBER(B41)),O41*B41,0)+IF(AND(ISNUMBER(O42),ISNUMBER(B42)),O42*B42,0)+IF(AND(ISNUMBER(O43),ISNUMBER(B43)),O43*B43,0)+IF(AND(ISNUMBER(O44),ISNUMBER(B44)),O44*B44,0))/(IF(AND(ISNUMBER(O38),ISNUMBER(B38)),B38,0)+IF(AND(ISNUMBER(O39),ISNUMBER(B39)),B39,0)+IF(AND(ISNUMBER(O40),ISNUMBER(B40)),B40,0)+IF(AND(ISNUMBER(O41),ISNUMBER(B41)),B41,0)+IF(AND(ISNUMBER(O42),ISNUMBER(B42)),B42,0)+IF(AND(ISNUMBER(O43),ISNUMBER(B43)),B43,0)+IF(AND(ISNUMBER(O44),ISNUMBER(B44)),B44,0))) | U46: =IF((IF(AND(ISNUMBER(U38),ISNUMBER(B38)),B38,0)+IF(AND(ISNUMBER(U39),ISNUMBER(B39)),B39,0)+IF(AND(ISNUMBER(U40),ISNUMBER(B40)),B40,0)+IF(AND(ISNUMBER(U41),ISNUMBER(B41)),B41,0)+IF(AND(ISNUMBER(U42),ISNUMBER(B42)),B42,0)+IF(AND(ISNUMBER(U43),ISNUMBER(B43)),B43,0)+IF(AND(ISNUMBER(U44),ISNUMBER(B44)),B44,0))=0,"",(IF(AND(ISNUMBER(U38),ISNUMBER(B38)),U38*B38,0)+IF(AND(ISNUMBER(U39),ISNUMBER(B39)),U39*B39,0)+IF(AND(ISNUMBER(U40),ISNUMBER(B40)),U40*B40,0)+IF(AND(ISNUMBER(U41),ISNUMBER(B41)),U41*B41,0)+IF(AND(ISNUMBER(U42),ISNUMBER(B42)),U42*B42,0)+IF(AND(ISNUMBER(U43),ISNUMBER(B43)),U43*B43,0)+IF(AND(ISNUMBER(U44),ISNUMBER(B44)),U44*B44,0))/(IF(AND(ISNUMBER(U38),ISNUMBER(B38)),B38,0)+IF(AND(ISNUMBER(U39),ISNUMBER(B39)),B39,0)+IF(AND(ISNUMBER(U40),ISNUMBER(B40)),B40,0)+IF(AND(ISNUMBER(U41),ISNUMBER(B41)),B41,0)+IF(AND(ISNUMBER(U42),ISNUMBER(B42)),B42,0)+IF(AND(ISNUMBER(U43),ISNUMBER(B43)),B43,0)+IF(AND(ISNUMBER(U44),ISNUMBER(B44)),B44,0))) | W46: =IF((IF(AND(ISNUMBER(W38),ISNUMBER(B38)),B38,0)+IF(AND(ISNUMBER(W39),ISNUMBER(B39)),B39,0)+IF(AND(ISNUMBER(W40),ISNUMBER(B40)),B40,0)+IF(AND(ISNUMBER(W41),ISNUMBER(B41)),B41,0)+IF(AND(ISNUMBER(W42),ISNUMBER(B42)),B42,0)+IF(AND(ISNUMBER(W43),ISNUMBER(B43)),B43,0)+IF(AND(ISNUMBER(W44),ISNUMBER(B44)),B44,0))=0,"",(IF(AND(ISNUMBER(W38),ISNUMBER(B38)),W38*B38,0)+IF(AND(ISNUMBER(W39),ISNUMBER(B39)),W39*B39,0)+IF(AND(ISNUMBER(W40),ISNUMBER(B40)),W40*B40,0)+IF(AND(ISNUMBER(W41),ISNUMBER(B41)),W41*B41,0)+IF(AND(ISNUMBER(W42),ISNUMBER(B42)),W42*B42,0)+IF(AND(ISNUMBER(W43),ISNUMBER(B43)),W43*B43,0)+IF(AND(ISNUMBER(W44),ISNUMBER(B44)),W44*B44,0))/(IF(AND(ISNUMBER(W38),ISNUMBER(B38)),B38,0)+IF(AND(ISNUMBER(W39),ISNUMBER(B39)),B39,0)+IF(AND(ISNUMBER(W40),ISNUMBER(B40)),B40,0)+IF(AND(ISNUMBER(W41),ISNUMBER(B41)),B41,0)+IF(AND(ISNUMBER(W42),ISNUMBER(B42)),B42,0)+IF(AND(ISNUMBER(W43),ISNUMBER(B43)),B43,0)+IF(AND(ISNUMBER(W44),ISNUMBER(B44)),B44,0))) | Y46: =IF(COUNT(Y38:Y44)=0,"",SUM(Y38:Y44)) | Z46: =IF((IF(AND(ISNUMBER(Z38),ISNUMBER(B38)),B38,0)+IF(AND(ISNUMBER(Z39),ISNUMBER(B39)),B39,0)+IF(AND(ISNUMBER(Z40),ISNUMBER(B40)),B40,0)+IF(AND(ISNUMBER(Z41),ISNUMBER(B41)),B41,0)+IF(AND(ISNUMBER(Z42),ISNUMBER(B42)),B42,0)+IF(AND(ISNUMBER(Z43),ISNUMBER(B43)),B43,0)+IF(AND(ISNUMBER(Z44),ISNUMBER(B44)),B44,0))=0,"",(IF(AND(ISNUMBER(Z38),ISNUMBER(B38)),Z38*B38,0)+IF(AND(ISNUMBER(Z39),ISNUMBER(B39)),Z39*B39,0)+IF(AND(ISNUMBER(Z40),ISNUMBER(B40)),Z40*B40,0)+IF(AND(ISNUMBER(Z41),ISNUMBER(B41)),Z41*B41,0)+IF(AND(ISNUMBER(Z42),ISNUMBER(B42)),Z42*B42,0)+IF(AND(ISNUMBER(Z43),ISNUMBER(B43)),Z43*B43,0)+IF(AND(ISNUMBER(Z44),ISNUMBER(B44)),Z44*B44,0))/(IF(AND(ISNUMBER(Z38),ISNUMBER(B38)),B38,0)+IF(AND(ISNUMBER(Z39),ISNUMBER(B39)),B39,0)+IF(AND(ISNUMBER(Z40),ISNUMBER(B40)),B40,0)+IF(AND(ISNUMBER(Z41),ISNUMBER(B41)),B41,0)+IF(AND(ISNUMBER(Z42),ISNUMBER(B42)),B42,0)+IF(AND(ISNUMBER(Z43),ISNUMBER(B43)),B43,0)+IF(AND(ISNUMBER(Z44),ISNUMBER(B44)),B44,0))) | AB46: =IF((IF(AND(ISNUMBER(AB38),ISNUMBER(B38)),B38,0)+IF(AND(ISNUMBER(AB39),ISNUMBER(B39)),B39,0)+IF(AND(ISNUMBER(AB40),ISNUMBER(B40)),B40,0)+IF(AND(ISNUMBER(AB41),ISNUMBER(B41)),B41,0)+IF(AND(ISNUMBER(AB42),ISNUMBER(B42)),B42,0)+IF(AND(ISNUMBER(AB43),ISNUMBER(B43)),B43,0)+IF(AND(ISNUMBER(AB44),ISNUMBER(B44)),B44,0))=0,"",(IF(AND(ISNUMBER(AB38),ISNUMBER(B38)),AB38*B38,0)+IF(AND(ISNUMBER(AB39),ISNUMBER(B39)),AB39*B39,0)+IF(AND(ISNUMBER(AB40),ISNUMBER(B40)),AB40*B40,0)+IF(AND(ISNUMBER(AB41),ISNUMBER(B41)),AB41*B41,0)+IF(AND(ISNUMBER(AB42),ISNUMBER(B42)),AB42*B42,0)+IF(AND(ISNUMBER(AB43),ISNUMBER(B43)),AB43*B43,0)+IF(AND(ISNUMBER(AB44),ISNUMBER(B44)),AB44*B44,0))/(IF(AND(ISNUMBER(AB38),ISNUMBER(B38)),B38,0)+IF(AND(ISNUMBER(AB39),ISNUMBER(B39)),B39,0)+IF(AND(ISNUMBER(AB40),ISNUMBER(B40)),B40,0)+IF(AND(ISNUMBER(AB41),ISNUMBER(B41)),B41,0)+IF(AND(ISNUMBER(AB42),ISNUMBER(B42)),B42,0)+IF(AND(ISNUMBER(AB43),ISNUMBER(B43)),B43,0)+IF(AND(ISNUMBER(AB44),ISNUMBER(B44)),B44,0))) | AD46: =IF((IF(AND(ISNUMBER(AD38),ISNUMBER(B38)),B38,0)+IF(AND(ISNUMBER(AD39),ISNUMBER(B39)),B39,0)+IF(AND(ISNUMBER(AD40),ISNUMBER(B40)),B40,0)+IF(AND(ISNUMBER(AD41),ISNUMBER(B41)),B41,0)+IF(AND(ISNUMBER(AD42),ISNUMBER(B42)),B42,0)+IF(AND(ISNUMBER(AD43),ISNUMBER(B43)),B43,0)+IF(AND(ISNUMBER(AD44),ISNUMBER(B44)),B44,0))=0,"",(IF(AND(ISNUMBER(AD38),ISNUMBER(B38)),AD38*B38,0)+IF(AND(ISNUMBER(AD39),ISNUMBER(B39)),AD39*B39,0)+IF(AND(ISNUMBER(AD40),ISNUMBER(B40)),AD40*B40,0)+IF(AND(ISNUMBER(AD41),ISNUMBER(B41)),AD41*B41,0)+IF(AND(ISNUMBER(AD42),ISNUMBER(B42)),AD42*B42,0)+IF(AND(ISNUMBER(AD43),ISNUMBER(B43)),AD43*B43,0)+IF(AND(ISNUMBER(AD44),ISNUMBER(B44)),AD44*B44,0))/(IF(AND(ISNUMBER(AD38),ISNUMBER(B38)),B38,0)+IF(AND(ISNUMBER(AD39),ISNUMBER(B39)),B39,0)+IF(AND(ISNUMBER(AD40),ISNUMBER(B40)),B40,0)+IF(AND(ISNUMBER(AD41),ISNUMBER(B41)),B41,0)+IF(AND(ISNUMBER(AD42),ISNUMBER(B42)),B42,0)+IF(AND(ISNUMBER(AD43),ISNUMBER(B43)),B43,0)+IF(AND(ISNUMBER(AD44),ISNUMBER(B44)),B44,0))) | AF46: =IF(OR(NOT(ISNUMBER(B46)),B46=0),"",AG46/B46) | AG46: =IF(COUNT(AG38:AG44)=0,"",SUM(AG38:AG44))
A48: TOTAL MES | B48: =IF(COUNT(B9,B18,B27,B36,B46)=0,"",SUM(B9,B18,B27,B36,B46)) | C48: =IF((IF(AND(ISNUMBER(C6),ISNUMBER(B6)),B6,0)+IF(AND(ISNUMBER(C7),ISNUMBER(B7)),B7,0)+IF(AND(ISNUMBER(C8),ISNUMBER(B8)),B8,0)+IF(AND(ISNUMBER(C11),ISNUMBER(B11)),B11,0)+IF(AND(ISNUMBER(C12),ISNUMBER(B12)),B12,0)+IF(AND(ISNUMBER(C13),ISNUMBER(B13)),B13,0)+IF(AND(ISNUMBER(C14),ISNUMBER(B14)),B14,0)+IF(AND(ISNUMBER(C15),ISNUMBER(B15)),B15,0)+IF(AND(ISNUMBER(C16),ISNUMBER(B16)),B16,0)+IF(AND(ISNUMBER(C17),ISNUMBER(B17)),B17,0)+IF(AND(ISNUMBER(C20),ISNUMBER(B20)),B20,0)+IF(AND(ISNUMBER(C21),ISNUMBER(B21)),B21,0)+IF(AND(ISNUMBER(C22),ISNUMBER(B22)),B22,0)+IF(AND(ISNUMBER(C23),ISNUMBER(B23)),B23,0)+IF(AND(ISNUMBER(C24),ISNUMBER(B24)),B24,0)+IF(AND(ISNUMBER(C25),ISNUMBER(B25)),B25,0)+IF(AND(ISNUMBER(C26),ISNUMBER(B26)),B26,0)+IF(AND(ISNUMBER(C29),ISNUMBER(B29)),B29,0)+IF(AND(ISNUMBER(C30),ISNUMBER(B30)),B30,0)+IF(AND(ISNUMBER(C31),ISNUMBER(B31)),B31,0)+IF(AND(ISNUMBER(C32),ISNUMBER(B32)),B32,0)+IF(AND(ISNUMBER(C33),ISNUMBER(B33)),B33,0)+IF(AND(ISNUMBER(C34),ISNUMBER(B34)),B34,0)+IF(AND(ISNUMBER(C35),ISNUMBER(B35)),B35,0)+IF(AND(ISNUMBER(C38),ISNUMBER(B38)),B38,0)+IF(AND(ISNUMBER(C39),ISNUMBER(B39)),B39,0)+IF(AND(ISNUMBER(C40),ISNUMBER(B40)),B40,0)+IF(AND(ISNUMBER(C41),ISNUMBER(B41)),B41,0)+IF(AND(ISNUMBER(C42),ISNUMBER(B42)),B42,0)+IF(AND(ISNUMBER(C43),ISNUMBER(B43)),B43,0)+IF(AND(ISNUMBER(C44),ISNUMBER(B44)),B44,0))=0,"",(IF(AND(ISNUMBER(C6),ISNUMBER(B6)),C6*B6,0)+IF(AND(ISNUMBER(C7),ISNUMBER(B7)),C7*B7,0)+IF(AND(ISNUMBER(C8),ISNUMBER(B8)),C8*B8,0)+IF(AND(ISNUMBER(C11),ISNUMBER(B11)),C11*B11,0)+IF(AND(ISNUMBER(C12),ISNUMBER(B12)),C12*B12,0)+IF(AND(ISNUMBER(C13),ISNUMBER(B13)),C13*B13,0)+IF(AND(ISNUMBER(C14),ISNUMBER(B14)),C14*B14,0)+IF(AND(ISNUMBER(C15),ISNUMBER(B15)),C15*B15,0)+IF(AND(ISNUMBER(C16),ISNUMBER(B16)),C16*B16,0)+IF(AND(ISNUMBER(C17),ISNUMBER(B17)),C17*B17,0)+IF(AND(ISNUMBER(C20),ISNUMBER(B20)),C20*B20,0)+IF(AND(ISNUMBER(C21),ISNUMBER(B21)),C21*B21,0)+IF(AND(ISNUMBER(C22),ISNUMBER(B22)),C22*B22,0)+IF(AND(ISNUMBER(C23),ISNUMBER(B23)),C23*B23,0)+IF(AND(ISNUMBER(C24),ISNUMBER(B24)),C24*B24,0)+IF(AND(ISNUMBER(C25),ISNUMBER(B25)),C25*B25,0)+IF(AND(ISNUMBER(C26),ISNUMBER(B26)),C26*B26,0)+IF(AND(ISNUMBER(C29),ISNUMBER(B29)),C29*B29,0)+IF(AND(ISNUMBER(C30),ISNUMBER(B30)),C30*B30,0)+IF(AND(ISNUMBER(C31),ISNUMBER(B31)),C31*B31,0)+IF(AND(ISNUMBER(C32),ISNUMBER(B32)),C32*B32,0)+IF(AND(ISNUMBER(C33),ISNUMBER(B33)),C33*B33,0)+IF(AND(ISNUMBER(C34),ISNUMBER(B34)),C34*B34,0)+IF(AND(ISNUMBER(C35),ISNUMBER(B35)),C35*B35,0)+IF(AND(ISNUMBER(C38),ISNUMBER(B38)),C38*B38,0)+IF(AND(ISNUMBER(C39),ISNUMBER(B39)),C39*B39,0)+IF(AND(ISNUMBER(C40),ISNUMBER(B40)),C40*B40,0)+IF(AND(ISNUMBER(C41),ISNUMBER(B41)),C41*B41,0)+IF(AND(ISNUMBER(C42),ISNUMBER(B42)),C42*B42,0)+IF(AND(ISNUMBER(C43),ISNUMBER(B43)),C43*B43,0)+IF(AND(ISNUMBER(C44),ISNUMBER(B44)),C44*B44,0))/(IF(AND(ISNUMBER(C6),ISNUMBER(B6)),B6,0)+IF(AND(ISNUMBER(C7),ISNUMBER(B7)),B7,0)+IF(AND(ISNUMBER(C8),ISNUMBER(B8)),B8,0)+IF(AND(ISNUMBER(C11),ISNUMBER(B11)),B11,0)+IF(AND(ISNUMBER(C12),ISNUMBER(B12)),B12,0)+IF(AND(ISNUMBER(C13),ISNUMBER(B13)),B13,0)+IF(AND(ISNUMBER(C14),ISNUMBER(B14)),B14,0)+IF(AND(ISNUMBER(C15),ISNUMBER(B15)),B15,0)+IF(AND(ISNUMBER(C16),ISNUMBER(B16)),B16,0)+IF(AND(ISNUMBER(C17),ISNUMBER(B17)),B17,0)+IF(AND(ISNUMBER(C20),ISNUMBER(B20)),B20,0)+IF(AND(ISNUMBER(C21),ISNUMBER(B21)),B21,0)+IF(AND(ISNUMBER(C22),ISNUMBER(B22)),B22,0)+IF(AND(ISNUMBER(C23),ISNUMBER(B23)),B23,0)+IF(AND(ISNUMBER(C24),ISNUMBER(B24)),B24,0)+IF(AND(ISNUMBER(C25),ISNUMBER(B25)),B25,0)+IF(AND(ISNUMBER(C26),ISNUMBER(B26)),B26,0)+IF(AND(ISNUMBER(C29),ISNUMBER(B29)),B29,0)+IF(AND(ISNUMBER(C30),ISNUMBER(B30)),B30,0)+IF(AND(ISNUMBER(C31),ISNUMBER(B31)),B31,0)+IF(AND(ISNUMBER(C32),ISNUMBER(B32)),B32,0)+IF(AND(ISNUMBER(C33),ISNUMBER(B33)),B33,0)+IF(AND(ISNUMBER(C34),ISNUMBER(B34)),B34,0)+IF(AND(ISNUMBER(C35),ISNUMBER(B35)),B35,0)+IF(AND(ISNUMBER(C38),ISNUMBER(B38)),B38,0)+IF(AND(ISNUMBER(C39),ISNUMBER(B39)),B39,0)+IF(AND(ISNUMBER(C40),ISNUMBER(B40)),B40,0)+IF(AND(ISNUMBER(C41),ISNUMBER(B41)),B41,0)+IF(AND(ISNUMBER(C42),ISNUMBER(B42)),B42,0)+IF(AND(ISNUMBER(C43),ISNUMBER(B43)),B43,0)+IF(AND(ISNUMBER(C44),ISNUMBER(B44)),B44,0))) | D48: =IF(COUNT(D9,D18,D27,D36,D46)=0,"",SUM(D9,D18,D27,D36,D46)) | F48: =IF((IF(AND(ISNUMBER(F6),ISNUMBER(B6)),B6,0)+IF(AND(ISNUMBER(F7),ISNUMBER(B7)),B7,0)+IF(AND(ISNUMBER(F8),ISNUMBER(B8)),B8,0)+IF(AND(ISNUMBER(F11),ISNUMBER(B11)),B11,0)+IF(AND(ISNUMBER(F12),ISNUMBER(B12)),B12,0)+IF(AND(ISNUMBER(F13),ISNUMBER(B13)),B13,0)+IF(AND(ISNUMBER(F14),ISNUMBER(B14)),B14,0)+IF(AND(ISNUMBER(F15),ISNUMBER(B15)),B15,0)+IF(AND(ISNUMBER(F16),ISNUMBER(B16)),B16,0)+IF(AND(ISNUMBER(F17),ISNUMBER(B17)),B17,0)+IF(AND(ISNUMBER(F20),ISNUMBER(B20)),B20,0)+IF(AND(ISNUMBER(F21),ISNUMBER(B21)),B21,0)+IF(AND(ISNUMBER(F22),ISNUMBER(B22)),B22,0)+IF(AND(ISNUMBER(F23),ISNUMBER(B23)),B23,0)+IF(AND(ISNUMBER(F24),ISNUMBER(B24)),B24,0)+IF(AND(ISNUMBER(F25),ISNUMBER(B25)),B25,0)+IF(AND(ISNUMBER(F26),ISNUMBER(B26)),B26,0)+IF(AND(ISNUMBER(F29),ISNUMBER(B29)),B29,0)+IF(AND(ISNUMBER(F30),ISNUMBER(B30)),B30,0)+IF(AND(ISNUMBER(F31),ISNUMBER(B31)),B31,0)+IF(AND(ISNUMBER(F32),ISNUMBER(B32)),B32,0)+IF(AND(ISNUMBER(F33),ISNUMBER(B33)),B33,0)+IF(AND(ISNUMBER(F34),ISNUMBER(B34)),B34,0)+IF(AND(ISNUMBER(F35),ISNUMBER(B35)),B35,0)+IF(AND(ISNUMBER(F38),ISNUMBER(B38)),B38,0)+IF(AND(ISNUMBER(F39),ISNUMBER(B39)),B39,0)+IF(AND(ISNUMBER(F40),ISNUMBER(B40)),B40,0)+IF(AND(ISNUMBER(F41),ISNUMBER(B41)),B41,0)+IF(AND(ISNUMBER(F42),ISNUMBER(B42)),B42,0)+IF(AND(ISNUMBER(F43),ISNUMBER(B43)),B43,0)+IF(AND(ISNUMBER(F44),ISNUMBER(B44)),B44,0))=0,"",(IF(AND(ISNUMBER(F6),ISNUMBER(B6)),F6*B6,0)+IF(AND(ISNUMBER(F7),ISNUMBER(B7)),F7*B7,0)+IF(AND(ISNUMBER(F8),ISNUMBER(B8)),F8*B8,0)+IF(AND(ISNUMBER(F11),ISNUMBER(B11)),F11*B11,0)+IF(AND(ISNUMBER(F12),ISNUMBER(B12)),F12*B12,0)+IF(AND(ISNUMBER(F13),ISNUMBER(B13)),F13*B13,0)+IF(AND(ISNUMBER(F14),ISNUMBER(B14)),F14*B14,0)+IF(AND(ISNUMBER(F15),ISNUMBER(B15)),F15*B15,0)+IF(AND(ISNUMBER(F16),ISNUMBER(B16)),F16*B16,0)+IF(AND(ISNUMBER(F17),ISNUMBER(B17)),F17*B17,0)+IF(AND(ISNUMBER(F20),ISNUMBER(B20)),F20*B20,0)+IF(AND(ISNUMBER(F21),ISNUMBER(B21)),F21*B21,0)+IF(AND(ISNUMBER(F22),ISNUMBER(B22)),F22*B22,0)+IF(AND(ISNUMBER(F23),ISNUMBER(B23)),F23*B23,0)+IF(AND(ISNUMBER(F24),ISNUMBER(B24)),F24*B24,0)+IF(AND(ISNUMBER(F25),ISNUMBER(B25)),F25*B25,0)+IF(AND(ISNUMBER(F26),ISNUMBER(B26)),F26*B26,0)+IF(AND(ISNUMBER(F29),ISNUMBER(B29)),F29*B29,0)+IF(AND(ISNUMBER(F30),ISNUMBER(B30)),F30*B30,0)+IF(AND(ISNUMBER(F31),ISNUMBER(B31)),F31*B31,0)+IF(AND(ISNUMBER(F32),ISNUMBER(B32)),F32*B32,0)+IF(AND(ISNUMBER(F33),ISNUMBER(B33)),F33*B33,0)+IF(AND(ISNUMBER(F34),ISNUMBER(B34)),F34*B34,0)+IF(AND(ISNUMBER(F35),ISNUMBER(B35)),F35*B35,0)+IF(AND(ISNUMBER(F38),ISNUMBER(B38)),F38*B38,0)+IF(AND(ISNUMBER(F39),ISNUMBER(B39)),F39*B39,0)+IF(AND(ISNUMBER(F40),ISNUMBER(B40)),F40*B40,0)+IF(AND(ISNUMBER(F41),ISNUMBER(B41)),F41*B41,0)+IF(AND(ISNUMBER(F42),ISNUMBER(B42)),F42*B42,0)+IF(AND(ISNUMBER(F43),ISNUMBER(B43)),F43*B43,0)+IF(AND(ISNUMBER(F44),ISNUMBER(B44)),F44*B44,0))/(IF(AND(ISNUMBER(F6),ISNUMBER(B6)),B6,0)+IF(AND(ISNUMBER(F7),ISNUMBER(B7)),B7,0)+IF(AND(ISNUMBER(F8),ISNUMBER(B8)),B8,0)+IF(AND(ISNUMBER(F11),ISNUMBER(B11)),B11,0)+IF(AND(ISNUMBER(F12),ISNUMBER(B12)),B12,0)+IF(AND(ISNUMBER(F13),ISNUMBER(B13)),B13,0)+IF(AND(ISNUMBER(F14),ISNUMBER(B14)),B14,0)+IF(AND(ISNUMBER(F15),ISNUMBER(B15)),B15,0)+IF(AND(ISNUMBER(F16),ISNUMBER(B16)),B16,0)+IF(AND(ISNUMBER(F17),ISNUMBER(B17)),B17,0)+IF(AND(ISNUMBER(F20),ISNUMBER(B20)),B20,0)+IF(AND(ISNUMBER(F21),ISNUMBER(B21)),B21,0)+IF(AND(ISNUMBER(F22),ISNUMBER(B22)),B22,0)+IF(AND(ISNUMBER(F23),ISNUMBER(B23)),B23,0)+IF(AND(ISNUMBER(F24),ISNUMBER(B24)),B24,0)+IF(AND(ISNUMBER(F25),ISNUMBER(B25)),B25,0)+IF(AND(ISNUMBER(F26),ISNUMBER(B26)),B26,0)+IF(AND(ISNUMBER(F29),ISNUMBER(B29)),B29,0)+IF(AND(ISNUMBER(F30),ISNUMBER(B30)),B30,0)+IF(AND(ISNUMBER(F31),ISNUMBER(B31)),B31,0)+IF(AND(ISNUMBER(F32),ISNUMBER(B32)),B32,0)+IF(AND(ISNUMBER(F33),ISNUMBER(B33)),B33,0)+IF(AND(ISNUMBER(F34),ISNUMBER(B34)),B34,0)+IF(AND(ISNUMBER(F35),ISNUMBER(B35)),B35,0)+IF(AND(ISNUMBER(F38),ISNUMBER(B38)),B38,0)+IF(AND(ISNUMBER(F39),ISNUMBER(B39)),B39,0)+IF(AND(ISNUMBER(F40),ISNUMBER(B40)),B40,0)+IF(AND(ISNUMBER(F41),ISNUMBER(B41)),B41,0)+IF(AND(ISNUMBER(F42),ISNUMBER(B42)),B42,0)+IF(AND(ISNUMBER(F43),ISNUMBER(B43)),B43,0)+IF(AND(ISNUMBER(F44),ISNUMBER(B44)),B44,0))) | G48: =IF((IF(AND(ISNUMBER(G6),ISNUMBER(B6)),B6,0)+IF(AND(ISNUMBER(G7),ISNUMBER(B7)),B7,0)+IF(AND(ISNUMBER(G8),ISNUMBER(B8)),B8,0)+IF(AND(ISNUMBER(G11),ISNUMBER(B11)),B11,0)+IF(AND(ISNUMBER(G12),ISNUMBER(B12)),B12,0)+IF(AND(ISNUMBER(G13),ISNUMBER(B13)),B13,0)+IF(AND(ISNUMBER(G14),ISNUMBER(B14)),B14,0)+IF(AND(ISNUMBER(G15),ISNUMBER(B15)),B15,0)+IF(AND(ISNUMBER(G16),ISNUMBER(B16)),B16,0)+IF(AND(ISNUMBER(G17),ISNUMBER(B17)),B17,0)+IF(AND(ISNUMBER(G20),ISNUMBER(B20)),B20,0)+IF(AND(ISNUMBER(G21),ISNUMBER(B21)),B21,0)+IF(AND(ISNUMBER(G22),ISNUMBER(B22)),B22,0)+IF(AND(ISNUMBER(G23),ISNUMBER(B23)),B23,0)+IF(AND(ISNUMBER(G24),ISNUMBER(B24)),B24,0)+IF(AND(ISNUMBER(G25),ISNUMBER(B25)),B25,0)+IF(AND(ISNUMBER(G26),ISNUMBER(B26)),B26,0)+IF(AND(ISNUMBER(G29),ISNUMBER(B29)),B29,0)+IF(AND(ISNUMBER(G30),ISNUMBER(B30)),B30,0)+IF(AND(ISNUMBER(G31),ISNUMBER(B31)),B31,0)+IF(AND(ISNUMBER(G32),ISNUMBER(B32)),B32,0)+IF(AND(ISNUMBER(G33),ISNUMBER(B33)),B33,0)+IF(AND(ISNUMBER(G34),ISNUMBER(B34)),B34,0)+IF(AND(ISNUMBER(G35),ISNUMBER(B35)),B35,0)+IF(AND(ISNUMBER(G38),ISNUMBER(B38)),B38,0)+IF(AND(ISNUMBER(G39),ISNUMBER(B39)),B39,0)+IF(AND(ISNUMBER(G40),ISNUMBER(B40)),B40,0)+IF(AND(ISNUMBER(G41),ISNUMBER(B41)),B41,0)+IF(AND(ISNUMBER(G42),ISNUMBER(B42)),B42,0)+IF(AND(ISNUMBER(G43),ISNUMBER(B43)),B43,0)+IF(AND(ISNUMBER(G44),ISNUMBER(B44)),B44,0))=0,"",(IF(AND(ISNUMBER(G6),ISNUMBER(B6)),G6*B6,0)+IF(AND(ISNUMBER(G7),ISNUMBER(B7)),G7*B7,0)+IF(AND(ISNUMBER(G8),ISNUMBER(B8)),G8*B8,0)+IF(AND(ISNUMBER(G11),ISNUMBER(B11)),G11*B11,0)+IF(AND(ISNUMBER(G12),ISNUMBER(B12)),G12*B12,0)+IF(AND(ISNUMBER(G13),ISNUMBER(B13)),G13*B13,0)+IF(AND(ISNUMBER(G14),ISNUMBER(B14)),G14*B14,0)+IF(AND(ISNUMBER(G15),ISNUMBER(B15)),G15*B15,0)+IF(AND(ISNUMBER(G16),ISNUMBER(B16)),G16*B16,0)+IF(AND(ISNUMBER(G17),ISNUMBER(B17)),G17*B17,0)+IF(AND(ISNUMBER(G20),ISNUMBER(B20)),G20*B20,0)+IF(AND(ISNUMBER(G21),ISNUMBER(B21)),G21*B21,0)+IF(AND(ISNUMBER(G22),ISNUMBER(B22)),G22*B22,0)+IF(AND(ISNUMBER(G23),ISNUMBER(B23)),G23*B23,0)+IF(AND(ISNUMBER(G24),ISNUMBER(B24)),G24*B24,0)+IF(AND(ISNUMBER(G25),ISNUMBER(B25)),G25*B25,0)+IF(AND(ISNUMBER(G26),ISNUMBER(B26)),G26*B26,0)+IF(AND(ISNUMBER(G29),ISNUMBER(B29)),G29*B29,0)+IF(AND(ISNUMBER(G30),ISNUMBER(B30)),G30*B30,0)+IF(AND(ISNUMBER(G31),ISNUMBER(B31)),G31*B31,0)+IF(AND(ISNUMBER(G32),ISNUMBER(B32)),G32*B32,0)+IF(AND(ISNUMBER(G33),ISNUMBER(B33)),G33*B33,0)+IF(AND(ISNUMBER(G34),ISNUMBER(B34)),G34*B34,0)+IF(AND(ISNUMBER(G35),ISNUMBER(B35)),G35*B35,0)+IF(AND(ISNUMBER(G38),ISNUMBER(B38)),G38*B38,0)+IF(AND(ISNUMBER(G39),ISNUMBER(B39)),G39*B39,0)+IF(AND(ISNUMBER(G40),ISNUMBER(B40)),G40*B40,0)+IF(AND(ISNUMBER(G41),ISNUMBER(B41)),G41*B41,0)+IF(AND(ISNUMBER(G42),ISNUMBER(B42)),G42*B42,0)+IF(AND(ISNUMBER(G43),ISNUMBER(B43)),G43*B43,0)+IF(AND(ISNUMBER(G44),ISNUMBER(B44)),G44*B44,0))/(IF(AND(ISNUMBER(G6),ISNUMBER(B6)),B6,0)+IF(AND(ISNUMBER(G7),ISNUMBER(B7)),B7,0)+IF(AND(ISNUMBER(G8),ISNUMBER(B8)),B8,0)+IF(AND(ISNUMBER(G11),ISNUMBER(B11)),B11,0)+IF(AND(ISNUMBER(G12),ISNUMBER(B12)),B12,0)+IF(AND(ISNUMBER(G13),ISNUMBER(B13)),B13,0)+IF(AND(ISNUMBER(G14),ISNUMBER(B14)),B14,0)+IF(AND(ISNUMBER(G15),ISNUMBER(B15)),B15,0)+IF(AND(ISNUMBER(G16),ISNUMBER(B16)),B16,0)+IF(AND(ISNUMBER(G17),ISNUMBER(B17)),B17,0)+IF(AND(ISNUMBER(G20),ISNUMBER(B20)),B20,0)+IF(AND(ISNUMBER(G21),ISNUMBER(B21)),B21,0)+IF(AND(ISNUMBER(G22),ISNUMBER(B22)),B22,0)+IF(AND(ISNUMBER(G23),ISNUMBER(B23)),B23,0)+IF(AND(ISNUMBER(G24),ISNUMBER(B24)),B24,0)+IF(AND(ISNUMBER(G25),ISNUMBER(B25)),B25,0)+IF(AND(ISNUMBER(G26),ISNUMBER(B26)),B26,0)+IF(AND(ISNUMBER(G29),ISNUMBER(B29)),B29,0)+IF(AND(ISNUMBER(G30),ISNUMBER(B30)),B30,0)+IF(AND(ISNUMBER(G31),ISNUMBER(B31)),B31,0)+IF(AND(ISNUMBER(G32),ISNUMBER(B32)),B32,0)+IF(AND(ISNUMBER(G33),ISNUMBER(B33)),B33,0)+IF(AND(ISNUMBER(G34),ISNUMBER(B34)),B34,0)+IF(AND(ISNUMBER(G35),ISNUMBER(B35)),B35,0)+IF(AND(ISNUMBER(G38),ISNUMBER(B38)),B38,0)+IF(AND(ISNUMBER(G39),ISNUMBER(B39)),B39,0)+IF(AND(ISNUMBER(G40),ISNUMBER(B40)),B40,0)+IF(AND(ISNUMBER(G41),ISNUMBER(B41)),B41,0)+IF(AND(ISNUMBER(G42),ISNUMBER(B42)),B42,0)+IF(AND(ISNUMBER(G43),ISNUMBER(B43)),B43,0)+IF(AND(ISNUMBER(G44),ISNUMBER(B44)),B44,0))) | H48: =IF((IF(AND(ISNUMBER(H6),ISNUMBER(B6)),B6,0)+IF(AND(ISNUMBER(H7),ISNUMBER(B7)),B7,0)+IF(AND(ISNUMBER(H8),ISNUMBER(B8)),B8,0)+IF(AND(ISNUMBER(H11),ISNUMBER(B11)),B11,0)+IF(AND(ISNUMBER(H12),ISNUMBER(B12)),B12,0)+IF(AND(ISNUMBER(H13),ISNUMBER(B13)),B13,0)+IF(AND(ISNUMBER(H14),ISNUMBER(B14)),B14,0)+IF(AND(ISNUMBER(H15),ISNUMBER(B15)),B15,0)+IF(AND(ISNUMBER(H16),ISNUMBER(B16)),B16,0)+IF(AND(ISNUMBER(H17),ISNUMBER(B17)),B17,0)+IF(AND(ISNUMBER(H20),ISNUMBER(B20)),B20,0)+IF(AND(ISNUMBER(H21),ISNUMBER(B21)),B21,0)+IF(AND(ISNUMBER(H22),ISNUMBER(B22)),B22,0)+IF(AND(ISNUMBER(H23),ISNUMBER(B23)),B23,0)+IF(AND(ISNUMBER(H24),ISNUMBER(B24)),B24,0)+IF(AND(ISNUMBER(H25),ISNUMBER(B25)),B25,0)+IF(AND(ISNUMBER(H26),ISNUMBER(B26)),B26,0)+IF(AND(ISNUMBER(H29),ISNUMBER(B29)),B29,0)+IF(AND(ISNUMBER(H30),ISNUMBER(B30)),B30,0)+IF(AND(ISNUMBER(H31),ISNUMBER(B31)),B31,0)+IF(AND(ISNUMBER(H32),ISNUMBER(B32)),B32,0)+IF(AND(ISNUMBER(H33),ISNUMBER(B33)),B33,0)+IF(AND(ISNUMBER(H34),ISNUMBER(B34)),B34,0)+IF(AND(ISNUMBER(H35),ISNUMBER(B35)),B35,0)+IF(AND(ISNUMBER(H38),ISNUMBER(B38)),B38,0)+IF(AND(ISNUMBER(H39),ISNUMBER(B39)),B39,0)+IF(AND(ISNUMBER(H40),ISNUMBER(B40)),B40,0)+IF(AND(ISNUMBER(H41),ISNUMBER(B41)),B41,0)+IF(AND(ISNUMBER(H42),ISNUMBER(B42)),B42,0)+IF(AND(ISNUMBER(H43),ISNUMBER(B43)),B43,0)+IF(AND(ISNUMBER(H44),ISNUMBER(B44)),B44,0))=0,"",(IF(AND(ISNUMBER(H6),ISNUMBER(B6)),H6*B6,0)+IF(AND(ISNUMBER(H7),ISNUMBER(B7)),H7*B7,0)+IF(AND(ISNUMBER(H8),ISNUMBER(B8)),H8*B8,0)+IF(AND(ISNUMBER(H11),ISNUMBER(B11)),H11*B11,0)+IF(AND(ISNUMBER(H12),ISNUMBER(B12)),H12*B12,0)+IF(AND(ISNUMBER(H13),ISNUMBER(B13)),H13*B13,0)+IF(AND(ISNUMBER(H14),ISNUMBER(B14)),H14*B14,0)+IF(AND(ISNUMBER(H15),ISNUMBER(B15)),H15*B15,0)+IF(AND(ISNUMBER(H16),ISNUMBER(B16)),H16*B16,0)+IF(AND(ISNUMBER(H17),ISNUMBER(B17)),H17*B17,0)+IF(AND(ISNUMBER(H20),ISNUMBER(B20)),H20*B20,0)+IF(AND(ISNUMBER(H21),ISNUMBER(B21)),H21*B21,0)+IF(AND(ISNUMBER(H22),ISNUMBER(B22)),H22*B22,0)+IF(AND(ISNUMBER(H23),ISNUMBER(B23)),H23*B23,0)+IF(AND(ISNUMBER(H24),ISNUMBER(B24)),H24*B24,0)+IF(AND(ISNUMBER(H25),ISNUMBER(B25)),H25*B25,0)+IF(AND(ISNUMBER(H26),ISNUMBER(B26)),H26*B26,0)+IF(AND(ISNUMBER(H29),ISNUMBER(B29)),H29*B29,0)+IF(AND(ISNUMBER(H30),ISNUMBER(B30)),H30*B30,0)+IF(AND(ISNUMBER(H31),ISNUMBER(B31)),H31*B31,0)+IF(AND(ISNUMBER(H32),ISNUMBER(B32)),H32*B32,0)+IF(AND(ISNUMBER(H33),ISNUMBER(B33)),H33*B33,0)+IF(AND(ISNUMBER(H34),ISNUMBER(B34)),H34*B34,0)+IF(AND(ISNUMBER(H35),ISNUMBER(B35)),H35*B35,0)+IF(AND(ISNUMBER(H38),ISNUMBER(B38)),H38*B38,0)+IF(AND(ISNUMBER(H39),ISNUMBER(B39)),H39*B39,0)+IF(AND(ISNUMBER(H40),ISNUMBER(B40)),H40*B40,0)+IF(AND(ISNUMBER(H41),ISNUMBER(B41)),H41*B41,0)+IF(AND(ISNUMBER(H42),ISNUMBER(B42)),H42*B42,0)+IF(AND(ISNUMBER(H43),ISNUMBER(B43)),H43*B43,0)+IF(AND(ISNUMBER(H44),ISNUMBER(B44)),H44*B44,0))/(IF(AND(ISNUMBER(H6),ISNUMBER(B6)),B6,0)+IF(AND(ISNUMBER(H7),ISNUMBER(B7)),B7,0)+IF(AND(ISNUMBER(H8),ISNUMBER(B8)),B8,0)+IF(AND(ISNUMBER(H11),ISNUMBER(B11)),B11,0)+IF(AND(ISNUMBER(H12),ISNUMBER(B12)),B12,0)+IF(AND(ISNUMBER(H13),ISNUMBER(B13)),B13,0)+IF(AND(ISNUMBER(H14),ISNUMBER(B14)),B14,0)+IF(AND(ISNUMBER(H15),ISNUMBER(B15)),B15,0)+IF(AND(ISNUMBER(H16),ISNUMBER(B16)),B16,0)+IF(AND(ISNUMBER(H17),ISNUMBER(B17)),B17,0)+IF(AND(ISNUMBER(H20),ISNUMBER(B20)),B20,0)+IF(AND(ISNUMBER(H21),ISNUMBER(B21)),B21,0)+IF(AND(ISNUMBER(H22),ISNUMBER(B22)),B22,0)+IF(AND(ISNUMBER(H23),ISNUMBER(B23)),B23,0)+IF(AND(ISNUMBER(H24),ISNUMBER(B24)),B24,0)+IF(AND(ISNUMBER(H25),ISNUMBER(B25)),B25,0)+IF(AND(ISNUMBER(H26),ISNUMBER(B26)),B26,0)+IF(AND(ISNUMBER(H29),ISNUMBER(B29)),B29,0)+IF(AND(ISNUMBER(H30),ISNUMBER(B30)),B30,0)+IF(AND(ISNUMBER(H31),ISNUMBER(B31)),B31,0)+IF(AND(ISNUMBER(H32),ISNUMBER(B32)),B32,0)+IF(AND(ISNUMBER(H33),ISNUMBER(B33)),B33,0)+IF(AND(ISNUMBER(H34),ISNUMBER(B34)),B34,0)+IF(AND(ISNUMBER(H35),ISNUMBER(B35)),B35,0)+IF(AND(ISNUMBER(H38),ISNUMBER(B38)),B38,0)+IF(AND(ISNUMBER(H39),ISNUMBER(B39)),B39,0)+IF(AND(ISNUMBER(H40),ISNUMBER(B40)),B40,0)+IF(AND(ISNUMBER(H41),ISNUMBER(B41)),B41,0)+IF(AND(ISNUMBER(H42),ISNUMBER(B42)),B42,0)+IF(AND(ISNUMBER(H43),ISNUMBER(B43)),B43,0)+IF(AND(ISNUMBER(H44),ISNUMBER(B44)),B44,0))) | M48: =IF((IF(AND(ISNUMBER(M6),ISNUMBER(B6)),B6,0)+IF(AND(ISNUMBER(M7),ISNUMBER(B7)),B7,0)+IF(AND(ISNUMBER(M8),ISNUMBER(B8)),B8,0)+IF(AND(ISNUMBER(M11),ISNUMBER(B11)),B11,0)+IF(AND(ISNUMBER(M12),ISNUMBER(B12)),B12,0)+IF(AND(ISNUMBER(M13),ISNUMBER(B13)),B13,0)+IF(AND(ISNUMBER(M14),ISNUMBER(B14)),B14,0)+IF(AND(ISNUMBER(M15),ISNUMBER(B15)),B15,0)+IF(AND(ISNUMBER(M16),ISNUMBER(B16)),B16,0)+IF(AND(ISNUMBER(M17),ISNUMBER(B17)),B17,0)+IF(AND(ISNUMBER(M20),ISNUMBER(B20)),B20,0)+IF(AND(ISNUMBER(M21),ISNUMBER(B21)),B21,0)+IF(AND(ISNUMBER(M22),ISNUMBER(B22)),B22,0)+IF(AND(ISNUMBER(M23),ISNUMBER(B23)),B23,0)+IF(AND(ISNUMBER(M24),ISNUMBER(B24)),B24,0)+IF(AND(ISNUMBER(M25),ISNUMBER(B25)),B25,0)+IF(AND(ISNUMBER(M26),ISNUMBER(B26)),B26,0)+IF(AND(ISNUMBER(M29),ISNUMBER(B29)),B29,0)+IF(AND(ISNUMBER(M30),ISNUMBER(B30)),B30,0)+IF(AND(ISNUMBER(M31),ISNUMBER(B31)),B31,0)+IF(AND(ISNUMBER(M32),ISNUMBER(B32)),B32,0)+IF(AND(ISNUMBER(M33),ISNUMBER(B33)),B33,0)+IF(AND(ISNUMBER(M34),ISNUMBER(B34)),B34,0)+IF(AND(ISNUMBER(M35),ISNUMBER(B35)),B35,0)+IF(AND(ISNUMBER(M38),ISNUMBER(B38)),B38,0)+IF(AND(ISNUMBER(M39),ISNUMBER(B39)),B39,0)+IF(AND(ISNUMBER(M40),ISNUMBER(B40)),B40,0)+IF(AND(ISNUMBER(M41),ISNUMBER(B41)),B41,0)+IF(AND(ISNUMBER(M42),ISNUMBER(B42)),B42,0)+IF(AND(ISNUMBER(M43),ISNUMBER(B43)),B43,0)+IF(AND(ISNUMBER(M44),ISNUMBER(B44)),B44,0))=0,"",(IF(AND(ISNUMBER(M6),ISNUMBER(B6)),M6*B6,0)+IF(AND(ISNUMBER(M7),ISNUMBER(B7)),M7*B7,0)+IF(AND(ISNUMBER(M8),ISNUMBER(B8)),M8*B8,0)+IF(AND(ISNUMBER(M11),ISNUMBER(B11)),M11*B11,0)+IF(AND(ISNUMBER(M12),ISNUMBER(B12)),M12*B12,0)+IF(AND(ISNUMBER(M13),ISNUMBER(B13)),M13*B13,0)+IF(AND(ISNUMBER(M14),ISNUMBER(B14)),M14*B14,0)+IF(AND(ISNUMBER(M15),ISNUMBER(B15)),M15*B15,0)+IF(AND(ISNUMBER(M16),ISNUMBER(B16)),M16*B16,0)+IF(AND(ISNUMBER(M17),ISNUMBER(B17)),M17*B17,0)+IF(AND(ISNUMBER(M20),ISNUMBER(B20)),M20*B20,0)+IF(AND(ISNUMBER(M21),ISNUMBER(B21)),M21*B21,0)+IF(AND(ISNUMBER(M22),ISNUMBER(B22)),M22*B22,0)+IF(AND(ISNUMBER(M23),ISNUMBER(B23)),M23*B23,0)+IF(AND(ISNUMBER(M24),ISNUMBER(B24)),M24*B24,0)+IF(AND(ISNUMBER(M25),ISNUMBER(B25)),M25*B25,0)+IF(AND(ISNUMBER(M26),ISNUMBER(B26)),M26*B26,0)+IF(AND(ISNUMBER(M29),ISNUMBER(B29)),M29*B29,0)+IF(AND(ISNUMBER(M30),ISNUMBER(B30)),M30*B30,0)+IF(AND(ISNUMBER(M31),ISNUMBER(B31)),M31*B31,0)+IF(AND(ISNUMBER(M32),ISNUMBER(B32)),M32*B32,0)+IF(AND(ISNUMBER(M33),ISNUMBER(B33)),M33*B33,0)+IF(AND(ISNUMBER(M34),ISNUMBER(B34)),M34*B34,0)+IF(AND(ISNUMBER(M35),ISNUMBER(B35)),M35*B35,0)+IF(AND(ISNUMBER(M38),ISNUMBER(B38)),M38*B38,0)+IF(AND(ISNUMBER(M39),ISNUMBER(B39)),M39*B39,0)+IF(AND(ISNUMBER(M40),ISNUMBER(B40)),M40*B40,0)+IF(AND(ISNUMBER(M41),ISNUMBER(B41)),M41*B41,0)+IF(AND(ISNUMBER(M42),ISNUMBER(B42)),M42*B42,0)+IF(AND(ISNUMBER(M43),ISNUMBER(B43)),M43*B43,0)+IF(AND(ISNUMBER(M44),ISNUMBER(B44)),M44*B44,0))/(IF(AND(ISNUMBER(M6),ISNUMBER(B6)),B6,0)+IF(AND(ISNUMBER(M7),ISNUMBER(B7)),B7,0)+IF(AND(ISNUMBER(M8),ISNUMBER(B8)),B8,0)+IF(AND(ISNUMBER(M11),ISNUMBER(B11)),B11,0)+IF(AND(ISNUMBER(M12),ISNUMBER(B12)),B12,0)+IF(AND(ISNUMBER(M13),ISNUMBER(B13)),B13,0)+IF(AND(ISNUMBER(M14),ISNUMBER(B14)),B14,0)+IF(AND(ISNUMBER(M15),ISNUMBER(B15)),B15,0)+IF(AND(ISNUMBER(M16),ISNUMBER(B16)),B16,0)+IF(AND(ISNUMBER(M17),ISNUMBER(B17)),B17,0)+IF(AND(ISNUMBER(M20),ISNUMBER(B20)),B20,0)+IF(AND(ISNUMBER(M21),ISNUMBER(B21)),B21,0)+IF(AND(ISNUMBER(M22),ISNUMBER(B22)),B22,0)+IF(AND(ISNUMBER(M23),ISNUMBER(B23)),B23,0)+IF(AND(ISNUMBER(M24),ISNUMBER(B24)),B24,0)+IF(AND(ISNUMBER(M25),ISNUMBER(B25)),B25,0)+IF(AND(ISNUMBER(M26),ISNUMBER(B26)),B26,0)+IF(AND(ISNUMBER(M29),ISNUMBER(B29)),B29,0)+IF(AND(ISNUMBER(M30),ISNUMBER(B30)),B30,0)+IF(AND(ISNUMBER(M31),ISNUMBER(B31)),B31,0)+IF(AND(ISNUMBER(M32),ISNUMBER(B32)),B32,0)+IF(AND(ISNUMBER(M33),ISNUMBER(B33)),B33,0)+IF(AND(ISNUMBER(M34),ISNUMBER(B34)),B34,0)+IF(AND(ISNUMBER(M35),ISNUMBER(B35)),B35,0)+IF(AND(ISNUMBER(M38),ISNUMBER(B38)),B38,0)+IF(AND(ISNUMBER(M39),ISNUMBER(B39)),B39,0)+IF(AND(ISNUMBER(M40),ISNUMBER(B40)),B40,0)+IF(AND(ISNUMBER(M41),ISNUMBER(B41)),B41,0)+IF(AND(ISNUMBER(M42),ISNUMBER(B42)),B42,0)+IF(AND(ISNUMBER(M43),ISNUMBER(B43)),B43,0)+IF(AND(ISNUMBER(M44),ISNUMBER(B44)),B44,0))) | O48: =IF((IF(AND(ISNUMBER(O6),ISNUMBER(B6)),B6,0)+IF(AND(ISNUMBER(O7),ISNUMBER(B7)),B7,0)+IF(AND(ISNUMBER(O8),ISNUMBER(B8)),B8,0)+IF(AND(ISNUMBER(O11),ISNUMBER(B11)),B11,0)+IF(AND(ISNUMBER(O12),ISNUMBER(B12)),B12,0)+IF(AND(ISNUMBER(O13),ISNUMBER(B13)),B13,0)+IF(AND(ISNUMBER(O14),ISNUMBER(B14)),B14,0)+IF(AND(ISNUMBER(O15),ISNUMBER(B15)),B15,0)+IF(AND(ISNUMBER(O16),ISNUMBER(B16)),B16,0)+IF(AND(ISNUMBER(O17),ISNUMBER(B17)),B17,0)+IF(AND(ISNUMBER(O20),ISNUMBER(B20)),B20,0)+IF(AND(ISNUMBER(O21),ISNUMBER(B21)),B21,0)+IF(AND(ISNUMBER(O22),ISNUMBER(B22)),B22,0)+IF(AND(ISNUMBER(O23),ISNUMBER(B23)),B23,0)+IF(AND(ISNUMBER(O24),ISNUMBER(B24)),B24,0)+IF(AND(ISNUMBER(O25),ISNUMBER(B25)),B25,0)+IF(AND(ISNUMBER(O26),ISNUMBER(B26)),B26,0)+IF(AND(ISNUMBER(O29),ISNUMBER(B29)),B29,0)+IF(AND(ISNUMBER(O30),ISNUMBER(B30)),B30,0)+IF(AND(ISNUMBER(O31),ISNUMBER(B31)),B31,0)+IF(AND(ISNUMBER(O32),ISNUMBER(B32)),B32,0)+IF(AND(ISNUMBER(O33),ISNUMBER(B33)),B33,0)+IF(AND(ISNUMBER(O34),ISNUMBER(B34)),B34,0)+IF(AND(ISNUMBER(O35),ISNUMBER(B35)),B35,0)+IF(AND(ISNUMBER(O38),ISNUMBER(B38)),B38,0)+IF(AND(ISNUMBER(O39),ISNUMBER(B39)),B39,0)+IF(AND(ISNUMBER(O40),ISNUMBER(B40)),B40,0)+IF(AND(ISNUMBER(O41),ISNUMBER(B41)),B41,0)+IF(AND(ISNUMBER(O42),ISNUMBER(B42)),B42,0)+IF(AND(ISNUMBER(O43),ISNUMBER(B43)),B43,0)+IF(AND(ISNUMBER(O44),ISNUMBER(B44)),B44,0))=0,"",(IF(AND(ISNUMBER(O6),ISNUMBER(B6)),O6*B6,0)+IF(AND(ISNUMBER(O7),ISNUMBER(B7)),O7*B7,0)+IF(AND(ISNUMBER(O8),ISNUMBER(B8)),O8*B8,0)+IF(AND(ISNUMBER(O11),ISNUMBER(B11)),O11*B11,0)+IF(AND(ISNUMBER(O12),ISNUMBER(B12)),O12*B12,0)+IF(AND(ISNUMBER(O13),ISNUMBER(B13)),O13*B13,0)+IF(AND(ISNUMBER(O14),ISNUMBER(B14)),O14*B14,0)+IF(AND(ISNUMBER(O15),ISNUMBER(B15)),O15*B15,0)+IF(AND(ISNUMBER(O16),ISNUMBER(B16)),O16*B16,0)+IF(AND(ISNUMBER(O17),ISNUMBER(B17)),O17*B17,0)+IF(AND(ISNUMBER(O20),ISNUMBER(B20)),O20*B20,0)+IF(AND(ISNUMBER(O21),ISNUMBER(B21)),O21*B21,0)+IF(AND(ISNUMBER(O22),ISNUMBER(B22)),O22*B22,0)+IF(AND(ISNUMBER(O23),ISNUMBER(B23)),O23*B23,0)+IF(AND(ISNUMBER(O24),ISNUMBER(B24)),O24*B24,0)+IF(AND(ISNUMBER(O25),ISNUMBER(B25)),O25*B25,0)+IF(AND(ISNUMBER(O26),ISNUMBER(B26)),O26*B26,0)+IF(AND(ISNUMBER(O29),ISNUMBER(B29)),O29*B29,0)+IF(AND(ISNUMBER(O30),ISNUMBER(B30)),O30*B30,0)+IF(AND(ISNUMBER(O31),ISNUMBER(B31)),O31*B31,0)+IF(AND(ISNUMBER(O32),ISNUMBER(B32)),O32*B32,0)+IF(AND(ISNUMBER(O33),ISNUMBER(B33)),O33*B33,0)+IF(AND(ISNUMBER(O34),ISNUMBER(B34)),O34*B34,0)+IF(AND(ISNUMBER(O35),ISNUMBER(B35)),O35*B35,0)+IF(AND(ISNUMBER(O38),ISNUMBER(B38)),O38*B38,0)+IF(AND(ISNUMBER(O39),ISNUMBER(B39)),O39*B39,0)+IF(AND(ISNUMBER(O40),ISNUMBER(B40)),O40*B40,0)+IF(AND(ISNUMBER(O41),ISNUMBER(B41)),O41*B41,0)+IF(AND(ISNUMBER(O42),ISNUMBER(B42)),O42*B42,0)+IF(AND(ISNUMBER(O43),ISNUMBER(B43)),O43*B43,0)+IF(AND(ISNUMBER(O44),ISNUMBER(B44)),O44*B44,0))/(IF(AND(ISNUMBER(O6),ISNUMBER(B6)),B6,0)+IF(AND(ISNUMBER(O7),ISNUMBER(B7)),B7,0)+IF(AND(ISNUMBER(O8),ISNUMBER(B8)),B8,0)+IF(AND(ISNUMBER(O11),ISNUMBER(B11)),B11,0)+IF(AND(ISNUMBER(O12),ISNUMBER(B12)),B12,0)+IF(AND(ISNUMBER(O13),ISNUMBER(B13)),B13,0)+IF(AND(ISNUMBER(O14),ISNUMBER(B14)),B14,0)+IF(AND(ISNUMBER(O15),ISNUMBER(B15)),B15,0)+IF(AND(ISNUMBER(O16),ISNUMBER(B16)),B16,0)+IF(AND(ISNUMBER(O17),ISNUMBER(B17)),B17,0)+IF(AND(ISNUMBER(O20),ISNUMBER(B20)),B20,0)+IF(AND(ISNUMBER(O21),ISNUMBER(B21)),B21,0)+IF(AND(ISNUMBER(O22),ISNUMBER(B22)),B22,0)+IF(AND(ISNUMBER(O23),ISNUMBER(B23)),B23,0)+IF(AND(ISNUMBER(O24),ISNUMBER(B24)),B24,0)+IF(AND(ISNUMBER(O25),ISNUMBER(B25)),B25,0)+IF(AND(ISNUMBER(O26),ISNUMBER(B26)),B26,0)+IF(AND(ISNUMBER(O29),ISNUMBER(B29)),B29,0)+IF(AND(ISNUMBER(O30),ISNUMBER(B30)),B30,0)+IF(AND(ISNUMBER(O31),ISNUMBER(B31)),B31,0)+IF(AND(ISNUMBER(O32),ISNUMBER(B32)),B32,0)+IF(AND(ISNUMBER(O33),ISNUMBER(B33)),B33,0)+IF(AND(ISNUMBER(O34),ISNUMBER(B34)),B34,0)+IF(AND(ISNUMBER(O35),ISNUMBER(B35)),B35,0)+IF(AND(ISNUMBER(O38),ISNUMBER(B38)),B38,0)+IF(AND(ISNUMBER(O39),ISNUMBER(B39)),B39,0)+IF(AND(ISNUMBER(O40),ISNUMBER(B40)),B40,0)+IF(AND(ISNUMBER(O41),ISNUMBER(B41)),B41,0)+IF(AND(ISNUMBER(O42),ISNUMBER(B42)),B42,0)+IF(AND(ISNUMBER(O43),ISNUMBER(B43)),B43,0)+IF(AND(ISNUMBER(O44),ISNUMBER(B44)),B44,0))) | U48: =IF((IF(AND(ISNUMBER(U6),ISNUMBER(B6)),B6,0)+IF(AND(ISNUMBER(U7),ISNUMBER(B7)),B7,0)+IF(AND(ISNUMBER(U8),ISNUMBER(B8)),B8,0)+IF(AND(ISNUMBER(U11),ISNUMBER(B11)),B11,0)+IF(AND(ISNUMBER(U12),ISNUMBER(B12)),B12,0)+IF(AND(ISNUMBER(U13),ISNUMBER(B13)),B13,0)+IF(AND(ISNUMBER(U14),ISNUMBER(B14)),B14,0)+IF(AND(ISNUMBER(U15),ISNUMBER(B15)),B15,0)+IF(AND(ISNUMBER(U16),ISNUMBER(B16)),B16,0)+IF(AND(ISNUMBER(U17),ISNUMBER(B17)),B17,0)+IF(AND(ISNUMBER(U20),ISNUMBER(B20)),B20,0)+IF(AND(ISNUMBER(U21),ISNUMBER(B21)),B21,0)+IF(AND(ISNUMBER(U22),ISNUMBER(B22)),B22,0)+IF(AND(ISNUMBER(U23),ISNUMBER(B23)),B23,0)+IF(AND(ISNUMBER(U24),ISNUMBER(B24)),B24,0)+IF(AND(ISNUMBER(U25),ISNUMBER(B25)),B25,0)+IF(AND(ISNUMBER(U26),ISNUMBER(B26)),B26,0)+IF(AND(ISNUMBER(U29),ISNUMBER(B29)),B29,0)+IF(AND(ISNUMBER(U30),ISNUMBER(B30)),B30,0)+IF(AND(ISNUMBER(U31),ISNUMBER(B31)),B31,0)+IF(AND(ISNUMBER(U32),ISNUMBER(B32)),B32,0)+IF(AND(ISNUMBER(U33),ISNUMBER(B33)),B33,0)+IF(AND(ISNUMBER(U34),ISNUMBER(B34)),B34,0)+IF(AND(ISNUMBER(U35),ISNUMBER(B35)),B35,0)+IF(AND(ISNUMBER(U38),ISNUMBER(B38)),B38,0)+IF(AND(ISNUMBER(U39),ISNUMBER(B39)),B39,0)+IF(AND(ISNUMBER(U40),ISNUMBER(B40)),B40,0)+IF(AND(ISNUMBER(U41),ISNUMBER(B41)),B41,0)+IF(AND(ISNUMBER(U42),ISNUMBER(B42)),B42,0)+IF(AND(ISNUMBER(U43),ISNUMBER(B43)),B43,0)+IF(AND(ISNUMBER(U44),ISNUMBER(B44)),B44,0))=0,"",(IF(AND(ISNUMBER(U6),ISNUMBER(B6)),U6*B6,0)+IF(AND(ISNUMBER(U7),ISNUMBER(B7)),U7*B7,0)+IF(AND(ISNUMBER(U8),ISNUMBER(B8)),U8*B8,0)+IF(AND(ISNUMBER(U11),ISNUMBER(B11)),U11*B11,0)+IF(AND(ISNUMBER(U12),ISNUMBER(B12)),U12*B12,0)+IF(AND(ISNUMBER(U13),ISNUMBER(B13)),U13*B13,0)+IF(AND(ISNUMBER(U14),ISNUMBER(B14)),U14*B14,0)+IF(AND(ISNUMBER(U15),ISNUMBER(B15)),U15*B15,0)+IF(AND(ISNUMBER(U16),ISNUMBER(B16)),U16*B16,0)+IF(AND(ISNUMBER(U17),ISNUMBER(B17)),U17*B17,0)+IF(AND(ISNUMBER(U20),ISNUMBER(B20)),U20*B20,0)+IF(AND(ISNUMBER(U21),ISNUMBER(B21)),U21*B21,0)+IF(AND(ISNUMBER(U22),ISNUMBER(B22)),U22*B22,0)+IF(AND(ISNUMBER(U23),ISNUMBER(B23)),U23*B23,0)+IF(AND(ISNUMBER(U24),ISNUMBER(B24)),U24*B24,0)+IF(AND(ISNUMBER(U25),ISNUMBER(B25)),U25*B25,0)+IF(AND(ISNUMBER(U26),ISNUMBER(B26)),U26*B26,0)+IF(AND(ISNUMBER(U29),ISNUMBER(B29)),U29*B29,0)+IF(AND(ISNUMBER(U30),ISNUMBER(B30)),U30*B30,0)+IF(AND(ISNUMBER(U31),ISNUMBER(B31)),U31*B31,0)+IF(AND(ISNUMBER(U32),ISNUMBER(B32)),U32*B32,0)+IF(AND(ISNUMBER(U33),ISNUMBER(B33)),U33*B33,0)+IF(AND(ISNUMBER(U34),ISNUMBER(B34)),U34*B34,0)+IF(AND(ISNUMBER(U35),ISNUMBER(B35)),U35*B35,0)+IF(AND(ISNUMBER(U38),ISNUMBER(B38)),U38*B38,0)+IF(AND(ISNUMBER(U39),ISNUMBER(B39)),U39*B39,0)+IF(AND(ISNUMBER(U40),ISNUMBER(B40)),U40*B40,0)+IF(AND(ISNUMBER(U41),ISNUMBER(B41)),U41*B41,0)+IF(AND(ISNUMBER(U42),ISNUMBER(B42)),U42*B42,0)+IF(AND(ISNUMBER(U43),ISNUMBER(B43)),U43*B43,0)+IF(AND(ISNUMBER(U44),ISNUMBER(B44)),U44*B44,0))/(IF(AND(ISNUMBER(U6),ISNUMBER(B6)),B6,0)+IF(AND(ISNUMBER(U7),ISNUMBER(B7)),B7,0)+IF(AND(ISNUMBER(U8),ISNUMBER(B8)),B8,0)+IF(AND(ISNUMBER(U11),ISNUMBER(B11)),B11,0)+IF(AND(ISNUMBER(U12),ISNUMBER(B12)),B12,0)+IF(AND(ISNUMBER(U13),ISNUMBER(B13)),B13,0)+IF(AND(ISNUMBER(U14),ISNUMBER(B14)),B14,0)+IF(AND(ISNUMBER(U15),ISNUMBER(B15)),B15,0)+IF(AND(ISNUMBER(U16),ISNUMBER(B16)),B16,0)+IF(AND(ISNUMBER(U17),ISNUMBER(B17)),B17,0)+IF(AND(ISNUMBER(U20),ISNUMBER(B20)),B20,0)+IF(AND(ISNUMBER(U21),ISNUMBER(B21)),B21,0)+IF(AND(ISNUMBER(U22),ISNUMBER(B22)),B22,0)+IF(AND(ISNUMBER(U23),ISNUMBER(B23)),B23,0)+IF(AND(ISNUMBER(U24),ISNUMBER(B24)),B24,0)+IF(AND(ISNUMBER(U25),ISNUMBER(B25)),B25,0)+IF(AND(ISNUMBER(U26),ISNUMBER(B26)),B26,0)+IF(AND(ISNUMBER(U29),ISNUMBER(B29)),B29,0)+IF(AND(ISNUMBER(U30),ISNUMBER(B30)),B30,0)+IF(AND(ISNUMBER(U31),ISNUMBER(B31)),B31,0)+IF(AND(ISNUMBER(U32),ISNUMBER(B32)),B32,0)+IF(AND(ISNUMBER(U33),ISNUMBER(B33)),B33,0)+IF(AND(ISNUMBER(U34),ISNUMBER(B34)),B34,0)+IF(AND(ISNUMBER(U35),ISNUMBER(B35)),B35,0)+IF(AND(ISNUMBER(U38),ISNUMBER(B38)),B38,0)+IF(AND(ISNUMBER(U39),ISNUMBER(B39)),B39,0)+IF(AND(ISNUMBER(U40),ISNUMBER(B40)),B40,0)+IF(AND(ISNUMBER(U41),ISNUMBER(B41)),B41,0)+IF(AND(ISNUMBER(U42),ISNUMBER(B42)),B42,0)+IF(AND(ISNUMBER(U43),ISNUMBER(B43)),B43,0)+IF(AND(ISNUMBER(U44),ISNUMBER(B44)),B44,0))) | W48: =IF((IF(AND(ISNUMBER(W6),ISNUMBER(B6)),B6,0)+IF(AND(ISNUMBER(W7),ISNUMBER(B7)),B7,0)+IF(AND(ISNUMBER(W8),ISNUMBER(B8)),B8,0)+IF(AND(ISNUMBER(W11),ISNUMBER(B11)),B11,0)+IF(AND(ISNUMBER(W12),ISNUMBER(B12)),B12,0)+IF(AND(ISNUMBER(W13),ISNUMBER(B13)),B13,0)+IF(AND(ISNUMBER(W14),ISNUMBER(B14)),B14,0)+IF(AND(ISNUMBER(W15),ISNUMBER(B15)),B15,0)+IF(AND(ISNUMBER(W16),ISNUMBER(B16)),B16,0)+IF(AND(ISNUMBER(W17),ISNUMBER(B17)),B17,0)+IF(AND(ISNUMBER(W20),ISNUMBER(B20)),B20,0)+IF(AND(ISNUMBER(W21),ISNUMBER(B21)),B21,0)+IF(AND(ISNUMBER(W22),ISNUMBER(B22)),B22,0)+IF(AND(ISNUMBER(W23),ISNUMBER(B23)),B23,0)+IF(AND(ISNUMBER(W24),ISNUMBER(B24)),B24,0)+IF(AND(ISNUMBER(W25),ISNUMBER(B25)),B25,0)+IF(AND(ISNUMBER(W26),ISNUMBER(B26)),B26,0)+IF(AND(ISNUMBER(W29),ISNUMBER(B29)),B29,0)+IF(AND(ISNUMBER(W30),ISNUMBER(B30)),B30,0)+IF(AND(ISNUMBER(W31),ISNUMBER(B31)),B31,0)+IF(AND(ISNUMBER(W32),ISNUMBER(B32)),B32,0)+IF(AND(ISNUMBER(W33),ISNUMBER(B33)),B33,0)+IF(AND(ISNUMBER(W34),ISNUMBER(B34)),B34,0)+IF(AND(ISNUMBER(W35),ISNUMBER(B35)),B35,0)+IF(AND(ISNUMBER(W38),ISNUMBER(B38)),B38,0)+IF(AND(ISNUMBER(W39),ISNUMBER(B39)),B39,0)+IF(AND(ISNUMBER(W40),ISNUMBER(B40)),B40,0)+IF(AND(ISNUMBER(W41),ISNUMBER(B41)),B41,0)+IF(AND(ISNUMBER(W42),ISNUMBER(B42)),B42,0)+IF(AND(ISNUMBER(W43),ISNUMBER(B43)),B43,0)+IF(AND(ISNUMBER(W44),ISNUMBER(B44)),B44,0))=0,"",(IF(AND(ISNUMBER(W6),ISNUMBER(B6)),W6*B6,0)+IF(AND(ISNUMBER(W7),ISNUMBER(B7)),W7*B7,0)+IF(AND(ISNUMBER(W8),ISNUMBER(B8)),W8*B8,0)+IF(AND(ISNUMBER(W11),ISNUMBER(B11)),W11*B11,0)+IF(AND(ISNUMBER(W12),ISNUMBER(B12)),W12*B12,0)+IF(AND(ISNUMBER(W13),ISNUMBER(B13)),W13*B13,0)+IF(AND(ISNUMBER(W14),ISNUMBER(B14)),W14*B14,0)+IF(AND(ISNUMBER(W15),ISNUMBER(B15)),W15*B15,0)+IF(AND(ISNUMBER(W16),ISNUMBER(B16)),W16*B16,0)+IF(AND(ISNUMBER(W17),ISNUMBER(B17)),W17*B17,0)+IF(AND(ISNUMBER(W20),ISNUMBER(B20)),W20*B20,0)+IF(AND(ISNUMBER(W21),ISNUMBER(B21)),W21*B21,0)+IF(AND(ISNUMBER(W22),ISNUMBER(B22)),W22*B22,0)+IF(AND(ISNUMBER(W23),ISNUMBER(B23)),W23*B23,0)+IF(AND(ISNUMBER(W24),ISNUMBER(B24)),W24*B24,0)+IF(AND(ISNUMBER(W25),ISNUMBER(B25)),W25*B25,0)+IF(AND(ISNUMBER(W26),ISNUMBER(B26)),W26*B26,0)+IF(AND(ISNUMBER(W29),ISNUMBER(B29)),W29*B29,0)+IF(AND(ISNUMBER(W30),ISNUMBER(B30)),W30*B30,0)+IF(AND(ISNUMBER(W31),ISNUMBER(B31)),W31*B31,0)+IF(AND(ISNUMBER(W32),ISNUMBER(B32)),W32*B32,0)+IF(AND(ISNUMBER(W33),ISNUMBER(B33)),W33*B33,0)+IF(AND(ISNUMBER(W34),ISNUMBER(B34)),W34*B34,0)+IF(AND(ISNUMBER(W35),ISNUMBER(B35)),W35*B35,0)+IF(AND(ISNUMBER(W38),ISNUMBER(B38)),W38*B38,0)+IF(AND(ISNUMBER(W39),ISNUMBER(B39)),W39*B39,0)+IF(AND(ISNUMBER(W40),ISNUMBER(B40)),W40*B40,0)+IF(AND(ISNUMBER(W41),ISNUMBER(B41)),W41*B41,0)+IF(AND(ISNUMBER(W42),ISNUMBER(B42)),W42*B42,0)+IF(AND(ISNUMBER(W43),ISNUMBER(B43)),W43*B43,0)+IF(AND(ISNUMBER(W44),ISNUMBER(B44)),W44*B44,0))/(IF(AND(ISNUMBER(W6),ISNUMBER(B6)),B6,0)+IF(AND(ISNUMBER(W7),ISNUMBER(B7)),B7,0)+IF(AND(ISNUMBER(W8),ISNUMBER(B8)),B8,0)+IF(AND(ISNUMBER(W11),ISNUMBER(B11)),B11,0)+IF(AND(ISNUMBER(W12),ISNUMBER(B12)),B12,0)+IF(AND(ISNUMBER(W13),ISNUMBER(B13)),B13,0)+IF(AND(ISNUMBER(W14),ISNUMBER(B14)),B14,0)+IF(AND(ISNUMBER(W15),ISNUMBER(B15)),B15,0)+IF(AND(ISNUMBER(W16),ISNUMBER(B16)),B16,0)+IF(AND(ISNUMBER(W17),ISNUMBER(B17)),B17,0)+IF(AND(ISNUMBER(W20),ISNUMBER(B20)),B20,0)+IF(AND(ISNUMBER(W21),ISNUMBER(B21)),B21,0)+IF(AND(ISNUMBER(W22),ISNUMBER(B22)),B22,0)+IF(AND(ISNUMBER(W23),ISNUMBER(B23)),B23,0)+IF(AND(ISNUMBER(W24),ISNUMBER(B24)),B24,0)+IF(AND(ISNUMBER(W25),ISNUMBER(B25)),B25,0)+IF(AND(ISNUMBER(W26),ISNUMBER(B26)),B26,0)+IF(AND(ISNUMBER(W29),ISNUMBER(B29)),B29,0)+IF(AND(ISNUMBER(W30),ISNUMBER(B30)),B30,0)+IF(AND(ISNUMBER(W31),ISNUMBER(B31)),B31,0)+IF(AND(ISNUMBER(W32),ISNUMBER(B32)),B32,0)+IF(AND(ISNUMBER(W33),ISNUMBER(B33)),B33,0)+IF(AND(ISNUMBER(W34),ISNUMBER(B34)),B34,0)+IF(AND(ISNUMBER(W35),ISNUMBER(B35)),B35,0)+IF(AND(ISNUMBER(W38),ISNUMBER(B38)),B38,0)+IF(AND(ISNUMBER(W39),ISNUMBER(B39)),B39,0)+IF(AND(ISNUMBER(W40),ISNUMBER(B40)),B40,0)+IF(AND(ISNUMBER(W41),ISNUMBER(B41)),B41,0)+IF(AND(ISNUMBER(W42),ISNUMBER(B42)),B42,0)+IF(AND(ISNUMBER(W43),ISNUMBER(B43)),B43,0)+IF(AND(ISNUMBER(W44),ISNUMBER(B44)),B44,0))) | Y48: =IF(COUNT(Y9,Y18,Y27,Y36,Y46)=0,"",SUM(Y9,Y18,Y27,Y36,Y46)) | Z48: =IF((IF(AND(ISNUMBER(Z6),ISNUMBER(B6)),B6,0)+IF(AND(ISNUMBER(Z7),ISNUMBER(B7)),B7,0)+IF(AND(ISNUMBER(Z8),ISNUMBER(B8)),B8,0)+IF(AND(ISNUMBER(Z11),ISNUMBER(B11)),B11,0)+IF(AND(ISNUMBER(Z12),ISNUMBER(B12)),B12,0)+IF(AND(ISNUMBER(Z13),ISNUMBER(B13)),B13,0)+IF(AND(ISNUMBER(Z14),ISNUMBER(B14)),B14,0)+IF(AND(ISNUMBER(Z15),ISNUMBER(B15)),B15,0)+IF(AND(ISNUMBER(Z16),ISNUMBER(B16)),B16,0)+IF(AND(ISNUMBER(Z17),ISNUMBER(B17)),B17,0)+IF(AND(ISNUMBER(Z20),ISNUMBER(B20)),B20,0)+IF(AND(ISNUMBER(Z21),ISNUMBER(B21)),B21,0)+IF(AND(ISNUMBER(Z22),ISNUMBER(B22)),B22,0)+IF(AND(ISNUMBER(Z23),ISNUMBER(B23)),B23,0)+IF(AND(ISNUMBER(Z24),ISNUMBER(B24)),B24,0)+IF(AND(ISNUMBER(Z25),ISNUMBER(B25)),B25,0)+IF(AND(ISNUMBER(Z26),ISNUMBER(B26)),B26,0)+IF(AND(ISNUMBER(Z29),ISNUMBER(B29)),B29,0)+IF(AND(ISNUMBER(Z30),ISNUMBER(B30)),B30,0)+IF(AND(ISNUMBER(Z31),ISNUMBER(B31)),B31,0)+IF(AND(ISNUMBER(Z32),ISNUMBER(B32)),B32,0)+IF(AND(ISNUMBER(Z33),ISNUMBER(B33)),B33,0)+IF(AND(ISNUMBER(Z34),ISNUMBER(B34)),B34,0)+IF(AND(ISNUMBER(Z35),ISNUMBER(B35)),B35,0)+IF(AND(ISNUMBER(Z38),ISNUMBER(B38)),B38,0)+IF(AND(ISNUMBER(Z39),ISNUMBER(B39)),B39,0)+IF(AND(ISNUMBER(Z40),ISNUMBER(B40)),B40,0)+IF(AND(ISNUMBER(Z41),ISNUMBER(B41)),B41,0)+IF(AND(ISNUMBER(Z42),ISNUMBER(B42)),B42,0)+IF(AND(ISNUMBER(Z43),ISNUMBER(B43)),B43,0)+IF(AND(ISNUMBER(Z44),ISNUMBER(B44)),B44,0))=0,"",(IF(AND(ISNUMBER(Z6),ISNUMBER(B6)),Z6*B6,0)+IF(AND(ISNUMBER(Z7),ISNUMBER(B7)),Z7*B7,0)+IF(AND(ISNUMBER(Z8),ISNUMBER(B8)),Z8*B8,0)+IF(AND(ISNUMBER(Z11),ISNUMBER(B11)),Z11*B11,0)+IF(AND(ISNUMBER(Z12),ISNUMBER(B12)),Z12*B12,0)+IF(AND(ISNUMBER(Z13),ISNUMBER(B13)),Z13*B13,0)+IF(AND(ISNUMBER(Z14),ISNUMBER(B14)),Z14*B14,0)+IF(AND(ISNUMBER(Z15),ISNUMBER(B15)),Z15*B15,0)+IF(AND(ISNUMBER(Z16),ISNUMBER(B16)),Z16*B16,0)+IF(AND(ISNUMBER(Z17),ISNUMBER(B17)),Z17*B17,0)+IF(AND(ISNUMBER(Z20),ISNUMBER(B20)),Z20*B20,0)+IF(AND(ISNUMBER(Z21),ISNUMBER(B21)),Z21*B21,0)+IF(AND(ISNUMBER(Z22),ISNUMBER(B22)),Z22*B22,0)+IF(AND(ISNUMBER(Z23),ISNUMBER(B23)),Z23*B23,0)+IF(AND(ISNUMBER(Z24),ISNUMBER(B24)),Z24*B24,0)+IF(AND(ISNUMBER(Z25),ISNUMBER(B25)),Z25*B25,0)+IF(AND(ISNUMBER(Z26),ISNUMBER(B26)),Z26*B26,0)+IF(AND(ISNUMBER(Z29),ISNUMBER(B29)),Z29*B29,0)+IF(AND(ISNUMBER(Z30),ISNUMBER(B30)),Z30*B30,0)+IF(AND(ISNUMBER(Z31),ISNUMBER(B31)),Z31*B31,0)+IF(AND(ISNUMBER(Z32),ISNUMBER(B32)),Z32*B32,0)+IF(AND(ISNUMBER(Z33),ISNUMBER(B33)),Z33*B33,0)+IF(AND(ISNUMBER(Z34),ISNUMBER(B34)),Z34*B34,0)+IF(AND(ISNUMBER(Z35),ISNUMBER(B35)),Z35*B35,0)+IF(AND(ISNUMBER(Z38),ISNUMBER(B38)),Z38*B38,0)+IF(AND(ISNUMBER(Z39),ISNUMBER(B39)),Z39*B39,0)+IF(AND(ISNUMBER(Z40),ISNUMBER(B40)),Z40*B40,0)+IF(AND(ISNUMBER(Z41),ISNUMBER(B41)),Z41*B41,0)+IF(AND(ISNUMBER(Z42),ISNUMBER(B42)),Z42*B42,0)+IF(AND(ISNUMBER(Z43),ISNUMBER(B43)),Z43*B43,0)+IF(AND(ISNUMBER(Z44),ISNUMBER(B44)),Z44*B44,0))/(IF(AND(ISNUMBER(Z6),ISNUMBER(B6)),B6,0)+IF(AND(ISNUMBER(Z7),ISNUMBER(B7)),B7,0)+IF(AND(ISNUMBER(Z8),ISNUMBER(B8)),B8,0)+IF(AND(ISNUMBER(Z11),ISNUMBER(B11)),B11,0)+IF(AND(ISNUMBER(Z12),ISNUMBER(B12)),B12,0)+IF(AND(ISNUMBER(Z13),ISNUMBER(B13)),B13,0)+IF(AND(ISNUMBER(Z14),ISNUMBER(B14)),B14,0)+IF(AND(ISNUMBER(Z15),ISNUMBER(B15)),B15,0)+IF(AND(ISNUMBER(Z16),ISNUMBER(B16)),B16,0)+IF(AND(ISNUMBER(Z17),ISNUMBER(B17)),B17,0)+IF(AND(ISNUMBER(Z20),ISNUMBER(B20)),B20,0)+IF(AND(ISNUMBER(Z21),ISNUMBER(B21)),B21,0)+IF(AND(ISNUMBER(Z22),ISNUMBER(B22)),B22,0)+IF(AND(ISNUMBER(Z23),ISNUMBER(B23)),B23,0)+IF(AND(ISNUMBER(Z24),ISNUMBER(B24)),B24,0)+IF(AND(ISNUMBER(Z25),ISNUMBER(B25)),B25,0)+IF(AND(ISNUMBER(Z26),ISNUMBER(B26)),B26,0)+IF(AND(ISNUMBER(Z29),ISNUMBER(B29)),B29,0)+IF(AND(ISNUMBER(Z30),ISNUMBER(B30)),B30,0)+IF(AND(ISNUMBER(Z31),ISNUMBER(B31)),B31,0)+IF(AND(ISNUMBER(Z32),ISNUMBER(B32)),B32,0)+IF(AND(ISNUMBER(Z33),ISNUMBER(B33)),B33,0)+IF(AND(ISNUMBER(Z34),ISNUMBER(B34)),B34,0)+IF(AND(ISNUMBER(Z35),ISNUMBER(B35)),B35,0)+IF(AND(ISNUMBER(Z38),ISNUMBER(B38)),B38,0)+IF(AND(ISNUMBER(Z39),ISNUMBER(B39)),B39,0)+IF(AND(ISNUMBER(Z40),ISNUMBER(B40)),B40,0)+IF(AND(ISNUMBER(Z41),ISNUMBER(B41)),B41,0)+IF(AND(ISNUMBER(Z42),ISNUMBER(B42)),B42,0)+IF(AND(ISNUMBER(Z43),ISNUMBER(B43)),B43,0)+IF(AND(ISNUMBER(Z44),ISNUMBER(B44)),B44,0))) | AB48: =IF((IF(AND(ISNUMBER(AB6),ISNUMBER(B6)),B6,0)+IF(AND(ISNUMBER(AB7),ISNUMBER(B7)),B7,0)+IF(AND(ISNUMBER(AB8),ISNUMBER(B8)),B8,0)+IF(AND(ISNUMBER(AB11),ISNUMBER(B11)),B11,0)+IF(AND(ISNUMBER(AB12),ISNUMBER(B12)),B12,0)+IF(AND(ISNUMBER(AB13),ISNUMBER(B13)),B13,0)+IF(AND(ISNUMBER(AB14),ISNUMBER(B14)),B14,0)+IF(AND(ISNUMBER(AB15),ISNUMBER(B15)),B15,0)+IF(AND(ISNUMBER(AB16),ISNUMBER(B16)),B16,0)+IF(AND(ISNUMBER(AB17),ISNUMBER(B17)),B17,0)+IF(AND(ISNUMBER(AB20),ISNUMBER(B20)),B20,0)+IF(AND(ISNUMBER(AB21),ISNUMBER(B21)),B21,0)+IF(AND(ISNUMBER(AB22),ISNUMBER(B22)),B22,0)+IF(AND(ISNUMBER(AB23),ISNUMBER(B23)),B23,0)+IF(AND(ISNUMBER(AB24),ISNUMBER(B24)),B24,0)+IF(AND(ISNUMBER(AB25),ISNUMBER(B25)),B25,0)+IF(AND(ISNUMBER(AB26),ISNUMBER(B26)),B26,0)+IF(AND(ISNUMBER(AB29),ISNUMBER(B29)),B29,0)+IF(AND(ISNUMBER(AB30),ISNUMBER(B30)),B30,0)+IF(AND(ISNUMBER(AB31),ISNUMBER(B31)),B31,0)+IF(AND(ISNUMBER(AB32),ISNUMBER(B32)),B32,0)+IF(AND(ISNUMBER(AB33),ISNUMBER(B33)),B33,0)+IF(AND(ISNUMBER(AB34),ISNUMBER(B34)),B34,0)+IF(AND(ISNUMBER(AB35),ISNUMBER(B35)),B35,0)+IF(AND(ISNUMBER(AB38),ISNUMBER(B38)),B38,0)+IF(AND(ISNUMBER(AB39),ISNUMBER(B39)),B39,0)+IF(AND(ISNUMBER(AB40),ISNUMBER(B40)),B40,0)+IF(AND(ISNUMBER(AB41),ISNUMBER(B41)),B41,0)+IF(AND(ISNUMBER(AB42),ISNUMBER(B42)),B42,0)+IF(AND(ISNUMBER(AB43),ISNUMBER(B43)),B43,0)+IF(AND(ISNUMBER(AB44),ISNUMBER(B44)),B44,0))=0,"",(IF(AND(ISNUMBER(AB6),ISNUMBER(B6)),AB6*B6,0)+IF(AND(ISNUMBER(AB7),ISNUMBER(B7)),AB7*B7,0)+IF(AND(ISNUMBER(AB8),ISNUMBER(B8)),AB8*B8,0)+IF(AND(ISNUMBER(AB11),ISNUMBER(B11)),AB11*B11,0)+IF(AND(ISNUMBER(AB12),ISNUMBER(B12)),AB12*B12,0)+IF(AND(ISNUMBER(AB13),ISNUMBER(B13)),AB13*B13,0)+IF(AND(ISNUMBER(AB14),ISNUMBER(B14)),AB14*B14,0)+IF(AND(ISNUMBER(AB15),ISNUMBER(B15)),AB15*B15,0)+IF(AND(ISNUMBER(AB16),ISNUMBER(B16)),AB16*B16,0)+IF(AND(ISNUMBER(AB17),ISNUMBER(B17)),AB17*B17,0)+IF(AND(ISNUMBER(AB20),ISNUMBER(B20)),AB20*B20,0)+IF(AND(ISNUMBER(AB21),ISNUMBER(B21)),AB21*B21,0)+IF(AND(ISNUMBER(AB22),ISNUMBER(B22)),AB22*B22,0)+IF(AND(ISNUMBER(AB23),ISNUMBER(B23)),AB23*B23,0)+IF(AND(ISNUMBER(AB24),ISNUMBER(B24)),AB24*B24,0)+IF(AND(ISNUMBER(AB25),ISNUMBER(B25)),AB25*B25,0)+IF(AND(ISNUMBER(AB26),ISNUMBER(B26)),AB26*B26,0)+IF(AND(ISNUMBER(AB29),ISNUMBER(B29)),AB29*B29,0)+IF(AND(ISNUMBER(AB30),ISNUMBER(B30)),AB30*B30,0)+IF(AND(ISNUMBER(AB31),ISNUMBER(B31)),AB31*B31,0)+IF(AND(ISNUMBER(AB32),ISNUMBER(B32)),AB32*B32,0)+IF(AND(ISNUMBER(AB33),ISNUMBER(B33)),AB33*B33,0)+IF(AND(ISNUMBER(AB34),ISNUMBER(B34)),AB34*B34,0)+IF(AND(ISNUMBER(AB35),ISNUMBER(B35)),AB35*B35,0)+IF(AND(ISNUMBER(AB38),ISNUMBER(B38)),AB38*B38,0)+IF(AND(ISNUMBER(AB39),ISNUMBER(B39)),AB39*B39,0)+IF(AND(ISNUMBER(AB40),ISNUMBER(B40)),AB40*B40,0)+IF(AND(ISNUMBER(AB41),ISNUMBER(B41)),AB41*B41,0)+IF(AND(ISNUMBER(AB42),ISNUMBER(B42)),AB42*B42,0)+IF(AND(ISNUMBER(AB43),ISNUMBER(B43)),AB43*B43,0)+IF(AND(ISNUMBER(AB44),ISNUMBER(B44)),AB44*B44,0))/(IF(AND(ISNUMBER(AB6),ISNUMBER(B6)),B6,0)+IF(AND(ISNUMBER(AB7),ISNUMBER(B7)),B7,0)+IF(AND(ISNUMBER(AB8),ISNUMBER(B8)),B8,0)+IF(AND(ISNUMBER(AB11),ISNUMBER(B11)),B11,0)+IF(AND(ISNUMBER(AB12),ISNUMBER(B12)),B12,0)+IF(AND(ISNUMBER(AB13),ISNUMBER(B13)),B13,0)+IF(AND(ISNUMBER(AB14),ISNUMBER(B14)),B14,0)+IF(AND(ISNUMBER(AB15),ISNUMBER(B15)),B15,0)+IF(AND(ISNUMBER(AB16),ISNUMBER(B16)),B16,0)+IF(AND(ISNUMBER(AB17),ISNUMBER(B17)),B17,0)+IF(AND(ISNUMBER(AB20),ISNUMBER(B20)),B20,0)+IF(AND(ISNUMBER(AB21),ISNUMBER(B21)),B21,0)+IF(AND(ISNUMBER(AB22),ISNUMBER(B22)),B22,0)+IF(AND(ISNUMBER(AB23),ISNUMBER(B23)),B23,0)+IF(AND(ISNUMBER(AB24),ISNUMBER(B24)),B24,0)+IF(AND(ISNUMBER(AB25),ISNUMBER(B25)),B25,0)+IF(AND(ISNUMBER(AB26),ISNUMBER(B26)),B26,0)+IF(AND(ISNUMBER(AB29),ISNUMBER(B29)),B29,0)+IF(AND(ISNUMBER(AB30),ISNUMBER(B30)),B30,0)+IF(AND(ISNUMBER(AB31),ISNUMBER(B31)),B31,0)+IF(AND(ISNUMBER(AB32),ISNUMBER(B32)),B32,0)+IF(AND(ISNUMBER(AB33),ISNUMBER(B33)),B33,0)+IF(AND(ISNUMBER(AB34),ISNUMBER(B34)),B34,0)+IF(AND(ISNUMBER(AB35),ISNUMBER(B35)),B35,0)+IF(AND(ISNUMBER(AB38),ISNUMBER(B38)),B38,0)+IF(AND(ISNUMBER(AB39),ISNUMBER(B39)),B39,0)+IF(AND(ISNUMBER(AB40),ISNUMBER(B40)),B40,0)+IF(AND(ISNUMBER(AB41),ISNUMBER(B41)),B41,0)+IF(AND(ISNUMBER(AB42),ISNUMBER(B42)),B42,0)+IF(AND(ISNUMBER(AB43),ISNUMBER(B43)),B43,0)+IF(AND(ISNUMBER(AB44),ISNUMBER(B44)),B44,0))) | AD48: =IF((IF(AND(ISNUMBER(AD6),ISNUMBER(B6)),B6,0)+IF(AND(ISNUMBER(AD7),ISNUMBER(B7)),B7,0)+IF(AND(ISNUMBER(AD8),ISNUMBER(B8)),B8,0)+IF(AND(ISNUMBER(AD11),ISNUMBER(B11)),B11,0)+IF(AND(ISNUMBER(AD12),ISNUMBER(B12)),B12,0)+IF(AND(ISNUMBER(AD13),ISNUMBER(B13)),B13,0)+IF(AND(ISNUMBER(AD14),ISNUMBER(B14)),B14,0)+IF(AND(ISNUMBER(AD15),ISNUMBER(B15)),B15,0)+IF(AND(ISNUMBER(AD16),ISNUMBER(B16)),B16,0)+IF(AND(ISNUMBER(AD17),ISNUMBER(B17)),B17,0)+IF(AND(ISNUMBER(AD20),ISNUMBER(B20)),B20,0)+IF(AND(ISNUMBER(AD21),ISNUMBER(B21)),B21,0)+IF(AND(ISNUMBER(AD22),ISNUMBER(B22)),B22,0)+IF(AND(ISNUMBER(AD23),ISNUMBER(B23)),B23,0)+IF(AND(ISNUMBER(AD24),ISNUMBER(B24)),B24,0)+IF(AND(ISNUMBER(AD25),ISNUMBER(B25)),B25,0)+IF(AND(ISNUMBER(AD26),ISNUMBER(B26)),B26,0)+IF(AND(ISNUMBER(AD29),ISNUMBER(B29)),B29,0)+IF(AND(ISNUMBER(AD30),ISNUMBER(B30)),B30,0)+IF(AND(ISNUMBER(AD31),ISNUMBER(B31)),B31,0)+IF(AND(ISNUMBER(AD32),ISNUMBER(B32)),B32,0)+IF(AND(ISNUMBER(AD33),ISNUMBER(B33)),B33,0)+IF(AND(ISNUMBER(AD34),ISNUMBER(B34)),B34,0)+IF(AND(ISNUMBER(AD35),ISNUMBER(B35)),B35,0)+IF(AND(ISNUMBER(AD38),ISNUMBER(B38)),B38,0)+IF(AND(ISNUMBER(AD39),ISNUMBER(B39)),B39,0)+IF(AND(ISNUMBER(AD40),ISNUMBER(B40)),B40,0)+IF(AND(ISNUMBER(AD41),ISNUMBER(B41)),B41,0)+IF(AND(ISNUMBER(AD42),ISNUMBER(B42)),B42,0)+IF(AND(ISNUMBER(AD43),ISNUMBER(B43)),B43,0)+IF(AND(ISNUMBER(AD44),ISNUMBER(B44)),B44,0))=0,"",(IF(AND(ISNUMBER(AD6),ISNUMBER(B6)),AD6*B6,0)+IF(AND(ISNUMBER(AD7),ISNUMBER(B7)),AD7*B7,0)+IF(AND(ISNUMBER(AD8),ISNUMBER(B8)),AD8*B8,0)+IF(AND(ISNUMBER(AD11),ISNUMBER(B11)),AD11*B11,0)+IF(AND(ISNUMBER(AD12),ISNUMBER(B12)),AD12*B12,0)+IF(AND(ISNUMBER(AD13),ISNUMBER(B13)),AD13*B13,0)+IF(AND(ISNUMBER(AD14),ISNUMBER(B14)),AD14*B14,0)+IF(AND(ISNUMBER(AD15),ISNUMBER(B15)),AD15*B15,0)+IF(AND(ISNUMBER(AD16),ISNUMBER(B16)),AD16*B16,0)+IF(AND(ISNUMBER(AD17),ISNUMBER(B17)),AD17*B17,0)+IF(AND(ISNUMBER(AD20),ISNUMBER(B20)),AD20*B20,0)+IF(AND(ISNUMBER(AD21),ISNUMBER(B21)),AD21*B21,0)+IF(AND(ISNUMBER(AD22),ISNUMBER(B22)),AD22*B22,0)+IF(AND(ISNUMBER(AD23),ISNUMBER(B23)),AD23*B23,0)+IF(AND(ISNUMBER(AD24),ISNUMBER(B24)),AD24*B24,0)+IF(AND(ISNUMBER(AD25),ISNUMBER(B25)),AD25*B25,0)+IF(AND(ISNUMBER(AD26),ISNUMBER(B26)),AD26*B26,0)+IF(AND(ISNUMBER(AD29),ISNUMBER(B29)),AD29*B29,0)+IF(AND(ISNUMBER(AD30),ISNUMBER(B30)),AD30*B30,0)+IF(AND(ISNUMBER(AD31),ISNUMBER(B31)),AD31*B31,0)+IF(AND(ISNUMBER(AD32),ISNUMBER(B32)),AD32*B32,0)+IF(AND(ISNUMBER(AD33),ISNUMBER(B33)),AD33*B33,0)+IF(AND(ISNUMBER(AD34),ISNUMBER(B34)),AD34*B34,0)+IF(AND(ISNUMBER(AD35),ISNUMBER(B35)),AD35*B35,0)+IF(AND(ISNUMBER(AD38),ISNUMBER(B38)),AD38*B38,0)+IF(AND(ISNUMBER(AD39),ISNUMBER(B39)),AD39*B39,0)+IF(AND(ISNUMBER(AD40),ISNUMBER(B40)),AD40*B40,0)+IF(AND(ISNUMBER(AD41),ISNUMBER(B41)),AD41*B41,0)+IF(AND(ISNUMBER(AD42),ISNUMBER(B42)),AD42*B42,0)+IF(AND(ISNUMBER(AD43),ISNUMBER(B43)),AD43*B43,0)+IF(AND(ISNUMBER(AD44),ISNUMBER(B44)),AD44*B44,0))/(IF(AND(ISNUMBER(AD6),ISNUMBER(B6)),B6,0)+IF(AND(ISNUMBER(AD7),ISNUMBER(B7)),B7,0)+IF(AND(ISNUMBER(AD8),ISNUMBER(B8)),B8,0)+IF(AND(ISNUMBER(AD11),ISNUMBER(B11)),B11,0)+IF(AND(ISNUMBER(AD12),ISNUMBER(B12)),B12,0)+IF(AND(ISNUMBER(AD13),ISNUMBER(B13)),B13,0)+IF(AND(ISNUMBER(AD14),ISNUMBER(B14)),B14,0)+IF(AND(ISNUMBER(AD15),ISNUMBER(B15)),B15,0)+IF(AND(ISNUMBER(AD16),ISNUMBER(B16)),B16,0)+IF(AND(ISNUMBER(AD17),ISNUMBER(B17)),B17,0)+IF(AND(ISNUMBER(AD20),ISNUMBER(B20)),B20,0)+IF(AND(ISNUMBER(AD21),ISNUMBER(B21)),B21,0)+IF(AND(ISNUMBER(AD22),ISNUMBER(B22)),B22,0)+IF(AND(ISNUMBER(AD23),ISNUMBER(B23)),B23,0)+IF(AND(ISNUMBER(AD24),ISNUMBER(B24)),B24,0)+IF(AND(ISNUMBER(AD25),ISNUMBER(B25)),B25,0)+IF(AND(ISNUMBER(AD26),ISNUMBER(B26)),B26,0)+IF(AND(ISNUMBER(AD29),ISNUMBER(B29)),B29,0)+IF(AND(ISNUMBER(AD30),ISNUMBER(B30)),B30,0)+IF(AND(ISNUMBER(AD31),ISNUMBER(B31)),B31,0)+IF(AND(ISNUMBER(AD32),ISNUMBER(B32)),B32,0)+IF(AND(ISNUMBER(AD33),ISNUMBER(B33)),B33,0)+IF(AND(ISNUMBER(AD34),ISNUMBER(B34)),B34,0)+IF(AND(ISNUMBER(AD35),ISNUMBER(B35)),B35,0)+IF(AND(ISNUMBER(AD38),ISNUMBER(B38)),B38,0)+IF(AND(ISNUMBER(AD39),ISNUMBER(B39)),B39,0)+IF(AND(ISNUMBER(AD40),ISNUMBER(B40)),B40,0)+IF(AND(ISNUMBER(AD41),ISNUMBER(B41)),B41,0)+IF(AND(ISNUMBER(AD42),ISNUMBER(B42)),B42,0)+IF(AND(ISNUMBER(AD43),ISNUMBER(B43)),B43,0)+IF(AND(ISNUMBER(AD44),ISNUMBER(B44)),B44,0))) | AF48: =IF(OR(NOT(ISNUMBER(B48)),B48=0),"",AG48/B48) | AG48: =IF(COUNT(AG9,AG18,AG27,AG36,AG46)=0,"",SUM(AG9,AG18,AG27,AG36,AG46))

Sheet Provincia Venta Diaria
A1: DÍA | B1: San Luis | J1: San Luis CASA | K1: San Luis COMISIONISTA
A2: 1
A3: 2
A4: 3
A5: 4
A6: 5
A7: 6
A8: 7
A9: 8
A10: 9
A11: 10
A12: 11
A13: 12 | B13: 0 | J13: 0 | K13: 0
A14: 13 | B14: 0 | J14: 0 | K14: 0
A15: 14 | B15: 0 | J15: 0 | K15: 0
A16: 15 | B16: 0 | J16: 0 | K16: 0
A17: 16 | B17: 0 | J17: 0 | K17: 0
A18: 17 | B18: 0 | J18: 0 | K18: 0
A19: 18 | B19: 0 | J19: 0 | K19: 0
A20: 19 | B20: 0 | J20: 0 | K20: 0
A21: 20 | B21: 0 | J21: 0 | K21: 0
A22: 21 | B22: 0 | J22: 0 | K22: 0
A23: 22 | B23: 0 | J23: 0 | K23: 0
A24: 23 | B24: 0 | J24: 0 | K24: 0
... A32: 31 | B32: 0 | J32: 0 | K32: 0
A34: ACUM | B34: 0 | J34: 0 | K34: 0
A35: PROM | B35: 0 | J35: 0 | K35: 0
A36: PROY | B36: 10
A37: Comp
A38: Dif Comp

Sheet Provincia Comisiones
A1: DÍA | B1: San Luis | J1: San Luis CASA | K1: San Luis COMISIONISTA
A2: 1
A3: 2
A4: 3
A5: 4
A6: 5
A7: 6
A8: 7
A9: 8
A10: 9
A11: 10
A12: 11
A13: 12 | B13: 0 | J13: 0 | K13: 0
A14: 13 | B14: 0 | J14: 0 | K14: 0
A15: 14 | B15: 0 | J15: 0 | K15: 0
A16: 15 | B16: 0 | J16: 0 | K16: 0
A17: 16 | B17: 0 | J17: 0 | K17: 0
A18: 17 | B18: 0 | J18: 0 | K18: 0
A19: 18 | B19: 0 | J19: 0 | K19: 0
A20: 19 | B20: 0 | J20: 0 | K20: 0
A21: 20 | B21: 0 | J21: 0 | K21: 0
A22: 21 | B22: 0 | J22: 0 | K22: 0
A23: 22 | B23: 0 | J23: 0 | K23: 0
A24: 23 | B24: 0 | J24: 0 | K24: 0
... A32: 31 | B32: 0 | J32: 0 | K32: 0
A34: ACUM

Sheet PRECIO
A1: Fecha | B1: PRECIO
A2: 46296 | B2: 10.5
A3: 46297 | B3: 10.5
A4: 46298 | B4: 10.5
A5: 46299 | B5: 10.5
A6: 46300 | B6: 10.5
A7: 46301 | B7: 10.5
A8: 46302 | B8: 10.5
A9: 46303 | B9: 10.5
A10: 46304 | B10: 10.5
A11: 46305 | B11: 10.5
A12: 46306 | B12: 10.5
A13: 46307 | B13: 10.5
... A32: 46326 | B32: 10.5

Sheet CONTROL DE COMPRAS
A1: CONTROL DE COMPRAS | U1: 2026
A2: PLANTA SAN LUIS | T2: MES | U2: OCTUBRE
B3: TARIFA 1.23 | O3: VALOR DEL FLETE SEGÚN ORIGEN
A4: FECHA | B4: PEMEX TUXPAN | F4: CONSOLIDADO | J4: HG EN KILOS | O4: PEMEX TUXPAN | S4: CONSOLIDADO
B5: COMPRA KG | C5: COSTO KG | D5: IMPORTE | F5: COMPRA KG | G5: COSTO KG | H5: IMPORTE | J5: COSTO | K5: HG EN KILOS | L5: IMPORTE | O5: COMPRA KG | P5: TARIFA | Q5: IMPORTE | S5: COMPRA KG | T5: TARIFA | U5: IMPORTE
A6: TOTAL MES | B6: 310 | C6: 12 | D6: 3720 | F6: 310 | G6: 12 | H6: 3720 | J6: 13.23 | K6: -220 | L6: 0 | O6: 310 | P6: 1.23 | Q6: 381.3 | S6: 310 | T6: 1.23 | U6: 381.3

Sheet Pronostico
A1: San Luis — venta (ton) 2026-10 | K1: San Luis — descuento ($/kg) 2026-10
A4: Semana (año) | B4: Lun | C4: Mar | D4: Mié | E4: Jue | F4: Vie | G4: Sáb | H4: Dom | I4: Total semana | K4: Semana (año) | L4: Lun | M4: Mar | N4: Mié | O4: Jue | P4: Vie | Q4: Sáb | R4: Dom | S4: Total semana | T4: Desc /kg
A5: Semana 38 (14/09–20/09) | I5: 0 | K5: Semana 38 (14/09–20/09)
A6: Semana 39 (21/09–27/09) | I6: 0 | K6: Semana 39 (21/09–27/09)
A7: Semana 40 (28/09–04/10) | I7: 0 | K7: Semana 40 (28/09–04/10)
A8: Semana 41 (05/10–11/10) | I8: 0 | K8: Semana 41 (05/10–11/10)
A9: Semana 42 (12/10–18/10) | B9: 0 | C9: 0 | D9: 0 | E9: 0 | F9: 0 | G9: 0 | H9: 0 | I9: 0 | K9: Semana 42 (12/10–18/10) | L9: 0 | M9: 0 | N9: 0 | O9: 0 | P9: 0 | Q9: 0 | R9: 0 | S9: 0
A10: Semana 43 (19/10–25/10) | B10: 0 | C10: 0 | D10: 0 | E10: 0 | F10: 0 | G10: 0 | H10: 0 | I10: 0 | K10: Semana 43 (19/10–25/10) | L10: 0 | M10: 0 | N10: 0 | O10: 0 | P10: 0 | Q10: 0 | R10: 0 | S10: 0
A11: Semana 44 (26/10–01/11) | B11: 0 | C11: 0 | D11: 0 | E11: 0 | F11: 0 | G11: 0 | I11: 0 | K11: Semana 44 (26/10–01/11) | L11: 0 | M11: 0 | N11: 0 | O11: 0 | P11: 0 | Q11: 0 | S11: 0
A12: PROM mes (por día de semana) | I12: 0 | K12: PROM mes (por día de semana)
A13: TOTAL mes (por día de semana) | B13: 0 | C13: 0 | D13: 0 | E13: 0 | F13: 0 | G13: 0 | H13: 0 | I13: 0 | K13: TOTAL mes (por día de semana) | L13: 0 | M13: 0 | N13: 0 | O13: 0 | P13: 0 | Q13: 0 | R13: 0 | S13: 0
K14: PROM | S14: 0
A15: POR COMPRAR | I15: 0 | K15: POR COMPRAR | S15: 0
A16: PROY | B16: 0 | C16: 0 | D16: 0 | E16: 0 | F16: 0 | G16: 0 | H16: 0 | I16: 0 | K16: PROY | L16: 0 | M16: 0 | N16: 0 | O16: 0 | P16: 0 | Q16: 0 | R16: 0 | S16: 0

Sheet IGF Forecast
A1: OCTUBRE, 2026
A6: Empresa | B6: Venta y margen | E6: Forecast ARR | H6: Impuestos | I6: HG | K6: Planta | M6: Utilidad operación | O6: Corporativo | S6: Resultado
A7: Empresa | B7: Venta (ton) | C7: Margen ($/kg) | D7: Com. y Desc. ($/kg) | E7: Presupuesto ($/kg) | F7: Folios Aprob. ZP ($/kg) | G7: Folios carro ($/kg) | H7: Impuesto ($/kg) | I7: HG (%) | J7: HG ($/kg) | K7: Bancos Planta | L7: Prov. Planta | M7: Util. Oper. ($/kg) | N7: Util. Oper. (Importe) | O7: Gtos/Apoyos Corp | P7: Bancos Corp. | Q7: Otros Programas | R7: Inversiones | S7: Resultado ($/kg) | T7: Resultado (Importe)
A9: San Luis | B9: 10 | C9: 1
A28: Empresa | B28: Venta (ton) | C28: Margen ($/kg) | D28: Com. y Desc. ($/kg) | E28: Presupuesto ($/kg) | F28: Folios Aprob. ZP ($/kg) | G28: Folios carro ($/kg) | H28: Impuesto ($/kg) | I28: HG (%) | J28: HG ($/kg) | K28: Bancos Planta | L28: Prov. Planta | M28: Util. Oper. ($/kg) | N28: Util. Oper. (Importe) | O28: Gtos/Apoyos Corp | P28: Bancos Corp. | Q28: Otros Programas | R28: Inversiones | S28: Resultado ($/kg) | T28: Resultado (Importe)
A29: GTM San Luis | B29: =Pronostico!$I$16 | C29: =$C$9 | D29: =Pronostico!$T$16 | E29: =IF(B29=0,0,E$9*$B$9/B29) | F29: =$F$9 | I29: =IF(B29=0,0,I$9*$B$9/B29) | J29: =IF(B29=0,0,J$9*$B$9/B29) | M29: =IF(B29=0,0,M$9*$B$9/B29) | N29: =IF(B29=0,0,N$9*$B$9/B29) | O29: =IF(B29=0,0,O$9*$B$9/B29) | P29: =IF(B29=0,0,P$9*$B$9/B29)
A30: Zona Provincia | B30: =SUM(B29:B29)

Sheet Enero
A1: Real por categoría y subcategoría (venta kg y descuento $, sin proyección) | B1: Mes: 2026-01 (mes completo) | C1: Periodo: 2026-01-01 a 2026-01-31 · Fuente: BD (arr)
A2: Regla: SUM(kg) y SUM(monto descuento) por planta/categoría/subcategoría en el rango; descuentos asignados con arr.cliente_categoria_mes del mes correspondiente.
A4: Planta | B4: Categoría | C4: Subcategoría | D4: Kg Acumulado | E4: Descuento $ Acumulado | F4: Desc $/kg Acumulado
A5: San Luis | D5: 0 | E5: -7

Sheet Febrero
A1: Real por categoría y subcategoría (venta kg y descuento $, sin proyección) | B1: Mes: 2026-02 (mes completo) | C1: Periodo: 2026-02-01 a 2026-02-28 · Fuente: BD (arr)
A2: Regla: SUM(kg) y SUM(monto descuento) por planta/categoría/subcategoría en el rango; descuentos asignados con arr.cliente_categoria_mes del mes correspondiente.
A4: Planta | B4: Categoría | C4: Subcategoría | D4: Kg Acumulado | E4: Descuento $ Acumulado | F4: Desc $/kg Acumulado
A5: San Luis | D5: 0 | E5: -7

Sheet Marzo
A1: Real por categoría y subcategoría (venta kg y descuento $, sin proyección) | B1: Mes: 2026-03 (mes completo) | C1: Periodo: 2026-03-01 a 2026-03-31 · Fuente: BD (arr)
A2: Regla: SUM(kg) y SUM(monto descuento) por planta/categoría/subcategoría en el rango; descuentos asignados con arr.cliente_categoria_mes del mes correspondiente.
A4: Planta | B4: Categoría | C4: Subcategoría | D4: Kg Acumulado | E4: Descuento $ Acumulado | F4: Desc $/kg Acumulado
A5: San Luis | D5: 0 | E5: -7

Sheet Abril
A1: Real por categoría y subcategoría (venta kg y descuento $, sin proyección) | B1: Mes: 2026-04 (mes completo) | C1: Periodo: 2026-04-01 a 2026-04-30 · Fuente: BD (arr)
A2: Regla: SUM(kg) y SUM(monto descuento) por planta/categoría/subcategoría en el rango; descuentos asignados con arr.cliente_categoria_mes del mes correspondiente.
A4: Planta | B4: Categoría | C4: Subcategoría | D4: Kg Acumulado | E4: Descuento $ Acumulado | F4: Desc $/kg Acumulado
A5: San Luis | D5: 0 | E5: -7

Sheet Mayo
A1: Real por categoría y subcategoría (venta kg y descuento $, sin proyección) | B1: Mes: 2026-05 (mes completo) | C1: Periodo: 2026-05-01 a 2026-05-31 · Fuente: BD (arr)
A2: Regla: SUM(kg) y SUM(monto descuento) por planta/categoría/subcategoría en el rango; descuentos asignados con arr.cliente_categoria_mes del mes correspondiente.
A4: Planta | B4: Categoría | C4: Subcategoría | D4: Kg Acumulado | E4: Descuento $ Acumulado | F4: Desc $/kg Acumulado
A5: San Luis | D5: 0 | E5: -7

Sheet Clientes desc mes
A1: Clientes por planta — descuento del mes ($/kg) | B1: 2026-10 | C1: Filtro planta: San Luis
A2: Descuento $/kg = |SUM(descuento MXN)| / SUM(kg) del mes (calendario).
A3: Kg mes (proyectado) = kg real × factor por planta. Factor = total forecast mensual (objetivo, mismo que Proy cat-sub Forecast para 2026-10) / Σ kg real clientes de esa planta. Referencia corte: 2026-10-12.
A4: Estatus vs mes anterior: Nuevo, Dejó de comprar, Aumentó, Disminuyó, Sin cambio (comparación de kg del mes calendario).
A6: Planta | B6: Cliente | C6: Categoría | D6: Subcategoría | E6: Kg mes (real) | F6: Kg mes (proyectado) | G6: Descuento MXN mes | H6: Descuento $/kg mes | I6: Estatus
A7: (sin datos) | E7: 0 | F7: 0 | G7: 0

Sheet Clientes desc Enero
A1: Clientes por planta — descuento del mes ($/kg) — mes histórico (real) | B1: 2026-01 | C1: Filtro planta: San Luis
A2: Descuento $/kg = |SUM(descuento MXN)| / SUM(kg) del mes (calendario).
A3: Kg mes (real) = SUM(kg) en arr.ventas_diarias_cliente del mes calendario 2026-01 (mes ya concluido, sin proyección).
A4: Estatus vs mes anterior: Nuevo, Dejó de comprar, Aumentó, Disminuyó, Sin cambio (comparación de kg del mes calendario).
A6: Planta | B6: Cliente | C6: Categoría | D6: Subcategoría | E6: Kg mes (real) | F6: Descuento MXN mes | G6: Descuento $/kg mes | H6: Estatus
A7: (sin datos) | E7: 0 | F7: 0

Sheet Clientes desc Febrero
A1: Clientes por planta — descuento del mes ($/kg) — mes histórico (real) | B1: 2026-02 | C1: Filtro planta: San Luis
A2: Descuento $/kg = |SUM(descuento MXN)| / SUM(kg) del mes (calendario).
A3: Kg mes (real) = SUM(kg) en arr.ventas_diarias_cliente del mes calendario 2026-02 (mes ya concluido, sin proyección).
A4: Estatus vs mes anterior: Nuevo, Dejó de comprar, Aumentó, Disminuyó, Sin cambio (comparación de kg del mes calendario).
A6: Planta | B6: Cliente | C6: Categoría | D6: Subcategoría | E6: Kg mes (real) | F6: Descuento MXN mes | G6: Descuento $/kg mes | H6: Estatus
A7: (sin datos) | E7: 0 | F7: 0

Sheet Clientes desc Marzo
A1: Clientes por planta — descuento del mes ($/kg) — mes histórico (real) | B1: 2026-03 | C1: Filtro planta: San Luis
A2: Descuento $/kg = |SUM(descuento MXN)| / SUM(kg) del mes (calendario).
A3: Kg mes (real) = SUM(kg) en arr.ventas_diarias_cliente del mes calendario 2026-03 (mes ya concluido, sin proyección).
A4: Estatus vs mes anterior: Nuevo, Dejó de comprar, Aumentó, Disminuyó, Sin cambio (comparación de kg del mes calendario).
A6: Planta | B6: Cliente | C6: Categoría | D6: Subcategoría | E6: Kg mes (real) | F6: Descuento MXN mes | G6: Descuento $/kg mes | H6: Estatus
A7: (sin datos) | E7: 0 | F7: 0

Sheet Clientes desc Abril
A1: Clientes por planta — descuento del mes ($/kg) — mes histórico (real) | B1: 2026-04 | C1: Filtro planta: San Luis
A2: Descuento $/kg = |SUM(descuento MXN)| / SUM(kg) del mes (calendario).
A3: Kg mes (real) = SUM(kg) en arr.ventas_diarias_cliente del mes calendario 2026-04 (mes ya concluido, sin proyección).
A4: Estatus vs mes anterior: Nuevo, Dejó de comprar, Aumentó, Disminuyó, Sin cambio (comparación de kg del mes calendario).
A6: Planta | B6: Cliente | C6: Categoría | D6: Subcategoría | E6: Kg mes (real) | F6: Descuento MXN mes | G6: Descuento $/kg mes | H6: Estatus
A7: (sin datos) | E7: 0 | F7: 0

Sheet Clientes desc Mayo
A1: Clientes por planta — descuento del mes ($/kg) — mes histórico (real) | B1: 2026-05 | C1: Filtro planta: San Luis
A2: Descuento $/kg = |SUM(descuento MXN)| / SUM(kg) del mes (calendario).
A3: Kg mes (real) = SUM(kg) en arr.ventas_diarias_cliente del mes calendario 2026-05 (mes ya concluido, sin proyección).
A4: Estatus vs mes anterior: Nuevo, Dejó de comprar, Aumentó, Disminuyó, Sin cambio (comparación de kg del mes calendario).
A6: Planta | B6: Cliente | C6: Categoría | D6: Subcategoría | E6: Kg mes (real) | F6: Descuento MXN mes | G6: Descuento $/kg mes | H6: Estatus
A7: (sin datos) | E7: 0 | F7: 0

Sheet Clientes desc Junio
A1: Clientes por planta — descuento del mes ($/kg) — mes histórico (real) | B1: 2026-06 | C1: Filtro planta: San Luis
A2: Descuento $/kg = |SUM(descuento MXN)| / SUM(kg) del mes (calendario).
A3: Kg mes (real) = SUM(kg) en arr.ventas_diarias_cliente del mes calendario 2026-06 (mes ya concluido, sin proyección).
A4: Estatus vs mes anterior: Nuevo, Dejó de comprar, Aumentó, Disminuyó, Sin cambio (comparación de kg del mes calendario).
A6: Planta | B6: Cliente | C6: Categoría | D6: Subcategoría | E6: Kg mes (real) | F6: Descuento MXN mes | G6: Descuento $/kg mes | H6: Estatus
A7: (sin datos) | E7: 0 | F7: 0

Sheet Clientes desc Julio
A1: Clientes por planta — descuento del mes ($/kg) — mes histórico (real) | B1: 2026-07 | C1: Filtro planta: San Luis
A2: Descuento $/kg = |SUM(descuento MXN)| / SUM(kg) del mes (calendario).
A3: Kg mes (real) = SUM(kg) en arr.ventas_diarias_cliente del mes calendario 2026-07 (mes ya concluido, sin proyección).
A4: Estatus vs mes anterior: Nuevo, Dejó de comprar, Aumentó, Disminuyó, Sin cambio (comparación de kg del mes calendario).
A6: Planta | B6: Cliente | C6: Categoría | D6: Subcategoría | E6: Kg mes (real) | F6: Descuento MXN mes | G6: Descuento $/kg mes | H6: Estatus
A7: (sin datos) | E7: 0 | F7: 0

Sheet Clientes desc Agosto
A1: Clientes por planta — descuento del mes ($/kg) — mes histórico (real) | B1: 2026-08 | C1: Filtro planta: San Luis
A2: Descuento $/kg = |SUM(descuento MXN)| / SUM(kg) del mes (calendario).
A3: Kg mes (real) = SUM(kg) en arr.ventas_diarias_cliente del mes calendario 2026-08 (mes ya concluido, sin proyección).
A4: Estatus vs mes anterior: Nuevo, Dejó de comprar, Aumentó, Disminuyó, Sin cambio (comparación de kg del mes calendario).
A6: Planta | B6: Cliente | C6: Categoría | D6: Subcategoría | E6: Kg mes (real) | F6: Descuento MXN mes | G6: Descuento $/kg mes | H6: Estatus
A7: (sin datos) | E7: 0 | F7: 0

Sheet Clientes desc Septiembre
A1: Clientes por planta — descuento del mes ($/kg) — mes histórico (real) | B1: 2026-09 | C1: Filtro planta: San Luis
A2: Descuento $/kg = |SUM(descuento MXN)| / SUM(kg) del mes (calendario).
A3: Kg mes (real) = SUM(kg) en arr.ventas_diarias_cliente del mes calendario 2026-09 (mes ya concluido, sin proyección).
A4: Estatus vs mes anterior: Nuevo, Dejó de comprar, Aumentó, Disminuyó, Sin cambio (comparación de kg del mes calendario).
A6: Planta | B6: Cliente | C6: Categoría | D6: Subcategoría | E6: Kg mes (real) | F6: Descuento MXN mes | G6: Descuento $/kg mes | H6: Estatus
A7: (sin datos) | E7: 0 | F7: 0
